Workbook

Sheet Summary
A1: Copart (NASDAQ: CPRT) - SHORT
A2: Margin Callers
A3: Horizon: Q1 FY27 through Q2 FY27; planned exit and valuation date mid-February 2027 (after Q2 FY27 results)
A5: Thesis
A6: We are short CPRT because a major insurance-customer loss is creating an FY27 earnings hole that consensus still underestimates. We model $0.37 Q1 EPS and $1.45 FY27 EPS ex-ACV versus $0.41 and $1.62–$1.65 consensus, with Q1/Q2 earnings as the discovery window.
A9: Return profile
A10: Reference price (10/1/26) | B10: =Inputs!$B$6 -> 27.29 | D10: EPS: ours vs consensus
A11: Base-case value (W2) | B11: =Valuation!$B$53 -> 23.103869 | D11: Period (ex-ACV) | E11: Ours | F11: Consensus | G11: Gap
A12: Probability-weighted value | B12: =Valuation!$B$50 -> 24.51619 | D12: Q1 FY27 vs Zacks | E12: =Consensus!B16 -> 0.36739041 | F12: =Consensus!C16 -> 0.41 | G12: =Consensus!D16 -> -0.10392583
A13: Expected short return | B13: =Valuation!$B$52 -> 0.10164201 | D13: FY27 vs S&P Global | E13: =Consensus!B18 -> 1.4520874 | F13: =Consensus!C18 -> 1.62 | G13: =Consensus!D18 -> -0.10364974
A14: Expected short return, EPS-only (no multiple change) | B14: =Valuation!$B$70 -> 0.10260038 | D14: FY27 vs Zacks | E14: =Consensus!B19 -> 1.4520874 | F14: =Consensus!C19 -> 1.65 | G14: =Consensus!D19 -> -0.11994702
A15: W4 adverse-case short loss | B15: =Valuation!$B$55 -> 0.14696287
A16: Rate-cut stress (10Y to 3.5%): short loss | B16: =Valuation!$B$65 -> 0.47072059
A18: Scenarios (Valuation sheet)
A19: World | B19: Probability | C19: FY27 EPS ex-ACV | D19: FY27 GAAP EPS | E19: NTM EPS ex-int. | F19: Justified P/E (NTM) | G19: Value, mid-Feb 27 | H19: Short return
A20: W1 Loss deepens | B20: =Valuation!B8 -> 0.2 | C20: =Valuation!B9 -> 1.2792888 | D20: =Valuation!B11 -> 1.184278 | E20: =Valuation!B24 -> 1.1492474 | F20: =Valuation!B40 -> 12.213675 | G20: =Valuation!B42 -> 17.341255 | H20: =Valuation!B44 -> 0.36455642
A21: W2 FY27 trough / FY28 normalizes | B21: =Valuation!C8 -> 0.45 | C21: =Valuation!C9 -> 1.4520874 | D21: =Valuation!C11 -> 1.3829887 | E21: =Valuation!C24 -> 1.396492 | F21: =Valuation!C40 -> 14.177774 | G21: =Valuation!C42 -> 23.103869 | H21: =Valuation!C44 -> 0.15339433
A22: W3 Cycle turns / ACV improves | B22: =Valuation!D8 -> 0.2 | C22: =Valuation!D9 -> 1.6104159 | D22: =Valuation!D11 -> 1.5672292 | E22: =Valuation!D24 -> 1.6271084 | F22: =Valuation!D40 -> 16.27169 | G22: =Valuation!D42 -> 29.780525 | H22: =Valuation!D44 -> -0.09126146
A23: W4 Street right / share recapture | B23: =Valuation!E8 -> 0.15 | C23: =Valuation!E9 -> 1.7054339 | D23: =Valuation!E11 -> 1.6622472 | E23: =Valuation!E24 -> 1.6976963 | F23: =Valuation!E40 -> 16.490521 | G23: =Valuation!E42 -> 31.300617 | H23: =Valuation!E44 -> -0.14696287
A24: Probability-weighted | G24: =Valuation!$B$50 -> 24.51619 | H24: =Valuation!$B$52 -> 0.10164201
A25: Value at mid-Feb 2027 on NTM (Q3 FY27-Q2 FY28) ex-interest EPS; P/E derived from growth, ROIC and cost of equity (year-specific payouts), not selected. Team scenario probabilities.
A26: Short returns are gross and exclude borrow fees, financing costs and transaction costs.
A27: Catalysts and falsification
A28: Mid-Nov 2026 (estimated) | B28: Q1 FY27: first full quarter reflecting the lost-customer volume impact (U.S. insurance units, OpEx/car, U.S. operating margin).
A29: Mid-Feb 2027 (estimated) | B29: Q2 FY27: second full quarter of lost volume plus first ACV GAAP contribution (model assumes closing during Q2 FY27; company guides close by CY-end 2026). Planned exit and valuation date.
A30: Falsification (Q1 FY27) | B30: Exit if U.S. insurance units are better than −6% y/y, consolidated operating margin ≥36%, or OpEx/car growth ≤ +3% (Catalysts sheet).
A32: Colour key: blue = input; black = formula; green = link to another sheet; red = negative.
A34: Chart data: FY27 quarterly EPS ($/sh), linked to Consensus and EPS_Build
A35: Quarter | B35: Zacks consensus | C35: Margin Callers ex-ACV
A36: Q1 | B36: =Consensus!C5 -> 0.41 | C36: =EPS_Build!B46 -> 0.36739041
A37: Q2 | B37: =Consensus!C6 -> 0.37 | C37: =EPS_Build!C46 -> 0.33206111
A38: Q3 | B38: =Consensus!C7 -> 0.45 | C38: =EPS_Build!D46 -> 0.39611609
A39: Q4 | B39: =Consensus!C8 -> 0.41 | C39: =EPS_Build!E46 -> 0.35651982
A41: Chart data: current-price reference line (linked to Inputs)
A42: Series label | B42: Price ($/sh) | C42: Height
A43: ="Current price "&TEXT(Inputs!$B$6,"$0.00") -> Current price $27.29 | B43: =Inputs!$B$6 -> 27.29 | C43: 0
B44: =Inputs!$B$6 -> 27.29 | C44: 1

Sheet Inputs
A1: Inputs
A2: Blue = hard-coded input; black = formula; green = link. Every input carries a source type; links and SEC accession numbers are on the Sources sheet.
A4: Market, capital structure and tax
A5: Input | B5: Value | C5: Units | D5: Source type | E5: Source / basis
A6: Share price (10/1/26 close) | B6: 27.29 | C6: $/share | D6: Secondary market data | E6: Yahoo Finance daily close, 10/1/26
A7: Diluted shares, FY27 (no net buybacks assumed) | B7: 932 | C7: m shares | D7: Primary + team estimate | E7: Q4 FY26 diluted WASO 932.1m (8-K Ex. 99.1, 9/10/26); 926.3m basic shares outstanding 9/25/26 (10-K cover) + ~5m dilution. No net FY27 buybacks assumed (cash committed to ACV); buyback risk (930m / 920m) and the earlier 940m tested in Sensitivity.
A8: Effective tax rate | B8: 0.195 | C8: % | D8: Primary-derived | E8: FY26 10-K: tax $354.6m / pre-tax $1,835.0m = 19.3%
A9: Cash + restricted cash + HTM securities, 7/31/26 | B9: 4.49 | C9: $bn | D9: Primary | E9: FY26 10-K: $1,907.9m cash, equivalents & restricted + $2,581.9m HTM
A10: Cash + securities at the valuation date (mid-Feb 2027, post-ACV) | B10: 3.08 | C10: $bn | D10: Team estimate | E10: $4.49bn − $1.90bn ACV + ~$0.49bn retained FCF (6.5 months at ~$0.91bn/yr ≈ 72% of FY26 FCF $1.27bn); no buybacks; each ±$0.2bn ≈ ±$0.21/sh
A11: FY26 interest income | B11: 181.9 | C11: $m | D11: Primary | E11: FY26 10-K segment note: interest income $181.9m
A12: Interest income per quarter before ACV close | B12: 38 | C12: $m | D12: Team estimate | E12: Q3/Q4-FY26 actual $38.8m / $39.6m; cash before the ACV payment
A14: ACV transaction timing
A15: Input | B15: Value | C15: Units | D15: Source type | E15: Source / basis
A16: Share of Q2 FY27 (Nov-Jan) with ACV consolidated | B16: 0.5 | C16: % | D16: Team estimate | E16: Model assumes closing during Q2 FY27 (base: mid-Q2, ~Dec 15); company guidance is close by calendar year-end 2026 (10-K; Q4 call). Tender (10/7) and HSR (10/13) milestones are not a close date. Early Q2 = 100%, late Q2 / CY-end = 33% (Sensitivity).
A18: Lost-customer run-rate reconciliation (Q4 FY26)
A19: Input | B19: Value | C19: Units | D19: Source type | E19: Source / basis
A20: Q4 FY26 domestic insurance assignments y/y (reported) | B20: -0.075 | C20: % | D20: Primary (SEC-filed transcript) | E20: Q4 FY26 call (9/10/26; transcript filed as Schedule TO-C Ex. 99.2): domestic insurance assignments −7.5%; CFO: U.S. insurance volumes −7.5%
A21: Q4 FY26 domestic insurance assignments y/y, excluding one lost customer | B21: 0.023 | C21: % | D21: Primary (SEC-filed transcript) | E21: Q4 FY26 call: 'with the exception of 1 single customer loss domestic insurance assignments would be up 2.3%'
A22: Observed Q4 FY26 lost-customer drag (pts) = ex-customer − reported | B22: =B21-B20 -> 0.098 | C22: pts | D22: Derived | E22: +2.3% − (−7.5%) = 9.8 pts; applied as the drag already in the Q4 FY26 base (FY26 segment table below)
A23: W2 full-run-rate drag (pts of U.S. insurance units) | B23: =-Scenarios!$C$7 -> 0.13 | C23: pts | D23: Team estimate | E23: Option A: keep the 13-pt W2 full-run-rate estimate (Scenarios)
A24: Implied share of the W2 run-rate already in Q4 FY26 = 9.8 / 13 | B24: =B22/B23 -> 0.75384615 | C24: % | D24: Derived | E24: ≈75%, replacing the v1 assumption of 60% (which did not reconcile: 9.8 / 13 ≠ 60%). Q1-Q3 FY27 carry the full drag; Q4 FY27 impact = (1 − run-rate) / (1 − 9.8%) − 1 in every world
A25: Full run-rate implied if only 60% was in Q4 FY26 = 9.8 / 0.60 | B25: =B22/0.6 -> 0.16333333 | C25: pts | D25: Derived | E25: ≈16 pts = W1. RB Global's 'probably over the last 90 days' (to 8/4/26) transition suggests ≤60% was in Copart's May-Jul quarter; W2 does not assume this. Tested in Sensitivity (10 / 13 / 16 pts).
A27: Cost of equity
A28: Input | B28: Value | C28: Units | D28: Source type | E28: Source / basis
A29: 10-year U.S. Treasury yield (risk-free) | B29: 0.0524 | C29: % | D29: Primary | E29: U.S. Treasury Daily Par Yield Curve, 10Y on 10/01/2026 = 5.24%
A30: Equity beta | B30: 0.9 | C30: x | D30: Team estimate | E30: Weekly regression of CPRT on SPY, Jul-2023 to Sep-2026 = 0.89 (team calculation); Yahoo 1.03 tested in Sensitivity
A31: Equity risk premium | B31: 0.05 | C31: % | D31: Team estimate | E31: Conventional U.S. ERP assumption; ±0.5pt ERP ≈ ±0.45pt cost of equity (Sensitivity cost-of-equity table)
A32: Terminal growth | B32: 0.03 | C32: % | D32: Team estimate | E32: ≈ long-run nominal U.S. growth; well below CPRT's FY21-FY26 net-income CAGR (~9.7%)
A33: Rate-cut stress: 10-year yield | B33: 0.035 | C33: % | D33: Team estimate | E33: Stress case only (10Y back to 3.5%)
A34: Cost of equity = risk-free + beta × ERP | B34: =B29+B30*B31 -> 0.0974 | C34: % | D34: Derived | E34: CAPM: 5.24% + 0.90 × 5.0% = 9.74%
A35: Stress cost of equity = stress risk-free + beta × ERP | B35: =B33+B30*B31 -> 0.08 | C35: % | D35: Derived | E35: 3.50% + 0.90 × 5.0% = 8.00%
A37: Operating structure (KPI model)
A38: Input | B38: Value | C38: Units | D38: Source type | E38: Source / basis
A39: U.S. insurance share of U.S. units | B39: 0.76 | C39: % | D39: Team estimate | E39: 10-K: insurers supplied 79% of vehicles company-wide; U.S. mix set slightly lower given U.S. dealer/BluCar volume
A40: Fixed share of U.S. facility costs (does not flex with units near term) | B40: 0.55 | C40: % | D40: Team estimate | E40: Q4-FY26 call: U.S. facility costs +7.7% (+14.2% per unit) while U.S. units −5.7% → majority fixed in the short run; 45% / 65% in Sensitivity
A41: U.S. non-insurance unit growth | B41: 0.03 | C41: % | D41: Team estimate | E41: Q4-FY26 U.S. non-insurance +0.2%, dealer units +5.8% (call)
A42: U.S. vehicle gross profit and G&A growth | B42: 0.05 | C42: % | D42: Team estimate | E42: FY26 U.S. G&A +3.7% (10-K segment note); ongoing investment
A43: International operating income and revenue growth | B43: 0.1 | C43: % | D43: Team estimate | E43: FY26 international op. income +8.2%; Q4 international revenue +11.7% (10-K, call)
A45: FY26 quarterly segment actuals ($m) — Primary: 10-Qs Q1-Q3 FY26; Q4 = FY26 10-K less nine months
A46: Line ($m unless stated) | B46: Q1 Aug-Oct | C46: Q2 Nov-Jan | D46: Q3 Feb-Apr | E46: Q4 May-Jul
A47: U.S. service revenue | B47: 855.5 | C47: 819.5 | D47: 895.5 | E47: 817.8
A48: U.S. vehicle sales | B48: 97.1 | C48: 102.2 | D48: 107.4 | E48: 112.5
A49: U.S. facility operations | B49: 398.5 | C49: 395.4 | D49: 419.7 | E49: 420.8
A50: U.S. cost of vehicle sales | B50: 90 | C50: 96.4 | D50: 99 | E50: 105.7
A51: U.S. G&A | B51: 89.2 | C51: 88.4 | D51: 93.7 | E51: 91.7
A52: International operating income | B52: 55.7 | C52: 47.2 | D52: 73.8 | E52: 56.8
A53: International revenue (service + vehicle sales) | B53: 202.4 | C53: 200.1 | D53: 234.2 | E53: 222
A54: Interest income | B54: 53.5 | C54: 50 | D54: 38.8 | E54: 39.6
A55: Lost-customer drag already in the FY26 quarter (pts) | B55: 0 | C55: 0 | D55: 0 | E55: =Inputs!$B$22 -> 0.098
A56: Reported FY26 diluted EPS by quarter ($/sh) | B56: 0.41 | C56: 0.36 | D56: 0.43 | E56: 0.35
A57: FY26 diluted weighted-average shares by quarter (m) | B57: 977.1 | C57: 975.1 | D57: 942.8 | E57: 932.1

Sheet Scenarios
A1: Scenarios
A2: Four economic worlds: what the market believes → KPIs → earnings → value. Blue = team estimate.
A4: Scenario drivers (all team estimates; basis in the rows below and on Sources)
A5: Driver | B5: W1 Loss deepens | C5: W2 FY27 trough / FY28 normalizes | D5: W3 Cycle turns / ACV improves | E5: W4 Street right / share recapture
A6: Underlying U.S. insurance unit growth, ex lost customer | B6: -0.02 | C6: 0.01 | D6: 0.03 | E6: 0.03
A7: Lost-customer full-run-rate drag (pts of U.S. insurance units) | B7: -0.16 | C7: -0.13 | D7: -0.1 | E7: -0.05
A8: Revenue per unit growth | B8: 0.02 | C8: 0.035 | D8: 0.05 | E8: 0.05
A9: Fixed facility cost growth | B9: 0.1 | C9: 0.07 | D9: 0.04 | E9: 0.04
A10: ACV acquired-intangible amortization per quarter ($m) | B10: 20 | C10: 15 | D10: 10 | E10: 10
A11: ACV operating income per quarter ($m) | B11: -8 | C11: -4 | D11: 0 | E11: 0
A12: Interest income per quarter after ACV close ($m) | B12: 22 | C12: 25 | D12: 28 | E12: 28
A13: FY28 ACV EPS contribution incl. amortization and forgone interest ($/sh) | B13: 0 | C13: 0.02 | D13: 0.04 | E13: 0.02
A14: Team scenario probability | B14: 0.2 | C14: 0.45 | D14: 0.2 | E14: 0.15
A15: FY28 EPS growth (core operating, ex-ACV) | B15: 0.04 | C15: 0.12 | D15: 0.18 | E15: 0.15
A16: EPS growth, 5 years after year 2 | B16: 0.03 | C16: 0.06 | D16: 0.09 | E16: 0.1
A17: Incremental ROIC | B17: 0.15 | C17: 0.2 | D17: 0.25 | E17: 0.25
A18: Probability check (must equal 100%) | B18: =SUM(B14:E14) -> 1
A20: Rationale and evidence (short; sources on Sources sheet)
A21: Item | B21: W1 Loss deepens | C21: W2 FY27 trough / FY28 normalizes | D21: W3 Cycle turns / ACV improves | E21: W4 Street right / share recapture
A22: What each world assumes (evidence) | B22: Loss broadens beyond one customer; ASP softens (Manheim −0.4% y/y mid-Sep, Cox); OpEx/car stays high (+12.7% in Q4, call). 16-pt run-rate ≈ only 60% in the Q4 FY26 base. | C22: The disclosed loss runs at its full 13-pt rate Q1-Q3 FY27 and partly laps in Q4 (~75% already in the Q4 FY26 base). Fixed costs +7%. ACV per model. | D22: Ex-customer insurance units +3% (Q4 ex-customer +2.3%, call); record second-quarter 23.3% total-loss frequency (call). | E22: Share recapture offsets most of the lost volume; published FY27 consensus roughly delivered. Team scenario based on public data only.
A23: Probability rationale (team scenario probabilities; judgmental, not objective) | B23: 20%: plausible but not base. Requires losses beyond the one disclosed customer; management described customer relationships as strong. | C23: 45%: most likely. The only disclosed loss runs at full rate until it laps in Q4 FY27; RB Global indicated substantial incremental partner volume had been transitioning over the prior ~90 days; costs are largely fixed near term (Q4 facility costs +7.7% on units −5.7%). | D23: 20%: record total-loss frequency, rising severity and pricing (U.S. insurance ASP +3.7%) offset the volume hole faster than we model. | E23: 15%: the Street is right. Published FY27 consensus ($1.62-$1.65) implies the loss is largely absorbed; CPRT has historically rebounded after large negative reactions (Checks).
A24: FY28 ACV contribution support | B24: $0.00: accretion guidance not met in FY28. | C24: +$0.02: modestly accretive, consistent with guidance (neutral in the first full year; accretive FY28 and beyond). | D24: +$0.04: synergies arrive faster than guided. | E24: +$0.02: guidance delivered.
A25: 5-year EPS growth (g) support | B25: 3%: pricing-only growth; no unit recovery. | C25: 6%: normalized low-single-digit unit growth plus pricing; below the FY21-FY26 net-income CAGR (~9.7%). | D25: 9%: close to the FY21-FY26 net-income CAGR (~9.7%). | E25: 10%: historical growth resumes.
A26: Incremental ROIC support | B26: 15%: about half of recent core ROIC; lower utilization persists. | C26: 20%: below recent core ROIC (~29-31%, FY25-FY26 NOPAT / equity ex cash & HTM), reflecting lower utilization and ACV mix. | D26: 25%: still below recent core ROIC. | E26: 25%: still below recent core ROIC.

Sheet EPS_Build
A1: FY27 EPS Build (Aug-26 to Jul-27), $m unless stated
A2: Chain: lost-customer impact → U.S. insurance units → U.S. service revenue → operating income → EPS. Model assumes closing during Q2 FY27; company guidance is close by calendar year-end 2026. Q2 ACV P&L and interest are pro-rated by the consolidated share of Q2 (Inputs). Ex-ACV and GAAP-with-ACV kept separate.
A4: W1 Loss deepens
A5: Line | B5: Q1 Aug-Oct | C5: Q2 Nov-Jan | D5: Q3 Feb-Apr | E5: Q4 May-Jul | F5: FY27
A6: Lost-customer impact vs FY26 quarter (pts) | B6: =(1+Scenarios!$B$7)/(1-Inputs!B$55)-1 -> -0.16 | C6: =(1+Scenarios!$B$7)/(1-Inputs!C$55)-1 -> -0.16 | D6: =(1+Scenarios!$B$7)/(1-Inputs!D$55)-1 -> -0.16 | E6: =(1+Scenarios!$B$7)/(1-Inputs!E$55)-1 -> -0.068736142
A7: U.S. insurance units y/y | B7: =Scenarios!$B$6+B6 -> -0.18 | C7: =Scenarios!$B$6+C6 -> -0.18 | D7: =Scenarios!$B$6+D6 -> -0.18 | E7: =Scenarios!$B$6+E6 -> -0.088736142
A8: U.S. units y/y | B8: =Inputs!$B$39*B7+(1-Inputs!$B$39)*Inputs!$B$41 -> -0.1296 | C8: =Inputs!$B$39*C7+(1-Inputs!$B$39)*Inputs!$B$41 -> -0.1296 | D8: =Inputs!$B$39*D7+(1-Inputs!$B$39)*Inputs!$B$41 -> -0.1296 | E8: =Inputs!$B$39*E7+(1-Inputs!$B$39)*Inputs!$B$41 -> -0.060239468
A9: U.S. service revenue ($m) | B9: =Inputs!B$47*(1+B8)*(1+Scenarios!$B$8) -> 759.51974 | C9: =Inputs!C$47*(1+C8)*(1+Scenarios!$B$8) -> 727.55866 | D9: =Inputs!D$47*(1+D8)*(1+Scenarios!$B$8) -> 795.03206 | E9: =Inputs!E$47*(1+E8)*(1+Scenarios!$B$8) -> 783.90689 | F9: =SUM(B9:E9) -> 3066.0174
A10: U.S. vehicle sales ($m) | B10: =Inputs!B$48*(1+Inputs!$B$42) -> 101.955 | C10: =Inputs!C$48*(1+Inputs!$B$42) -> 107.31 | D10: =Inputs!D$48*(1+Inputs!$B$42) -> 112.77 | E10: =Inputs!E$48*(1+Inputs!$B$42) -> 118.125 | F10: =SUM(B10:E10) -> 440.16
A11: U.S. vehicle gross profit ($m) | B11: =(Inputs!B$48-Inputs!B$50)*(1+Inputs!$B$42) -> 7.455 | C11: =(Inputs!C$48-Inputs!C$50)*(1+Inputs!$B$42) -> 6.09 | D11: =(Inputs!D$48-Inputs!D$50)*(1+Inputs!$B$42) -> 8.82 | E11: =(Inputs!E$48-Inputs!E$50)*(1+Inputs!$B$42) -> 7.14
A12: U.S. facility operations ($m) | B12: =Inputs!B$49*Inputs!$B$40*(1+Scenarios!$B$9)+Inputs!B$49*(1-Inputs!$B$40)*(1+B8) -> 397.17698 | C12: =Inputs!C$49*Inputs!$B$40*(1+Scenarios!$B$9)+Inputs!C$49*(1-Inputs!$B$40)*(1+C8) -> 394.08727 | D12: =Inputs!D$49*Inputs!$B$40*(1+Scenarios!$B$9)+Inputs!D$49*(1-Inputs!$B$40)*(1+D8) -> 418.3066 | E12: =Inputs!E$49*Inputs!$B$40*(1+Scenarios!$B$9)+Inputs!E$49*(1-Inputs!$B$40)*(1+E8) -> 432.53705 | F12: =SUM(B12:E12) -> 1642.1079
A13: U.S. G&A ($m) | B13: =Inputs!B$51*(1+Inputs!$B$42) -> 93.66 | C13: =Inputs!C$51*(1+Inputs!$B$42) -> 92.82 | D13: =Inputs!D$51*(1+Inputs!$B$42) -> 98.385 | E13: =Inputs!E$51*(1+Inputs!$B$42) -> 96.285 | F13: =SUM(B13:E13) -> 381.15
A14: U.S. operating income ($m) | B14: =B9+B11-B12-B13 -> 276.13776 | C14: =C9+C11-C12-C13 -> 246.74138 | D14: =D9+D11-D12-D13 -> 287.16047 | E14: =E9+E11-E12-E13 -> 262.22483 | F14: =SUM(B14:E14) -> 1072.2644
A15: U.S. operating margin | B15: =B14/(B9+B10) -> 0.32054075 | C15: =C14/(C9+C10) -> 0.29554515 | D15: =D14/(D9+D10) -> 0.31632498 | E15: =E14/(E9+E10) -> 0.29070461 | F15: =F14/(F9+F10) -> 0.30582151
A16: International operating income ($m) | B16: =Inputs!B$52*(1+Inputs!$B$43) -> 61.27 | C16: =Inputs!C$52*(1+Inputs!$B$43) -> 51.92 | D16: =Inputs!D$52*(1+Inputs!$B$43) -> 81.18 | E16: =Inputs!E$52*(1+Inputs!$B$43) -> 62.48 | F16: =SUM(B16:E16) -> 256.85
A17: International revenue ($m) | B17: =Inputs!B$53*(1+Inputs!$B$43) -> 222.64 | C17: =Inputs!C$53*(1+Inputs!$B$43) -> 220.11 | D17: =Inputs!D$53*(1+Inputs!$B$43) -> 257.62 | E17: =Inputs!E$53*(1+Inputs!$B$43) -> 244.2 | F17: =SUM(B17:E17) -> 944.57
A18: Consolidated operating margin, ex-ACV | B18: =(B14+B16)/(B9+B10+B17) -> 0.31122883 | C18: =(C14+C16)/(C9+C10+C17) -> 0.28309709 | D18: =(D14+D16)/(D9+D10+D17) -> 0.31605757 | E18: =(E14+E16)/(E9+E10+E17) -> 0.28328023 | F18: =(F14+F16)/(F9+F10+F17) -> 0.29862725
A19: Core operating EPS, ex-interest, ex-ACV ($/sh) | B19: =(B14+B16)*(1-Inputs!$B$8)/Inputs!$B$7 -> 0.29143053 | C19: =(C14+C16)*(1-Inputs!$B$8)/Inputs!$B$7 -> 0.25796396 | D19: =(D14+D16)*(1-Inputs!$B$8)/Inputs!$B$7 -> 0.31814815 | E19: =(E14+E16)*(1-Inputs!$B$8)/Inputs!$B$7 -> 0.28045857 | F19: =SUM(B19:E19) -> 1.1480012
A20: Interest income, ex-ACV case ($m) | B20: =Inputs!$B$12 -> 38 | C20: =Inputs!$B$12 -> 38 | D20: =Inputs!$B$12 -> 38 | E20: =Inputs!$B$12 -> 38 | F20: =SUM(B20:E20) -> 152
A21: EPS ex-ACV (operating thesis) | B21: =(B14+B16+B20)*(1-Inputs!$B$8)/Inputs!$B$7 -> 0.32425241 | C21: =(C14+C16+C20)*(1-Inputs!$B$8)/Inputs!$B$7 -> 0.29078585 | D21: =(D14+D16+D20)*(1-Inputs!$B$8)/Inputs!$B$7 -> 0.35097004 | E21: =(E14+E16+E20)*(1-Inputs!$B$8)/Inputs!$B$7 -> 0.31328046 | F21: =SUM(B21:E21) -> 1.2792888
A22: ACV pre-tax: operating income − amortization ($m) | B22: =0 -> 0 | C22: =Inputs!$B$16*(Scenarios!$B$11-Scenarios!$B$10) -> -14 | D22: =Scenarios!$B$11-Scenarios!$B$10 -> -28 | E22: =Scenarios!$B$11-Scenarios!$B$10 -> -28 | F22: =SUM(B22:E22) -> -70
A23: Interest income after ACV cash outflow ($m) | B23: =Inputs!$B$12 -> 38 | C23: =Inputs!$B$16*Scenarios!$B$12+(1-Inputs!$B$16)*Inputs!$B$12 -> 30 | D23: =Scenarios!$B$12 -> 22 | E23: =Scenarios!$B$12 -> 22 | F23: =SUM(B23:E23) -> 112
A24: GAAP EPS incl. ACV | B24: =(B14+B16+B22+B23)*(1-Inputs!$B$8)/Inputs!$B$7 -> 0.32425241 | C24: =(C14+C16+C22+C23)*(1-Inputs!$B$8)/Inputs!$B$7 -> 0.27178371 | D24: =(D14+D16+D22+D23)*(1-Inputs!$B$8)/Inputs!$B$7 -> 0.31296575 | E24: =(E14+E16+E22+E23)*(1-Inputs!$B$8)/Inputs!$B$7 -> 0.27527617 | F24: =SUM(B24:E24) -> 1.184278
A25: ACV EPS impact incl. forgone interest ($/sh) | B25: =B24-B21 -> 0 | C25: =C24-C21 -> -0.019002146 | D25: =D24-D21 -> -0.038004292 | E25: =E24-E21 -> -0.038004292 | F25: =SUM(B25:E25) -> -0.09501073
A26: EPS ex-interest incl. ACV (valuation base, $/sh) | B26: =(B14+B16+B22)*(1-Inputs!$B$8)/Inputs!$B$7 -> 0.29143053 | C26: =(C14+C16+C22)*(1-Inputs!$B$8)/Inputs!$B$7 -> 0.24587169 | D26: =(D14+D16+D22)*(1-Inputs!$B$8)/Inputs!$B$7 -> 0.2939636 | E26: =(E14+E16+E22)*(1-Inputs!$B$8)/Inputs!$B$7 -> 0.25627402 | F26: =SUM(B26:E26) -> 1.0875398
A29: W2 FY27 trough / FY28 normalizes
A30: Line | B30: Q1 Aug-Oct | C30: Q2 Nov-Jan | D30: Q3 Feb-Apr | E30: Q4 May-Jul | F30: FY27
A31: Lost-customer impact vs FY26 quarter (pts) | B31: =(1+Scenarios!$C$7)/(1-Inputs!B$55)-1 -> -0.13 | C31: =(1+Scenarios!$C$7)/(1-Inputs!C$55)-1 -> -0.13 | D31: =(1+Scenarios!$C$7)/(1-Inputs!D$55)-1 -> -0.13 | E31: =(1+Scenarios!$C$7)/(1-Inputs!E$55)-1 -> -0.035476718
A32: U.S. insurance units y/y | B32: =Scenarios!$C$6+B31 -> -0.12 | C32: =Scenarios!$C$6+C31 -> -0.12 | D32: =Scenarios!$C$6+D31 -> -0.12 | E32: =Scenarios!$C$6+E31 -> -0.025476718
A33: U.S. units y/y | B33: =Inputs!$B$39*B32+(1-Inputs!$B$39)*Inputs!$B$41 -> -0.084 | C33: =Inputs!$B$39*C32+(1-Inputs!$B$39)*Inputs!$B$41 -> -0.084 | D33: =Inputs!$B$39*D32+(1-Inputs!$B$39)*Inputs!$B$41 -> -0.084 | E33: =Inputs!$B$39*E32+(1-Inputs!$B$39)*Inputs!$B$41 -> -0.012162306
A34: U.S. service revenue ($m) | B34: =Inputs!B$47*(1+B33)*(1+Scenarios!$C$8) -> 811.06533 | C34: =Inputs!C$47*(1+C33)*(1+Scenarios!$C$8) -> 776.93517 | D34: =Inputs!D$47*(1+D33)*(1+Scenarios!$C$8) -> 848.98773 | E34: =Inputs!E$47*(1+E33)*(1+Scenarios!$C$8) -> 836.12854 | F34: =SUM(B34:E34) -> 3273.1168
A35: U.S. vehicle sales ($m) | B35: =Inputs!B$48*(1+Inputs!$B$42) -> 101.955 | C35: =Inputs!C$48*(1+Inputs!$B$42) -> 107.31 | D35: =Inputs!D$48*(1+Inputs!$B$42) -> 112.77 | E35: =Inputs!E$48*(1+Inputs!$B$42) -> 118.125 | F35: =SUM(B35:E35) -> 440.16
A36: U.S. vehicle gross profit ($m) | B36: =(Inputs!B$48-Inputs!B$50)*(1+Inputs!$B$42) -> 7.455 | C36: =(Inputs!C$48-Inputs!C$50)*(1+Inputs!$B$42) -> 6.09 | D36: =(Inputs!D$48-Inputs!D$50)*(1+Inputs!$B$42) -> 8.82 | E36: =(Inputs!E$48-Inputs!E$50)*(1+Inputs!$B$42) -> 7.14
A37: U.S. facility operations ($m) | B37: =Inputs!B$49*Inputs!$B$40*(1+Scenarios!$C$9)+Inputs!B$49*(1-Inputs!$B$40)*(1+B33) -> 398.77895 | C37: =Inputs!C$49*Inputs!$B$40*(1+Scenarios!$C$9)+Inputs!C$49*(1-Inputs!$B$40)*(1+C33) -> 395.67678 | D37: =Inputs!D$49*Inputs!$B$40*(1+Scenarios!$C$9)+Inputs!D$49*(1-Inputs!$B$40)*(1+D33) -> 419.99379 | E37: =Inputs!E$49*Inputs!$B$40*(1+Scenarios!$C$9)+Inputs!E$49*(1-Inputs!$B$40)*(1+E33) -> 434.69775 | F37: =SUM(B37:E37) -> 1649.1473
A38: U.S. G&A ($m) | B38: =Inputs!B$51*(1+Inputs!$B$42) -> 93.66 | C38: =Inputs!C$51*(1+Inputs!$B$42) -> 92.82 | D38: =Inputs!D$51*(1+Inputs!$B$42) -> 98.385 | E38: =Inputs!E$51*(1+Inputs!$B$42) -> 96.285 | F38: =SUM(B38:E38) -> 381.15
A39: U.S. operating income ($m) | B39: =B34+B36-B37-B38 -> 326.08138 | C39: =C34+C36-C37-C38 -> 294.52839 | D39: =D34+D36-D37-D38 -> 339.42894 | E39: =E34+E36-E37-E38 -> 312.2858 | F39: =SUM(B39:E39) -> 1272.3245
A40: U.S. operating margin | B40: =B39/(B34+B35) -> 0.3571458 | C40: =C39/(C34+C35) -> 0.33308453 | D40: =D39/(D34+D35) -> 0.35292562 | E40: =E39/(E34+E35) -> 0.32725663 | F40: =F39/(F34+F35) -> 0.34264198
A41: International operating income ($m) | B41: =Inputs!B$52*(1+Inputs!$B$43) -> 61.27 | C41: =Inputs!C$52*(1+Inputs!$B$43) -> 51.92 | D41: =Inputs!D$52*(1+Inputs!$B$43) -> 81.18 | E41: =Inputs!E$52*(1+Inputs!$B$43) -> 62.48 | F41: =SUM(B41:E41) -> 256.85
A42: International revenue ($m) | B42: =Inputs!B$53*(1+Inputs!$B$43) -> 222.64 | C42: =Inputs!C$53*(1+Inputs!$B$43) -> 220.11 | D42: =Inputs!D$53*(1+Inputs!$B$43) -> 257.62 | E42: =Inputs!E$53*(1+Inputs!$B$43) -> 244.2 | F42: =SUM(B42:E42) -> 944.57
A43: Consolidated operating margin, ex-ACV | B43: =(B39+B41)/(B34+B35+B42) -> 0.34108031 | C43: =(C39+C41)/(C34+C35+C42) -> 0.31371102 | D43: =(D39+D41)/(D34+D35+D42) -> 0.34493736 | E43: =(E39+E41)/(E34+E35+E42) -> 0.31270782 | F43: =(F39+F41)/(F34+F35+F42) -> 0.32830073
A44: Core operating EPS, ex-interest, ex-ACV ($/sh) | B44: =(B39+B41)*(1-Inputs!$B$8)/Inputs!$B$7 -> 0.33456852 | C44: =(C39+C41)*(1-Inputs!$B$8)/Inputs!$B$7 -> 0.29923922 | D44: =(D39+D41)*(1-Inputs!$B$8)/Inputs!$B$7 -> 0.3632942 | E44: =(E39+E41)*(1-Inputs!$B$8)/Inputs!$B$7 -> 0.32369793 | F44: =SUM(B44:E44) -> 1.3207999
A45: Interest income, ex-ACV case ($m) | B45: =Inputs!$B$12 -> 38 | C45: =Inputs!$B$12 -> 38 | D45: =Inputs!$B$12 -> 38 | E45: =Inputs!$B$12 -> 38 | F45: =SUM(B45:E45) -> 152
A46: EPS ex-ACV (operating thesis) | B46: =(B39+B41+B45)*(1-Inputs!$B$8)/Inputs!$B$7 -> 0.36739041 | C46: =(C39+C41+C45)*(1-Inputs!$B$8)/Inputs!$B$7 -> 0.33206111 | D46: =(D39+D41+D45)*(1-Inputs!$B$8)/Inputs!$B$7 -> 0.39611609 | E46: =(E39+E41+E45)*(1-Inputs!$B$8)/Inputs!$B$7 -> 0.35651982 | F46: =SUM(B46:E46) -> 1.4520874
A47: ACV pre-tax: operating income − amortization ($m) | B47: =0 -> 0 | C47: =Inputs!$B$16*(Scenarios!$C$11-Scenarios!$C$10) -> -9.5 | D47: =Scenarios!$C$11-Scenarios!$C$10 -> -19 | E47: =Scenarios!$C$11-Scenarios!$C$10 -> -19 | F47: =SUM(B47:E47) -> -47.5
A48: Interest income after ACV cash outflow ($m) | B48: =Inputs!$B$12 -> 38 | C48: =Inputs!$B$16*Scenarios!$C$12+(1-Inputs!$B$16)*Inputs!$B$12 -> 31.5 | D48: =Scenarios!$C$12 -> 25 | E48: =Scenarios!$C$12 -> 25 | F48: =SUM(B48:E48) -> 119.5
A49: GAAP EPS incl. ACV | B49: =(B39+B41+B47+B48)*(1-Inputs!$B$8)/Inputs!$B$7 -> 0.36739041 | C49: =(C39+C41+C47+C48)*(1-Inputs!$B$8)/Inputs!$B$7 -> 0.31824137 | D49: =(D39+D41+D47+D48)*(1-Inputs!$B$8)/Inputs!$B$7 -> 0.36847661 | E49: =(E39+E41+E47+E48)*(1-Inputs!$B$8)/Inputs!$B$7 -> 0.32888033 | F49: =SUM(B49:E49) -> 1.3829887
A50: ACV EPS impact incl. forgone interest ($/sh) | B50: =B49-B46 -> 0 | C50: =C49-C46 -> -0.013819742 | D50: =D49-D46 -> -0.027639485 | E50: =E49-E46 -> -0.027639485 | F50: =SUM(B50:E50) -> -0.069098712
A51: EPS ex-interest incl. ACV (valuation base, $/sh) | B51: =(B39+B41+B47)*(1-Inputs!$B$8)/Inputs!$B$7 -> 0.33456852 | C51: =(C39+C41+C47)*(1-Inputs!$B$8)/Inputs!$B$7 -> 0.29103375 | D51: =(D39+D41+D47)*(1-Inputs!$B$8)/Inputs!$B$7 -> 0.34688326 | E51: =(E39+E41+E47)*(1-Inputs!$B$8)/Inputs!$B$7 -> 0.30728698 | F51: =SUM(B51:E51) -> 1.2797725
A54: W3 Cycle turns / ACV improves
A55: Line | B55: Q1 Aug-Oct | C55: Q2 Nov-Jan | D55: Q3 Feb-Apr | E55: Q4 May-Jul | F55: FY27
A56: Lost-customer impact vs FY26 quarter (pts) | B56: =(1+Scenarios!$D$7)/(1-Inputs!B$55)-1 -> -0.1 | C56: =(1+Scenarios!$D$7)/(1-Inputs!C$55)-1 -> -0.1 | D56: =(1+Scenarios!$D$7)/(1-Inputs!D$55)-1 -> -0.1 | E56: =(1+Scenarios!$D$7)/(1-Inputs!E$55)-1 -> -0.0022172949
A57: U.S. insurance units y/y | B57: =Scenarios!$D$6+B56 -> -0.07 | C57: =Scenarios!$D$6+C56 -> -0.07 | D57: =Scenarios!$D$6+D56 -> -0.07 | E57: =Scenarios!$D$6+E56 -> 0.027782705
A58: U.S. units y/y | B58: =Inputs!$B$39*B57+(1-Inputs!$B$39)*Inputs!$B$41 -> -0.046 | C58: =Inputs!$B$39*C57+(1-Inputs!$B$39)*Inputs!$B$41 -> -0.046 | D58: =Inputs!$B$39*D57+(1-Inputs!$B$39)*Inputs!$B$41 -> -0.046 | E58: =Inputs!$B$39*E57+(1-Inputs!$B$39)*Inputs!$B$41 -> 0.028314856
A59: U.S. service revenue ($m) | B59: =Inputs!B$47*(1+B58)*(1+Scenarios!$D$8) -> 856.95435 | C59: =Inputs!C$47*(1+C58)*(1+Scenarios!$D$8) -> 820.89315 | D59: =Inputs!D$47*(1+D58)*(1+Scenarios!$D$8) -> 897.02235 | E59: =Inputs!E$47*(1+E58)*(1+Scenarios!$D$8) -> 883.00368 | F59: =SUM(B59:E59) -> 3457.8735
A60: U.S. vehicle sales ($m) | B60: =Inputs!B$48*(1+Inputs!$B$42) -> 101.955 | C60: =Inputs!C$48*(1+Inputs!$B$42) -> 107.31 | D60: =Inputs!D$48*(1+Inputs!$B$42) -> 112.77 | E60: =Inputs!E$48*(1+Inputs!$B$42) -> 118.125 | F60: =SUM(B60:E60) -> 440.16
A61: U.S. vehicle gross profit ($m) | B61: =(Inputs!B$48-Inputs!B$50)*(1+Inputs!$B$42) -> 7.455 | C61: =(Inputs!C$48-Inputs!C$50)*(1+Inputs!$B$42) -> 6.09 | D61: =(Inputs!D$48-Inputs!D$50)*(1+Inputs!$B$42) -> 8.82 | E61: =(Inputs!E$48-Inputs!E$50)*(1+Inputs!$B$42) -> 7.14
A62: U.S. facility operations ($m) | B62: =Inputs!B$49*Inputs!$B$40*(1+Scenarios!$D$9)+Inputs!B$49*(1-Inputs!$B$40)*(1+B58) -> 399.01805 | C62: =Inputs!C$49*Inputs!$B$40*(1+Scenarios!$D$9)+Inputs!C$49*(1-Inputs!$B$40)*(1+C58) -> 395.91402 | D62: =Inputs!D$49*Inputs!$B$40*(1+Scenarios!$D$9)+Inputs!D$49*(1-Inputs!$B$40)*(1+D58) -> 420.24561 | E62: =Inputs!E$49*Inputs!$B$40*(1+Scenarios!$D$9)+Inputs!E$49*(1-Inputs!$B$40)*(1+E58) -> 435.4193 | F62: =SUM(B62:E62) -> 1650.597
A63: U.S. G&A ($m) | B63: =Inputs!B$51*(1+Inputs!$B$42) -> 93.66 | C63: =Inputs!C$51*(1+Inputs!$B$42) -> 92.82 | D63: =Inputs!D$51*(1+Inputs!$B$42) -> 98.385 | E63: =Inputs!E$51*(1+Inputs!$B$42) -> 96.285 | F63: =SUM(B63:E63) -> 381.15
A64: U.S. operating income ($m) | B64: =B59+B61-B62-B63 -> 371.7313 | C64: =C59+C61-C62-C63 -> 338.24913 | D64: =D59+D61-D62-D63 -> 387.21174 | E64: =E59+E61-E62-E63 -> 358.43938 | F64: =SUM(B64:E64) -> 1455.6316
A65: U.S. operating margin | B65: =B64/(B59+B60) -> 0.38766052 | C65: =C64/(C59+C60) -> 0.36441282 | D65: =D64/(D59+D60) -> 0.3834568 | E65: =E64/(E59+E60) -> 0.35803527 | F65: =F64/(F59+F60) -> 0.37342715
A66: International operating income ($m) | B66: =Inputs!B$52*(1+Inputs!$B$43) -> 61.27 | C66: =Inputs!C$52*(1+Inputs!$B$43) -> 51.92 | D66: =Inputs!D$52*(1+Inputs!$B$43) -> 81.18 | E66: =Inputs!E$52*(1+Inputs!$B$43) -> 62.48 | F66: =SUM(B66:E66) -> 256.85
A67: International revenue ($m) | B67: =Inputs!B$53*(1+Inputs!$B$43) -> 222.64 | C67: =Inputs!C$53*(1+Inputs!$B$43) -> 220.11 | D67: =Inputs!D$53*(1+Inputs!$B$43) -> 257.62 | E67: =Inputs!E$53*(1+Inputs!$B$43) -> 244.2 | F67: =SUM(B67:E67) -> 944.57
A68: Consolidated operating margin, ex-ACV | B68: =(B64+B66)/(B59+B60+B67) -> 0.36646908 | C68: =(C64+C66)/(C59+C60+C67) -> 0.3397759 | D68: =(D64+D66)/(D59+D60+D67) -> 0.36956539 | E68: =(E64+E66)/(E59+E60+E67) -> 0.33799862 | F68: =(F64+F66)/(F59+F60+F67) -> 0.35362828
A69: Core operating EPS, ex-interest, ex-ACV ($/sh) | B69: =(B64+B66)*(1-Inputs!$B$8)/Inputs!$B$7 -> 0.3739979 | C69: =(C64+C66)*(1-Inputs!$B$8)/Inputs!$B$7 -> 0.33700231 | D69: =(D64+D66)*(1-Inputs!$B$8)/Inputs!$B$7 -> 0.40456583 | E69: =(E64+E66)*(1-Inputs!$B$8)/Inputs!$B$7 -> 0.36356234 | F69: =SUM(B69:E69) -> 1.4791284
A70: Interest income, ex-ACV case ($m) | B70: =Inputs!$B$12 -> 38 | C70: =Inputs!$B$12 -> 38 | D70: =Inputs!$B$12 -> 38 | E70: =Inputs!$B$12 -> 38 | F70: =SUM(B70:E70) -> 152
A71: EPS ex-ACV (operating thesis) | B71: =(B64+B66+B70)*(1-Inputs!$B$8)/Inputs!$B$7 -> 0.40681979 | C71: =(C64+C66+C70)*(1-Inputs!$B$8)/Inputs!$B$7 -> 0.36982419 | D71: =(D64+D66+D70)*(1-Inputs!$B$8)/Inputs!$B$7 -> 0.43738772 | E71: =(E64+E66+E70)*(1-Inputs!$B$8)/Inputs!$B$7 -> 0.39638423 | F71: =SUM(B71:E71) -> 1.6104159
A72: ACV pre-tax: operating income − amortization ($m) | B72: =0 -> 0 | C72: =Inputs!$B$16*(Scenarios!$D$11-Scenarios!$D$10) -> -5 | D72: =Scenarios!$D$11-Scenarios!$D$10 -> -10 | E72: =Scenarios!$D$11-Scenarios!$D$10 -> -10 | F72: =SUM(B72:E72) -> -25
A73: Interest income after ACV cash outflow ($m) | B73: =Inputs!$B$12 -> 38 | C73: =Inputs!$B$16*Scenarios!$D$12+(1-Inputs!$B$16)*Inputs!$B$12 -> 33 | D73: =Scenarios!$D$12 -> 28 | E73: =Scenarios!$D$12 -> 28 | F73: =SUM(B73:E73) -> 127
A74: GAAP EPS incl. ACV | B74: =(B64+B66+B72+B73)*(1-Inputs!$B$8)/Inputs!$B$7 -> 0.40681979 | C74: =(C64+C66+C72+C73)*(1-Inputs!$B$8)/Inputs!$B$7 -> 0.36118686 | D74: =(D64+D66+D72+D73)*(1-Inputs!$B$8)/Inputs!$B$7 -> 0.42011304 | E74: =(E64+E66+E72+E73)*(1-Inputs!$B$8)/Inputs!$B$7 -> 0.37910955 | F74: =SUM(B74:E74) -> 1.5672292
A75: ACV EPS impact incl. forgone interest ($/sh) | B75: =B74-B71 -> 0 | C75: =C74-C71 -> -0.0086373391 | D75: =D74-D71 -> -0.017274678 | E75: =E74-E71 -> -0.017274678 | F75: =SUM(B75:E75) -> -0.043186695
A76: EPS ex-interest incl. ACV (valuation base, $/sh) | B76: =(B64+B66+B72)*(1-Inputs!$B$8)/Inputs!$B$7 -> 0.3739979 | C76: =(C64+C66+C72)*(1-Inputs!$B$8)/Inputs!$B$7 -> 0.33268364 | D76: =(D64+D66+D72)*(1-Inputs!$B$8)/Inputs!$B$7 -> 0.39592849 | E76: =(E64+E66+E72)*(1-Inputs!$B$8)/Inputs!$B$7 -> 0.354925 | F76: =SUM(B76:E76) -> 1.457535
A79: W4 Street right / share recapture
A80: Line | B80: Q1 Aug-Oct | C80: Q2 Nov-Jan | D80: Q3 Feb-Apr | E80: Q4 May-Jul | F80: FY27
A81: Lost-customer impact vs FY26 quarter (pts) | B81: =(1+Scenarios!$E$7)/(1-Inputs!B$55)-1 -> -0.05 | C81: =(1+Scenarios!$E$7)/(1-Inputs!C$55)-1 -> -0.05 | D81: =(1+Scenarios!$E$7)/(1-Inputs!D$55)-1 -> -0.05 | E81: =(1+Scenarios!$E$7)/(1-Inputs!E$55)-1 -> 0.053215078
A82: U.S. insurance units y/y | B82: =Scenarios!$E$6+B81 -> -0.02 | C82: =Scenarios!$E$6+C81 -> -0.02 | D82: =Scenarios!$E$6+D81 -> -0.02 | E82: =Scenarios!$E$6+E81 -> 0.083215078
A83: U.S. units y/y | B83: =Inputs!$B$39*B82+(1-Inputs!$B$39)*Inputs!$B$41 -> -0.008 | C83: =Inputs!$B$39*C82+(1-Inputs!$B$39)*Inputs!$B$41 -> -0.008 | D83: =Inputs!$B$39*D82+(1-Inputs!$B$39)*Inputs!$B$41 -> -0.008 | E83: =Inputs!$B$39*E82+(1-Inputs!$B$39)*Inputs!$B$41 -> 0.070443459
A84: U.S. service revenue ($m) | B84: =Inputs!B$47*(1+B83)*(1+Scenarios!$E$8) -> 891.0888 | C84: =Inputs!C$47*(1+C83)*(1+Scenarios!$E$8) -> 853.5912 | D84: =Inputs!D$47*(1+D83)*(1+Scenarios!$E$8) -> 932.7528 | E84: =Inputs!E$47*(1+E83)*(1+Scenarios!$E$8) -> 919.17909 | F84: =SUM(B84:E84) -> 3596.6119
A85: U.S. vehicle sales ($m) | B85: =Inputs!B$48*(1+Inputs!$B$42) -> 101.955 | C85: =Inputs!C$48*(1+Inputs!$B$42) -> 107.31 | D85: =Inputs!D$48*(1+Inputs!$B$42) -> 112.77 | E85: =Inputs!E$48*(1+Inputs!$B$42) -> 118.125 | F85: =SUM(B85:E85) -> 440.16
A86: U.S. vehicle gross profit ($m) | B86: =(Inputs!B$48-Inputs!B$50)*(1+Inputs!$B$42) -> 7.455 | C86: =(Inputs!C$48-Inputs!C$50)*(1+Inputs!$B$42) -> 6.09 | D86: =(Inputs!D$48-Inputs!D$50)*(1+Inputs!$B$42) -> 8.82 | E86: =(Inputs!E$48-Inputs!E$50)*(1+Inputs!$B$42) -> 7.14
A87: U.S. facility operations ($m) | B87: =Inputs!B$49*Inputs!$B$40*(1+Scenarios!$E$9)+Inputs!B$49*(1-Inputs!$B$40)*(1+B83) -> 405.8324 | C87: =Inputs!C$49*Inputs!$B$40*(1+Scenarios!$E$9)+Inputs!C$49*(1-Inputs!$B$40)*(1+C83) -> 402.67536 | D87: =Inputs!D$49*Inputs!$B$40*(1+Scenarios!$E$9)+Inputs!D$49*(1-Inputs!$B$40)*(1+D83) -> 427.42248 | E87: =Inputs!E$49*Inputs!$B$40*(1+Scenarios!$E$9)+Inputs!E$49*(1-Inputs!$B$40)*(1+E83) -> 443.39677 | F87: =SUM(B87:E87) -> 1679.327
A88: U.S. G&A ($m) | B88: =Inputs!B$51*(1+Inputs!$B$42) -> 93.66 | C88: =Inputs!C$51*(1+Inputs!$B$42) -> 92.82 | D88: =Inputs!D$51*(1+Inputs!$B$42) -> 98.385 | E88: =Inputs!E$51*(1+Inputs!$B$42) -> 96.285 | F88: =SUM(B88:E88) -> 381.15
A89: U.S. operating income ($m) | B89: =B84+B86-B87-B88 -> 399.0514 | C89: =C84+C86-C87-C88 -> 364.18584 | D89: =D84+D86-D87-D88 -> 415.76532 | E89: =E84+E86-E87-E88 -> 386.63732 | F89: =SUM(B89:E89) -> 1565.6399
A90: U.S. operating margin | B90: =B89/(B84+B85) -> 0.40184673 | C90: =C89/(C84+C85) -> 0.37900446 | D90: =D89/(D84+D85) -> 0.3976626 | E90: =E89/(E84+E85) -> 0.37273286 | F90: =F89/(F84+F85) -> 0.38784453
A91: International operating income ($m) | B91: =Inputs!B$52*(1+Inputs!$B$43) -> 61.27 | C91: =Inputs!C$52*(1+Inputs!$B$43) -> 51.92 | D91: =Inputs!D$52*(1+Inputs!$B$43) -> 81.18 | E91: =Inputs!E$52*(1+Inputs!$B$43) -> 62.48 | F91: =SUM(B91:E91) -> 256.85
A92: International revenue ($m) | B92: =Inputs!B$53*(1+Inputs!$B$43) -> 222.64 | C92: =Inputs!C$53*(1+Inputs!$B$43) -> 220.11 | D92: =Inputs!D$53*(1+Inputs!$B$43) -> 257.62 | E92: =Inputs!E$53*(1+Inputs!$B$43) -> 244.2 | F92: =SUM(B92:E92) -> 944.57
A93: Consolidated operating margin, ex-ACV | B93: =(B89+B91)/(B84+B85+B92) -> 0.37865224 | C93: =(C89+C91)/(C84+C85+C92) -> 0.35233014 | D93: =(D89+D91)/(D84+D85+D92) -> 0.38134372 | E93: =(E89+E91)/(E84+E85+E92) -> 0.35046109 | F93: =(F89+F91)/(F84+F85+F92) -> 0.36586324
A94: Core operating EPS, ex-interest, ex-ACV ($/sh) | B94: =(B89+B91)*(1-Inputs!$B$8)/Inputs!$B$7 -> 0.3975952 | C94: =(C89+C91)*(1-Inputs!$B$8)/Inputs!$B$7 -> 0.35940472 | D94: =(D89+D91)*(1-Inputs!$B$8)/Inputs!$B$7 -> 0.42922852 | E94: =(E89+E91)*(1-Inputs!$B$8)/Inputs!$B$7 -> 0.38791786 | F94: =SUM(B94:E94) -> 1.5741463
A95: Interest income, ex-ACV case ($m) | B95: =Inputs!$B$12 -> 38 | C95: =Inputs!$B$12 -> 38 | D95: =Inputs!$B$12 -> 38 | E95: =Inputs!$B$12 -> 38 | F95: =SUM(B95:E95) -> 152
A96: EPS ex-ACV (operating thesis) | B96: =(B89+B91+B95)*(1-Inputs!$B$8)/Inputs!$B$7 -> 0.43041709 | C96: =(C89+C91+C95)*(1-Inputs!$B$8)/Inputs!$B$7 -> 0.39222661 | D96: =(D89+D91+D95)*(1-Inputs!$B$8)/Inputs!$B$7 -> 0.46205041 | E96: =(E89+E91+E95)*(1-Inputs!$B$8)/Inputs!$B$7 -> 0.42073975 | F96: =SUM(B96:E96) -> 1.7054339
A97: ACV pre-tax: operating income − amortization ($m) | B97: =0 -> 0 | C97: =Inputs!$B$16*(Scenarios!$E$11-Scenarios!$E$10) -> -5 | D97: =Scenarios!$E$11-Scenarios!$E$10 -> -10 | E97: =Scenarios!$E$11-Scenarios!$E$10 -> -10 | F97: =SUM(B97:E97) -> -25
A98: Interest income after ACV cash outflow ($m) | B98: =Inputs!$B$12 -> 38 | C98: =Inputs!$B$16*Scenarios!$E$12+(1-Inputs!$B$16)*Inputs!$B$12 -> 33 | D98: =Scenarios!$E$12 -> 28 | E98: =Scenarios!$E$12 -> 28 | F98: =SUM(B98:E98) -> 127
A99: GAAP EPS incl. ACV | B99: =(B89+B91+B97+B98)*(1-Inputs!$B$8)/Inputs!$B$7 -> 0.43041709 | C99: =(C89+C91+C97+C98)*(1-Inputs!$B$8)/Inputs!$B$7 -> 0.38358927 | D99: =(D89+D91+D97+D98)*(1-Inputs!$B$8)/Inputs!$B$7 -> 0.44477573 | E99: =(E89+E91+E97+E98)*(1-Inputs!$B$8)/Inputs!$B$7 -> 0.40346507 | F99: =SUM(B99:E99) -> 1.6622472
A100: ACV EPS impact incl. forgone interest ($/sh) | B100: =B99-B96 -> 0 | C100: =C99-C96 -> -0.0086373391 | D100: =D99-D96 -> -0.017274678 | E100: =E99-E96 -> -0.017274678 | F100: =SUM(B100:E100) -> -0.043186695
A101: EPS ex-interest incl. ACV (valuation base, $/sh) | B101: =(B89+B91+B97)*(1-Inputs!$B$8)/Inputs!$B$7 -> 0.3975952 | C101: =(C89+C91+C97)*(1-Inputs!$B$8)/Inputs!$B$7 -> 0.35508605 | D101: =(D89+D91+D97)*(1-Inputs!$B$8)/Inputs!$B$7 -> 0.42059118 | E101: =(E89+E91+E97)*(1-Inputs!$B$8)/Inputs!$B$7 -> 0.37928052 | F101: =SUM(B101:E101) -> 1.552553
A105: W2 FY27 EPS bridge from FY26 reported EPS (cumulative replay of the W2 block; drivers switched on in order)
A106: Step | B106: Underlying u | C106: Run-rate drag | D106: Q4 base drag on | E106: RPU growth | F106: Fixed cost growth | G106: Non-ins. growth | H106: Veh. GP / G&A growth | I106: Intl growth | J106: FY27 EPS ex-ACV | K106: Step change
A107: FY26 reported diluted EPS | J107: =SUM(Inputs!B56:E56) -> 1.55
A108: FY26 replay at FY27 share count and pre-ACV interest (zero growth) | B108: 0 | C108: 0 | D108: 0 | E108: 0 | F108: 0 | G108: 0 | H108: 0 | I108: 0 | J108: =(((Inputs!$B$47*(1+(Inputs!$B$39*($B108+((1+$C108)/(1-Inputs!$B$55*$D108)-1))+(1-Inputs!$B$39)*$G108))*(1+$E108)+(Inputs!$B$48-Inputs!$B$50)*(1+$H108)-(Inputs!$B$49*Inputs!$B$40*(1+$F108)+Inputs!$B$49*(1-Inputs!$B$40)*(1+(Inputs!$B$39*($B108+((1+$C108)/(1-Inputs!$B$55*$D108)-1))+(1-Inputs!$B$39)*$G108)))-Inputs!$B$51*(1+$H108))+Inputs!$B$52*(1+$I108))+((Inputs!$C$47*(1+(Inputs!$B$39*($B108+((1+$C108)/(1-Inputs!$C$55*$D108)-1))+(1-Inputs!$B$39)*$G108))*(1+$E108)+(Inputs!$C$48-Inputs!$C$50)*(1+$H108)-(Inputs!$C$49*Inputs!$B$40*(1+$F108)+Inputs!$C$49*(1-Inputs!$B$40)*(1+(Inputs!$B$39*($B108+((1+$C108)/(1-Inputs!$C$55*$D108)-1))+(1-Inputs!$B$39)*$G108)))-Inputs!$C$51*(1+$H108))+Inputs!$C$52*(1+$I108))+((Inputs!$D$47*(1+(Inputs!$B$39*($B108+((1+$C108)/(1-Inputs!$D$55*$D108)-1))+(1-Inputs!$B$39)*$G108))*(1+$E108)+(Inputs!$D$48-Inputs!$D$50)*(1+$H108)-(Inputs!$D$49*Inputs!$B$40*(1+$F108)+Inputs!$D$49*(1-Inputs!$B$40)*(1+(Inputs!$B$39*($B108+((1+$C108)/(1-Inputs!$D$55*$D108)-1))+(1-Inputs!$B$39)*$G108)))-Inputs!$D$51*(1+$H108))+Inputs!$D$52*(1+$I108))+((Inputs!$E$47*(1+(Inputs!$B$39*($B108+((1+$C108)/(1-Inputs!$E$55*$D108)-1))+(1-Inputs!$B$39)*$G108))*(1+$E108)+(Inputs!$E$48-Inputs!$E$50)*(1+$H108)-(Inputs!$E$49*Inputs!$B$40*(1+$F108)+Inputs!$E$49*(1-Inputs!$B$40)*(1+(Inputs!$B$39*($B108+((1+$C108)/(1-Inputs!$E$55*$D108)-1))+(1-Inputs!$B$39)*$G108)))-Inputs!$E$51*(1+$H108))+Inputs!$E$52*(1+$I108))+4*Inputs!$B$12)*(1-Inputs!$B$8)/Inputs!$B$7 -> 1.5586078 | K108: =J108-J107 -> 0.0086078326
A109: + lost-customer drag (13-pt run-rate, net of Q4 FY26 base) | B109: 0 | C109: =Scenarios!$C$7 -> -0.13 | D109: 1 | E109: 0 | F109: 0 | G109: 0 | H109: 0 | I109: 0 | J109: =(((Inputs!$B$47*(1+(Inputs!$B$39*($B109+((1+$C109)/(1-Inputs!$B$55*$D109)-1))+(1-Inputs!$B$39)*$G109))*(1+$E109)+(Inputs!$B$48-Inputs!$B$50)*(1+$H109)-(Inputs!$B$49*Inputs!$B$40*(1+$F109)+Inputs!$B$49*(1-Inputs!$B$40)*(1+(Inputs!$B$39*($B109+((1+$C109)/(1-Inputs!$B$55*$D109)-1))+(1-Inputs!$B$39)*$G109)))-Inputs!$B$51*(1+$H109))+Inputs!$B$52*(1+$I109))+((Inputs!$C$47*(1+(Inputs!$B$39*($B109+((1+$C109)/(1-Inputs!$C$55*$D109)-1))+(1-Inputs!$B$39)*$G109))*(1+$E109)+(Inputs!$C$48-Inputs!$C$50)*(1+$H109)-(Inputs!$C$49*Inputs!$B$40*(1+$F109)+Inputs!$C$49*(1-Inputs!$B$40)*(1+(Inputs!$B$39*($B109+((1+$C109)/(1-Inputs!$C$55*$D109)-1))+(1-Inputs!$B$39)*$G109)))-Inputs!$C$51*(1+$H109))+Inputs!$C$52*(1+$I109))+((Inputs!$D$47*(1+(Inputs!$B$39*($B109+((1+$C109)/(1-Inputs!$D$55*$D109)-1))+(1-Inputs!$B$39)*$G109))*(1+$E109)+(Inputs!$D$48-Inputs!$D$50)*(1+$H109)-(Inputs!$D$49*Inputs!$B$40*(1+$F109)+Inputs!$D$49*(1-Inputs!$B$40)*(1+(Inputs!$B$39*($B109+((1+$C109)/(1-Inputs!$D$55*$D109)-1))+(1-Inputs!$B$39)*$G109)))-Inputs!$D$51*(1+$H109))+Inputs!$D$52*(1+$I109))+((Inputs!$E$47*(1+(Inputs!$B$39*($B109+((1+$C109)/(1-Inputs!$E$55*$D109)-1))+(1-Inputs!$B$39)*$G109))*(1+$E109)+(Inputs!$E$48-Inputs!$E$50)*(1+$H109)-(Inputs!$E$49*Inputs!$B$40*(1+$F109)+Inputs!$E$49*(1-Inputs!$B$40)*(1+(Inputs!$B$39*($B109+((1+$C109)/(1-Inputs!$E$55*$D109)-1))+(1-Inputs!$B$39)*$G109)))-Inputs!$E$51*(1+$H109))+Inputs!$E$52*(1+$I109))+4*Inputs!$B$12)*(1-Inputs!$B$8)/Inputs!$B$7 -> 1.3712182 | K109: =J109-J108 -> -0.18738961
A110: + underlying insurance and non-insurance unit growth | B110: =Scenarios!$C$6 -> 0.01 | C110: =Scenarios!$C$7 -> -0.13 | D110: 1 | E110: 0 | F110: 0 | G110: =Inputs!$B$41 -> 0.03 | H110: 0 | I110: 0 | J110: =(((Inputs!$B$47*(1+(Inputs!$B$39*($B110+((1+$C110)/(1-Inputs!$B$55*$D110)-1))+(1-Inputs!$B$39)*$G110))*(1+$E110)+(Inputs!$B$48-Inputs!$B$50)*(1+$H110)-(Inputs!$B$49*Inputs!$B$40*(1+$F110)+Inputs!$B$49*(1-Inputs!$B$40)*(1+(Inputs!$B$39*($B110+((1+$C110)/(1-Inputs!$B$55*$D110)-1))+(1-Inputs!$B$39)*$G110)))-Inputs!$B$51*(1+$H110))+Inputs!$B$52*(1+$I110))+((Inputs!$C$47*(1+(Inputs!$B$39*($B110+((1+$C110)/(1-Inputs!$C$55*$D110)-1))+(1-Inputs!$B$39)*$G110))*(1+$E110)+(Inputs!$C$48-Inputs!$C$50)*(1+$H110)-(Inputs!$C$49*Inputs!$B$40*(1+$F110)+Inputs!$C$49*(1-Inputs!$B$40)*(1+(Inputs!$B$39*($B110+((1+$C110)/(1-Inputs!$C$55*$D110)-1))+(1-Inputs!$B$39)*$G110)))-Inputs!$C$51*(1+$H110))+Inputs!$C$52*(1+$I110))+((Inputs!$D$47*(1+(Inputs!$B$39*($B110+((1+$C110)/(1-Inputs!$D$55*$D110)-1))+(1-Inputs!$B$39)*$G110))*(1+$E110)+(Inputs!$D$48-Inputs!$D$50)*(1+$H110)-(Inputs!$D$49*Inputs!$B$40*(1+$F110)+Inputs!$D$49*(1-Inputs!$B$40)*(1+(Inputs!$B$39*($B110+((1+$C110)/(1-Inputs!$D$55*$D110)-1))+(1-Inputs!$B$39)*$G110)))-Inputs!$D$51*(1+$H110))+Inputs!$D$52*(1+$I110))+((Inputs!$E$47*(1+(Inputs!$B$39*($B110+((1+$C110)/(1-Inputs!$E$55*$D110)-1))+(1-Inputs!$B$39)*$G110))*(1+$E110)+(Inputs!$E$48-Inputs!$E$50)*(1+$H110)-(Inputs!$E$49*Inputs!$B$40*(1+$F110)+Inputs!$E$49*(1-Inputs!$B$40)*(1+(Inputs!$B$39*($B110+((1+$C110)/(1-Inputs!$E$55*$D110)-1))+(1-Inputs!$B$39)*$G110)))-Inputs!$E$51*(1+$H110))+Inputs!$E$52*(1+$I110))+4*Inputs!$B$12)*(1-Inputs!$B$8)/Inputs!$B$7 -> 1.4051299 | K110: =J110-J109 -> 0.033911693
...

Sheet Valuation
A1: Valuation at the planned exit: mid-February 2027 (after Q2 FY27 results)
A2: Value = PV of distributions from year-1 (NTM) and year-2 earnings, years 3-5 at g and a Gordon terminal, discounted at the cost of equity; ex-interest earnings, with net cash at the valuation date added. Justified P/E = ex-cash value / NTM EPS (derived from growth, ROIC and cost of equity, not selected). Explicit-period payout ratios are linked to each year's modeled EPS growth and incremental ROIC; normalized payout is used only after the recovery period.
A3: Valuation date: mid-February 2027, following Q2 FY27 results
A4: Forward earnings basis: NTM = Q3 FY27 + Q4 FY27 (modeled, incl. ACV) + Q1 FY28 + Q2 FY28 (each = the matching FY27 quarter's core operating EPS × (1 + FY28 growth) + ¼ of the FY28 ACV contribution ex-interest); ex-interest. Year 2 = Q3 FY28 - Q2 FY29.
A6: EPS by world: FY27 and FY28 (FY28 = standalone + explicit ACV)
A7: Line | B7: W1 Loss deepens | C7: W2 FY27 trough / FY28 normalizes | D7: W3 Cycle turns / ACV improves | E7: W4 Street right / share recapture
A8: Team scenario probability | B8: =Scenarios!B$14 -> 0.2 | C8: =Scenarios!C$14 -> 0.45 | D8: =Scenarios!D$14 -> 0.2 | E8: =Scenarios!E$14 -> 0.15
A9: FY27 EPS ex-ACV ($/sh) | B9: =EPS_Build!$F$21 -> 1.2792888 | C9: =EPS_Build!$F$46 -> 1.4520874 | D9: =EPS_Build!$F$71 -> 1.6104159 | E9: =EPS_Build!$F$96 -> 1.7054339
A10: FY27 modeled ACV impact ($/sh) | B10: =EPS_Build!F25 -> -0.09501073 | C10: =EPS_Build!F50 -> -0.069098712 | D10: =EPS_Build!F75 -> -0.043186695 | E10: =EPS_Build!F100 -> -0.043186695
A11: FY27 GAAP EPS incl. ACV ($/sh) | B11: =EPS_Build!$F$24 -> 1.184278 | C11: =EPS_Build!$F$49 -> 1.3829887 | D11: =EPS_Build!$F$74 -> 1.5672292 | E11: =EPS_Build!$F$99 -> 1.6622472
A12: FY28 standalone CPRT EPS before ACV ($/sh) | B12: =EPS_Build!F19*(1+Scenarios!B$15)+Inputs!$B$12*4*(1-Inputs!$B$8)/Inputs!$B$7 -> 1.3252088 | C12: =EPS_Build!F44*(1+Scenarios!C$15)+Inputs!$B$12*4*(1-Inputs!$B$8)/Inputs!$B$7 -> 1.6105834 | D12: =EPS_Build!F69*(1+Scenarios!D$15)+Inputs!$B$12*4*(1-Inputs!$B$8)/Inputs!$B$7 -> 1.876659 | E12: =EPS_Build!F94*(1+Scenarios!E$15)+Inputs!$B$12*4*(1-Inputs!$B$8)/Inputs!$B$7 -> 1.9415558
A13: FY28 ACV contribution ($/sh, team estimate) | B13: =Scenarios!B$13 -> 0 | C13: =Scenarios!C$13 -> 0.02 | D13: =Scenarios!D$13 -> 0.04 | E13: =Scenarios!E$13 -> 0.02
A14: FY28 EPS incl. ACV ($/sh) | B14: =B12+B13 -> 1.3252088 | C14: =C12+C13 -> 1.6305834 | D14: =D12+D13 -> 1.916659 | E14: =E12+E13 -> 1.9615558
A17: Forward earnings bridge at the valuation date (ex-interest, $/sh)
A18: Line | B18: W1 Loss deepens | C18: W2 FY27 trough / FY28 normalizes | D18: W3 Cycle turns / ACV improves | E18: W4 Street right / share recapture
A19: Q3 FY27 (Feb-Apr 27) ex-interest EPS incl. ACV | B19: =EPS_Build!D26 -> 0.2939636 | C19: =EPS_Build!D51 -> 0.34688326 | D19: =EPS_Build!D76 -> 0.39592849 | E19: =EPS_Build!D101 -> 0.42059118
A20: Q4 FY27 (May-Jul 27) ex-interest EPS incl. ACV | B20: =EPS_Build!E26 -> 0.25627402 | C20: =EPS_Build!E51 -> 0.30728698 | D20: =EPS_Build!E76 -> 0.354925 | E20: =EPS_Build!E101 -> 0.37928052
A21: FY28 ACV contribution ex-interest, per quarter | B21: =(Scenarios!B$13+(Inputs!$B$12-Scenarios!B$12)*4*(1-Inputs!$B$8)/Inputs!$B$7)/4 -> 0.013819742 | C21: =(Scenarios!C$13+(Inputs!$B$12-Scenarios!C$12)*4*(1-Inputs!$B$8)/Inputs!$B$7)/4 -> 0.016228541 | D21: =(Scenarios!D$13+(Inputs!$B$12-Scenarios!D$12)*4*(1-Inputs!$B$8)/Inputs!$B$7)/4 -> 0.018637339 | E21: =(Scenarios!E$13+(Inputs!$B$12-Scenarios!E$12)*4*(1-Inputs!$B$8)/Inputs!$B$7)/4 -> 0.013637339
A22: Q1 FY28 (Aug-Oct 27) ex-interest EPS | B22: =EPS_Build!B19*(1+Scenarios!B$15)+B21 -> 0.31690749 | C22: =EPS_Build!B44*(1+Scenarios!C$15)+C21 -> 0.39094528 | D22: =EPS_Build!B69*(1+Scenarios!D$15)+D21 -> 0.45995487 | E22: =EPS_Build!B94*(1+Scenarios!E$15)+E21 -> 0.47087182
A23: Q2 FY28 (Nov 27-Jan 28) ex-interest EPS | B23: =EPS_Build!C19*(1+Scenarios!B$15)+B21 -> 0.28210226 | C23: =EPS_Build!C44*(1+Scenarios!C$15)+C21 -> 0.35137647 | D23: =EPS_Build!C69*(1+Scenarios!D$15)+D21 -> 0.41630006 | E23: =EPS_Build!C94*(1+Scenarios!E$15)+E21 -> 0.42695277
A24: NTM ex-interest EPS at mid-Feb 2027 (year 1) | B24: =B19+B20+B22+B23 -> 1.1492474 | C24: =C19+C20+C22+C23 -> 1.396492 | D24: =D19+D20+D22+D23 -> 1.6271084 | E24: =E19+E20+E22+E23 -> 1.6976963
A25: Year 2 ex-interest EPS (Q3 FY28 - Q2 FY29) | B25: =(EPS_Build!D19+EPS_Build!E19)*(1+Scenarios!B$15)+2*B21+(B22+B23)*(1+Scenarios!B$16) -> 1.2671705 | C25: =(EPS_Build!D44+EPS_Build!E44)*(1+Scenarios!C$15)+2*C21+(C22+C23)*(1+Scenarios!C$16) -> 1.5887493 | D25: =(EPS_Build!D69+EPS_Build!E69)*(1+Scenarios!D$15)+2*D21+(D22+D23)*(1+Scenarios!D$16) -> 1.8987838 | E25: =(EPS_Build!D94+EPS_Build!E94)*(1+Scenarios!E$15)+2*E21+(E22+E23)*(1+Scenarios!E$16) -> 1.9546001
A26: Year-2 growth (FY28 recovery completes) | B26: =B25/B24-1 -> 0.10260902 | C26: =C25/C24-1 -> 0.13767163 | D26: =D25/D24-1 -> 0.1669682 | E26: =E25/E24-1 -> 0.15132493
A29: Valuation
A30: Line | B30: W1 Loss deepens | C30: W2 FY27 trough / FY28 normalizes | D30: W3 Cycle turns / ACV improves | E30: W4 Street right / share recapture
A31: EPS growth, years 3-5 and terminal fade start (g) | B31: =Scenarios!B$16 -> 0.03 | C31: =Scenarios!C$16 -> 0.06 | D31: =Scenarios!D$16 -> 0.09 | E31: =Scenarios!E$16 -> 0.1
A32: Incremental ROIC | B32: =Scenarios!B$17 -> 0.15 | C32: =Scenarios!C$17 -> 0.2 | D32: =Scenarios!D$17 -> 0.25 | E32: =Scenarios!E$17 -> 0.25
A33: Cost of equity (Inputs) | B33: =Inputs!$B$34 -> 0.0974 | C33: =Inputs!$B$34 -> 0.0974 | D33: =Inputs!$B$34 -> 0.0974 | E33: =Inputs!$B$34 -> 0.0974
A34: Terminal growth (Inputs) | B34: =Inputs!$B$32 -> 0.03 | C34: =Inputs!$B$32 -> 0.03 | D34: =Inputs!$B$32 -> 0.03 | E34: =Inputs!$B$32 -> 0.03
A35: Year-1 payout = 1 − g1 / ROIC (g1 = year-2 growth above) | B35: =1-B26/B32 -> 0.31593988 | C35: =1-C26/C32 -> 0.31164184 | D35: =1-D26/D32 -> 0.33212718 | E35: =1-E26/E32 -> 0.39470028
A36: Normalized payout, years 2-5 = 1 − g / ROIC | B36: =1-B31/B32 -> 0.8 | C36: =1-C31/C32 -> 0.7 | D36: =1-D31/D32 -> 0.64 | E36: =1-E31/E32 -> 0.6
A37: PV of years 1-5 distributions ($/sh) | B37: =B35*B24/(1+B33)+(1-B31/B32)*(B25/(1+B33)^2+B25*(1+B31)/(1+B33)^3+B25*(1+B31)^2/(1+B33)^4+B25*(1+B31)^3/(1+B33)^5) -> 3.4002663 | C37: =C35*C24/(1+C33)+(1-C31/C32)*(C25/(1+C33)^2+C25*(1+C31)/(1+C33)^3+C25*(1+C31)^2/(1+C33)^4+C25*(1+C31)^3/(1+C33)^5) -> 3.905884 | D37: =D35*D24/(1+D33)+(1-D31/D32)*(D25/(1+D33)^2+D25*(1+D31)/(1+D33)^3+D25*(1+D31)^2/(1+D33)^4+D25*(1+D31)^3/(1+D33)^5) -> 4.4881194 | E37: =E35*E24/(1+E33)+(1-E31/E32)*(E25/(1+E33)^2+E25*(1+E31)/(1+E33)^3+E25*(1+E31)^2/(1+E33)^4+E25*(1+E31)^3/(1+E33)^5) -> 4.5197581
A38: PV of terminal value ($/sh) | B38: =B25*(1+B31)^4*(1-B34/B32)/(B33-B34)/(1+B33)^5 -> 10.636268 | C38: =C25*(1+C31)^4*(1-C34/C32)/(C33-C34)/(1+C33)^5 -> 15.893264 | D38: =D25*(1+D31)^4*(1-D34/D32)/(D33-D34)/(1+D33)^5 -> 21.987685 | E38: =E25*(1+E31)^4*(1-E34/E32)/(E33-E34)/(1+E33)^5 -> 23.476138
A39: Ex-cash equity value ($/sh) | B39: =B37+B38 -> 14.036534 | C39: =C37+C38 -> 19.799148 | D39: =D37+D38 -> 26.475804 | E39: =E37+E38 -> 27.995896
A40: Justified ex-cash P/E on NTM EPS | B40: =B39/B24 -> 12.213675 | C40: =C39/C24 -> 14.177774 | D40: =D39/D24 -> 16.27169 | E40: =E39/E24 -> 16.490521
A41: Net cash per share at the valuation date ($/sh) | B41: =Inputs!$B$10*1000/Inputs!$B$7 -> 3.304721 | C41: =Inputs!$B$10*1000/Inputs!$B$7 -> 3.304721 | D41: =Inputs!$B$10*1000/Inputs!$B$7 -> 3.304721 | E41: =Inputs!$B$10*1000/Inputs!$B$7 -> 3.304721
A42: Value per share, mid-Feb 2027 ($/sh) | B42: =B39+B41 -> 17.341255 | C42: =C39+C41 -> 23.103869 | D42: =D39+D41 -> 29.780525 | E42: =E39+E41 -> 31.300617
A43: Stock return vs reference price | B43: =B42/Inputs!$B$6-1 -> -0.36455642 | C43: =C42/Inputs!$B$6-1 -> -0.15339433 | D43: =D42/Inputs!$B$6-1 -> 0.09126146 | E43: =E42/Inputs!$B$6-1 -> 0.14696287
A44: Short return | B44: =-B43 -> 0.36455642 | C44: =-C43 -> 0.15339433 | D44: =-D43 -> -0.09126146 | E44: =-E43 -> -0.14696287
A45: NTM after-tax interest per share ($/sh) | B45: =Scenarios!B$12*4*(1-Inputs!$B$8)/Inputs!$B$7 -> 0.076008584 | C45: =Scenarios!C$12*4*(1-Inputs!$B$8)/Inputs!$B$7 -> 0.086373391 | D45: =Scenarios!D$12*4*(1-Inputs!$B$8)/Inputs!$B$7 -> 0.096738197 | E45: =Scenarios!E$12*4*(1-Inputs!$B$8)/Inputs!$B$7 -> 0.096738197
A46: Implied total P/E on NTM EPS incl. interest | B46: =B42/(B24+B45) -> 14.15317 | C46: =C42/(C24+C45) -> 15.580557 | D46: =D42/(D24+D45) -> 17.275624 | E46: =E42/(E24+E45) -> 17.443165
A49: Probability-weighted result and downside
A50: Probability-weighted value ($/sh) | B50: =SUMPRODUCT(B8:E8,B42:E42) -> 24.51619
A51: Probability-weighted (expected) stock return | B51: =B50/Inputs!$B$6-1 -> -0.10164201
A52: Expected short return | B52: =-B51 -> 0.10164201
A53: Base-case (W2) value ($/sh) | B53: =C42 -> 23.103869
A54: Base-case (W2) stock return | B54: =C43 -> -0.15339433
A55: W4 adverse-case short loss (W4 stock return) | B55: =E43 -> 0.14696287
A57: Rate-cut stress: W3 economics with the 10-year yield at 3.5% (more severe than W4)
A58: W3 NTM ex-interest EPS ($/sh) | B58: =D24 -> 1.6271084
A59: W3 year-2 ex-interest EPS ($/sh) | B59: =D25 -> 1.8987838
A60: EPS growth (W3) | B60: =D31 -> 0.09
A61: Incremental ROIC (W3) | B61: =D32 -> 0.25
A62: Stress cost of equity (Inputs) | B62: =Inputs!$B$35 -> 0.08
A63: Stress ex-cash value ($/sh) | B63: =(1-(B59/B58-1)/B61)*B58/(1+B62)+(1-B60/B61)*(B59/(1+B62)^2+B59*(1+B60)/(1+B62)^3+B59*(1+B60)^2/(1+B62)^4+B59*(1+B60)^3/(1+B62)^5)+B59*(1+B60)^4*(1-Inputs!$B$32/B61)/(B62-Inputs!$B$32)/(1+B62)^5 -> 36.831244
A64: Stress value per share ($/sh) | B64: =B63+D41 -> 40.135965
A65: Rate-cut stress short loss (stock return) | B65: =B64/Inputs!$B$6-1 -> 0.47072059
A67: EPS-only check: today's market multiple held constant; only EPS changes
A68: Market ex-cash, ex-interest NTM P/E on published FY27 consensus $1.62 | B68: =(Inputs!$B$6-Inputs!$B$9*1000/Inputs!$B$7)/(Consensus!C9-Inputs!$B$11*0.6*(1-Inputs!$B$8)/Inputs!$B$7) -> 14.728932
A69: Stock return, EPS-only (market P/E × our NTM + cash) | B69: =($B$68*B24+B41)/Inputs!$B$6-1 -> -0.25863294 | C69: =($B$68*C24+C41)/Inputs!$B$6-1 -> -0.12519032 | D69: =($B$68*D24+D41)/Inputs!$B$6-1 -> -0.00072225803 | E69: =($B$68*E24+E41)/Inputs!$B$6-1 -> 0.037375359
A70: Expected short return, EPS-only (no multiple change) | B70: =-SUMPRODUCT(B8:E8,B69:E69) -> 0.10260038
A72: Short returns are gross and exclude borrow fees, financing costs and transaction costs.
A73: Horizon cash is held constant across scenarios to isolate operating differences; ±$200m of cash changes value by approximately $0.21/share.
A74: ACV acquired net cash is not explicitly modeled in horizon cash; June-30 ACV net cash was approximately +$37m before subsequent changes, an impact of < $0.05/share.

Sheet Sensitivity
A1: Sensitivity (live formulas)
A2: Operating drivers first (lost-customer drag × fixed cost share), then valuation, ACV and share-count risks.
A4: Key operating sensitivity: lost-customer drag × fixed facility cost share (W2; all other drivers unchanged)
A5: Run-rate drag \ fixed share | B5: 45% | C5: 55% | D5: 65%
A6: Q1 FY27 EPS ex-ACV ($/sh)
A7: 10 pts drag | B7: =I73 -> 0.38581195 | C7: =I74 -> 0.38129607 | D7: =I75 -> 0.3767802
A8: 13 pts drag (W2 base) | B8: =I76 -> 0.37269106 | C8: =I77 -> 0.36739041 | D8: =I78 -> 0.36208976
A9: 16 pts drag | B9: =I79 -> 0.35957016 | C9: =I80 -> 0.35348474 | D9: =I81 -> 0.34739932
A11: FY27 EPS ex-ACV ($/sh)
A12: 10 pts drag | B12: =J73 -> 1.5238913 | C12: =J74 -> 1.508071 | D12: =J75 -> 1.4922508
A13: 13 pts drag (W2 base) | B13: =J76 -> 1.4712164 | C13: =J77 -> 1.4520874 | D13: =J78 -> 1.4329585
A14: 16 pts drag | B14: =J79 -> 1.4185415 | C14: =J80 -> 1.3961038 | D14: =J81 -> 1.3736662
A16: Base-case (W2) value ($/sh)
A17: 10 pts drag | B17: =M73 -> 24.154434 | C17: =M74 -> 23.921746 | D17: =M75 -> 23.689059
A18: 13 pts drag (W2 base) | B18: =M76 -> 23.384848 | C18: =M77 -> 23.103869 | D18: =M78 -> 22.822889
A19: 16 pts drag | B19: =M79 -> 22.615263 | C19: =M80 -> 22.285991 | D19: =M81 -> 21.956719
A21: Lost-customer drag (W2, fixed share 55%)
A22: Full-run-rate drag | B22: Q1 FY27 EPS | C22: FY27 EPS ex-ACV | D22: Base-case value | E22: Short return
A23: 10 pts (≈ W3 run-rate) | B23: =I74 -> 0.38129607 | C23: =J74 -> 1.508071 | D23: =M74 -> 23.921746 | E23: =-(D23/Inputs!$B$6-1) -> 0.12342447
A24: 13 pts (W2 base) | B24: =I77 -> 0.36739041 | C24: =J77 -> 1.4520874 | D24: =M77 -> 23.103869 | E24: =-(D24/Inputs!$B$6-1) -> 0.15339433
A25: 16 pts (≈ 60%-in-Q4 implied; W1) | B25: =I80 -> 0.35348474 | C25: =J80 -> 1.3961038 | D25: =M80 -> 22.285991 | E25: =-(D25/Inputs!$B$6-1) -> 0.18336419
A27: Diluted shares / buyback risk (W2; buybacks at $27.29 funded from cash, interest forgone)
A28: Diluted shares (m) | B28: Q1 FY27 EPS | C28: FY27 EPS ex-ACV | D28: Base-case value | E28: Short return
A29: 940m (v1 assumption) | B29: =I82 -> 0.36584602 | C29: =J82 -> 1.4460586 | D29: =M82 -> 23.141303 | E29: =-(D29/Inputs!$B$6-1) -> 0.15202261
A30: 932m (model: Q4 FY26 diluted WASO) | B30: =I83 -> 0.36739041 | C30: =J83 -> 1.4520874 | D30: =M83 -> 23.103869 | E30: =-(D30/Inputs!$B$6-1) -> 0.15339433
A31: 930m (modest buybacks) | B31: =I84 -> 0.36778066 | C31: =J84 -> 1.4536108 | D31: =M84 -> 23.09441 | E31: =-(D31/Inputs!$B$6-1) -> 0.15374095
A32: 920m (accelerated buybacks) | B32: =I85 -> 0.36975736 | C32: =J85 -> 1.4613273 | D32: =M85 -> 23.046497 | E32: =-(D32/Inputs!$B$6-1) -> 0.15549664
A34: Cost-of-equity shift (all four worlds revalued)
A35: Cost-of-equity shift | B35: Shift | C35: Cost of equity | D35: Base-case value | E35: Expected short return
A36: Cost of equity -1.0pt | B36: -0.01 | C36: =Inputs!$B$34+B36 -> 0.0874 | D36: =((1-((Valuation!$C$25)/(Valuation!$C$24)-1)/Valuation!$C$32)*(Valuation!$C$24)/(1+$C36)+(1-Valuation!$C$31/Valuation!$C$32)*((Valuation!$C$25)/(1+$C36)^2+(Valuation!$C$25)*(1+Valuation!$C$31)/(1+$C36)^3+(Valuation!$C$25)*(1+Valuation!$C$31)^2/(1+$C36)^4+(Valuation!$C$25)*(1+Valuation!$C$31)^3/(1+$C36)^5)+(Valuation!$C$25)*(1+Valuation!$C$31)^4*(1-Valuation!$C$34/Valuation!$C$32)/($C36-Valuation!$C$34)/(1+$C36)^5+Valuation!$C$41) -> 26.863424 | E36: =-(Valuation!B8*(((1-((Valuation!$B$25)/(Valuation!$B$24)-1)/Valuation!$B$32)*(Valuation!$B$24)/(1+$C36)+(1-Valuation!$B$31/Valuation!$B$32)*((Valuation!$B$25)/(1+$C36)^2+(Valuation!$B$25)*(1+Valuation!$B$31)/(1+$C36)^3+(Valuation!$B$25)*(1+Valuation!$B$31)^2/(1+$C36)^4+(Valuation!$B$25)*(1+Valuation!$B$31)^3/(1+$C36)^5)+(Valuation!$B$25)*(1+Valuation!$B$31)^4*(1-Valuation!$B$34/Valuation!$B$32)/($C36-Valuation!$B$34)/(1+$C36)^5+Valuation!$B$41)/Inputs!$B$6-1)+Valuation!C8*(((1-((Valuation!$C$25)/(Valuation!$C$24)-1)/Valuation!$C$32)*(Valuation!$C$24)/(1+$C36)+(1-Valuation!$C$31/Valuation!$C$32)*((Valuation!$C$25)/(1+$C36)^2+(Valuation!$C$25)*(1+Valuation!$C$31)/(1+$C36)^3+(Valuation!$C$25)*(1+Valuation!$C$31)^2/(1+$C36)^4+(Valuation!$C$25)*(1+Valuation!$C$31)^3/(1+$C36)^5)+(Valuation!$C$25)*(1+Valuation!$C$31)^4*(1-Valuation!$C$34/Valuation!$C$32)/($C36-Valuation!$C$34)/(1+$C36)^5+Valuation!$C$41)/Inputs!$B$6-1)+Valuation!D8*(((1-((Valuation!$D$25)/(Valuation!$D$24)-1)/Valuation!$D$32)*(Valuation!$D$24)/(1+$C36)+(1-Valuation!$D$31/Valuation!$D$32)*((Valuation!$D$25)/(1+$C36)^2+(Valuation!$D$25)*(1+Valuation!$D$31)/(1+$C36)^3+(Valuation!$D$25)*(1+Valuation!$D$31)^2/(1+$C36)^4+(Valuation!$D$25)*(1+Valuation!$D$31)^3/(1+$C36)^5)+(Valuation!$D$25)*(1+Valuation!$D$31)^4*(1-Valuation!$D$34/Valuation!$D$32)/($C36-Valuation!$D$34)/(1+$C36)^5+Valuation!$D$41)/Inputs!$B$6-1)+Valuation!E8*(((1-((Valuation!$E$25)/(Valuation!$E$24)-1)/Valuation!$E$32)*(Valuation!$E$24)/(1+$C36)+(1-Valuation!$E$31/Valuation!$E$32)*((Valuation!$E$25)/(1+$C36)^2+(Valuation!$E$25)*(1+Valuation!$E$31)/(1+$C36)^3+(Valuation!$E$25)*(1+Valuation!$E$31)^2/(1+$C36)^4+(Valuation!$E$25)*(1+Valuation!$E$31)^3/(1+$C36)^5)+(Valuation!$E$25)*(1+Valuation!$E$31)^4*(1-Valuation!$E$34/Valuation!$E$32)/($C36-Valuation!$E$34)/(1+$C36)^5+Valuation!$E$41)/Inputs!$B$6-1)) -> -0.047187182
A37: Cost of equity -0.5pt | B37: -0.005 | C37: =Inputs!$B$34+B37 -> 0.0924 | D37: =((1-((Valuation!$C$25)/(Valuation!$C$24)-1)/Valuation!$C$32)*(Valuation!$C$24)/(1+$C37)+(1-Valuation!$C$31/Valuation!$C$32)*((Valuation!$C$25)/(1+$C37)^2+(Valuation!$C$25)*(1+Valuation!$C$31)/(1+$C37)^3+(Valuation!$C$25)*(1+Valuation!$C$31)^2/(1+$C37)^4+(Valuation!$C$25)*(1+Valuation!$C$31)^3/(1+$C37)^5)+(Valuation!$C$25)*(1+Valuation!$C$31)^4*(1-Valuation!$C$34/Valuation!$C$32)/($C37-Valuation!$C$34)/(1+$C37)^5+Valuation!$C$41) -> 24.831545 | E37: =-(Valuation!B8*(((1-((Valuation!$B$25)/(Valuation!$B$24)-1)/Valuation!$B$32)*(Valuation!$B$24)/(1+$C37)+(1-Valuation!$B$31/Valuation!$B$32)*((Valuation!$B$25)/(1+$C37)^2+(Valuation!$B$25)*(1+Valuation!$B$31)/(1+$C37)^3+(Valuation!$B$25)*(1+Valuation!$B$31)^2/(1+$C37)^4+(Valuation!$B$25)*(1+Valuation!$B$31)^3/(1+$C37)^5)+(Valuation!$B$25)*(1+Valuation!$B$31)^4*(1-Valuation!$B$34/Valuation!$B$32)/($C37-Valuation!$B$34)/(1+$C37)^5+Valuation!$B$41)/Inputs!$B$6-1)+Valuation!C8*(((1-((Valuation!$C$25)/(Valuation!$C$24)-1)/Valuation!$C$32)*(Valuation!$C$24)/(1+$C37)+(1-Valuation!$C$31/Valuation!$C$32)*((Valuation!$C$25)/(1+$C37)^2+(Valuation!$C$25)*(1+Valuation!$C$31)/(1+$C37)^3+(Valuation!$C$25)*(1+Valuation!$C$31)^2/(1+$C37)^4+(Valuation!$C$25)*(1+Valuation!$C$31)^3/(1+$C37)^5)+(Valuation!$C$25)*(1+Valuation!$C$31)^4*(1-Valuation!$C$34/Valuation!$C$32)/($C37-Valuation!$C$34)/(1+$C37)^5+Valuation!$C$41)/Inputs!$B$6-1)+Valuation!D8*(((1-((Valuation!$D$25)/(Valuation!$D$24)-1)/Valuation!$D$32)*(Valuation!$D$24)/(1+$C37)+(1-Valuation!$D$31/Valuation!$D$32)*((Valuation!$D$25)/(1+$C37)^2+(Valuation!$D$25)*(1+Valuation!$D$31)/(1+$C37)^3+(Valuation!$D$25)*(1+Valuation!$D$31)^2/(1+$C37)^4+(Valuation!$D$25)*(1+Valuation!$D$31)^3/(1+$C37)^5)+(Valuation!$D$25)*(1+Valuation!$D$31)^4*(1-Valuation!$D$34/Valuation!$D$32)/($C37-Valuation!$D$34)/(1+$C37)^5+Valuation!$D$41)/Inputs!$B$6-1)+Valuation!E8*(((1-((Valuation!$E$25)/(Valuation!$E$24)-1)/Valuation!$E$32)*(Valuation!$E$24)/(1+$C37)+(1-Valuation!$E$31/Valuation!$E$32)*((Valuation!$E$25)/(1+$C37)^2+(Valuation!$E$25)*(1+Valuation!$E$31)/(1+$C37)^3+(Valuation!$E$25)*(1+Valuation!$E$31)^2/(1+$C37)^4+(Valuation!$E$25)*(1+Valuation!$E$31)^3/(1+$C37)^5)+(Valuation!$E$25)*(1+Valuation!$E$31)^4*(1-Valuation!$E$34/Valuation!$E$32)/($C37-Valuation!$E$34)/(1+$C37)^5+Valuation!$E$41)/Inputs!$B$6-1)) -> 0.033257222
A38: Cost of equity (base) | B38: 0 | C38: =Inputs!$B$34+B38 -> 0.0974 | D38: =((1-((Valuation!$C$25)/(Valuation!$C$24)-1)/Valuation!$C$32)*(Valuation!$C$24)/(1+$C38)+(1-Valuation!$C$31/Valuation!$C$32)*((Valuation!$C$25)/(1+$C38)^2+(Valuation!$C$25)*(1+Valuation!$C$31)/(1+$C38)^3+(Valuation!$C$25)*(1+Valuation!$C$31)^2/(1+$C38)^4+(Valuation!$C$25)*(1+Valuation!$C$31)^3/(1+$C38)^5)+(Valuation!$C$25)*(1+Valuation!$C$31)^4*(1-Valuation!$C$34/Valuation!$C$32)/($C38-Valuation!$C$34)/(1+$C38)^5+Valuation!$C$41) -> 23.103869 | E38: =-(Valuation!B8*(((1-((Valuation!$B$25)/(Valuation!$B$24)-1)/Valuation!$B$32)*(Valuation!$B$24)/(1+$C38)+(1-Valuation!$B$31/Valuation!$B$32)*((Valuation!$B$25)/(1+$C38)^2+(Valuation!$B$25)*(1+Valuation!$B$31)/(1+$C38)^3+(Valuation!$B$25)*(1+Valuation!$B$31)^2/(1+$C38)^4+(Valuation!$B$25)*(1+Valuation!$B$31)^3/(1+$C38)^5)+(Valuation!$B$25)*(1+Valuation!$B$31)^4*(1-Valuation!$B$34/Valuation!$B$32)/($C38-Valuation!$B$34)/(1+$C38)^5+Valuation!$B$41)/Inputs!$B$6-1)+Valuation!C8*(((1-((Valuation!$C$25)/(Valuation!$C$24)-1)/Valuation!$C$32)*(Valuation!$C$24)/(1+$C38)+(1-Valuation!$C$31/Valuation!$C$32)*((Valuation!$C$25)/(1+$C38)^2+(Valuation!$C$25)*(1+Valuation!$C$31)/(1+$C38)^3+(Valuation!$C$25)*(1+Valuation!$C$31)^2/(1+$C38)^4+(Valuation!$C$25)*(1+Valuation!$C$31)^3/(1+$C38)^5)+(Valuation!$C$25)*(1+Valuation!$C$31)^4*(1-Valuation!$C$34/Valuation!$C$32)/($C38-Valuation!$C$34)/(1+$C38)^5+Valuation!$C$41)/Inputs!$B$6-1)+Valuation!D8*(((1-((Valuation!$D$25)/(Valuation!$D$24)-1)/Valuation!$D$32)*(Valuation!$D$24)/(1+$C38)+(1-Valuation!$D$31/Valuation!$D$32)*((Valuation!$D$25)/(1+$C38)^2+(Valuation!$D$25)*(1+Valuation!$D$31)/(1+$C38)^3+(Valuation!$D$25)*(1+Valuation!$D$31)^2/(1+$C38)^4+(Valuation!$D$25)*(1+Valuation!$D$31)^3/(1+$C38)^5)+(Valuation!$D$25)*(1+Valuation!$D$31)^4*(1-Valuation!$D$34/Valuation!$D$32)/($C38-Valuation!$D$34)/(1+$C38)^5+Valuation!$D$41)/Inputs!$B$6-1)+Valuation!E8*(((1-((Valuation!$E$25)/(Valuation!$E$24)-1)/Valuation!$E$32)*(Valuation!$E$24)/(1+$C38)+(1-Valuation!$E$31/Valuation!$E$32)*((Valuation!$E$25)/(1+$C38)^2+(Valuation!$E$25)*(1+Valuation!$E$31)/(1+$C38)^3+(Valuation!$E$25)*(1+Valuation!$E$31)^2/(1+$C38)^4+(Valuation!$E$25)*(1+Valuation!$E$31)^3/(1+$C38)^5)+(Valuation!$E$25)*(1+Valuation!$E$31)^4*(1-Valuation!$E$34/Valuation!$E$32)/($C38-Valuation!$E$34)/(1+$C38)^5+Valuation!$E$41)/Inputs!$B$6-1)) -> 0.10164201
A39: Cost of equity +0.5pt | B39: 0.005 | C39: =Inputs!$B$34+B39 -> 0.1024 | D39: =((1-((Valuation!$C$25)/(Valuation!$C$24)-1)/Valuation!$C$32)*(Valuation!$C$24)/(1+$C39)+(1-Valuation!$C$31/Valuation!$C$32)*((Valuation!$C$25)/(1+$C39)^2+(Valuation!$C$25)*(1+Valuation!$C$31)/(1+$C39)^3+(Valuation!$C$25)*(1+Valuation!$C$31)^2/(1+$C39)^4+(Valuation!$C$25)*(1+Valuation!$C$31)^3/(1+$C39)^5)+(Valuation!$C$25)*(1+Valuation!$C$31)^4*(1-Valuation!$C$34/Valuation!$C$32)/($C39-Valuation!$C$34)/(1+$C39)^5+Valuation!$C$41) -> 21.617298 | E39: =-(Valuation!B8*(((1-((Valuation!$B$25)/(Valuation!$B$24)-1)/Valuation!$B$32)*(Valuation!$B$24)/(1+$C39)+(1-Valuation!$B$31/Valuation!$B$32)*((Valuation!$B$25)/(1+$C39)^2+(Valuation!$B$25)*(1+Valuation!$B$31)/(1+$C39)^3+(Valuation!$B$25)*(1+Valuation!$B$31)^2/(1+$C39)^4+(Valuation!$B$25)*(1+Valuation!$B$31)^3/(1+$C39)^5)+(Valuation!$B$25)*(1+Valuation!$B$31)^4*(1-Valuation!$B$34/Valuation!$B$32)/($C39-Valuation!$B$34)/(1+$C39)^5+Valuation!$B$41)/Inputs!$B$6-1)+Valuation!C8*(((1-((Valuation!$C$25)/(Valuation!$C$24)-1)/Valuation!$C$32)*(Valuation!$C$24)/(1+$C39)+(1-Valuation!$C$31/Valuation!$C$32)*((Valuation!$C$25)/(1+$C39)^2+(Valuation!$C$25)*(1+Valuation!$C$31)/(1+$C39)^3+(Valuation!$C$25)*(1+Valuation!$C$31)^2/(1+$C39)^4+(Valuation!$C$25)*(1+Valuation!$C$31)^3/(1+$C39)^5)+(Valuation!$C$25)*(1+Valuation!$C$31)^4*(1-Valuation!$C$34/Valuation!$C$32)/($C39-Valuation!$C$34)/(1+$C39)^5+Valuation!$C$41)/Inputs!$B$6-1)+Valuation!D8*(((1-((Valuation!$D$25)/(Valuation!$D$24)-1)/Valuation!$D$32)*(Valuation!$D$24)/(1+$C39)+(1-Valuation!$D$31/Valuation!$D$32)*((Valuation!$D$25)/(1+$C39)^2+(Valuation!$D$25)*(1+Valuation!$D$31)/(1+$C39)^3+(Valuation!$D$25)*(1+Valuation!$D$31)^2/(1+$C39)^4+(Valuation!$D$25)*(1+Valuation!$D$31)^3/(1+$C39)^5)+(Valuation!$D$25)*(1+Valuation!$D$31)^4*(1-Valuation!$D$34/Valuation!$D$32)/($C39-Valuation!$D$34)/(1+$C39)^5+Valuation!$D$41)/Inputs!$B$6-1)+Valuation!E8*(((1-((Valuation!$E$25)/(Valuation!$E$24)-1)/Valuation!$E$32)*(Valuation!$E$24)/(1+$C39)+(1-Valuation!$E$31/Valuation!$E$32)*((Valuation!$E$25)/(1+$C39)^2+(Valuation!$E$25)*(1+Valuation!$E$31)/(1+$C39)^3+(Valuation!$E$25)*(1+Valuation!$E$31)^2/(1+$C39)^4+(Valuation!$E$25)*(1+Valuation!$E$31)^3/(1+$C39)^5)+(Valuation!$E$25)*(1+Valuation!$E$31)^4*(1-Valuation!$E$34/Valuation!$E$32)/($C39-Valuation!$E$34)/(1+$C39)^5+Valuation!$E$41)/Inputs!$B$6-1)) -> 0.16046904
A40: Cost of equity +1.0pt | B40: 0.01 | C40: =Inputs!$B$34+B40 -> 0.1074 | D40: =((1-((Valuation!$C$25)/(Valuation!$C$24)-1)/Valuation!$C$32)*(Valuation!$C$24)/(1+$C40)+(1-Valuation!$C$31/Valuation!$C$32)*((Valuation!$C$25)/(1+$C40)^2+(Valuation!$C$25)*(1+Valuation!$C$31)/(1+$C40)^3+(Valuation!$C$25)*(1+Valuation!$C$31)^2/(1+$C40)^4+(Valuation!$C$25)*(1+Valuation!$C$31)^3/(1+$C40)^5)+(Valuation!$C$25)*(1+Valuation!$C$31)^4*(1-Valuation!$C$34/Valuation!$C$32)/($C40-Valuation!$C$34)/(1+$C40)^5+Valuation!$C$41) -> 20.325041 | E40: =-(Valuation!B8*(((1-((Valuation!$B$25)/(Valuation!$B$24)-1)/Valuation!$B$32)*(Valuation!$B$24)/(1+$C40)+(1-Valuation!$B$31/Valuation!$B$32)*((Valuation!$B$25)/(1+$C40)^2+(Valuation!$B$25)*(1+Valuation!$B$31)/(1+$C40)^3+(Valuation!$B$25)*(1+Valuation!$B$31)^2/(1+$C40)^4+(Valuation!$B$25)*(1+Valuation!$B$31)^3/(1+$C40)^5)+(Valuation!$B$25)*(1+Valuation!$B$31)^4*(1-Valuation!$B$34/Valuation!$B$32)/($C40-Valuation!$B$34)/(1+$C40)^5+Valuation!$B$41)/Inputs!$B$6-1)+Valuation!C8*(((1-((Valuation!$C$25)/(Valuation!$C$24)-1)/Valuation!$C$32)*(Valuation!$C$24)/(1+$C40)+(1-Valuation!$C$31/Valuation!$C$32)*((Valuation!$C$25)/(1+$C40)^2+(Valuation!$C$25)*(1+Valuation!$C$31)/(1+$C40)^3+(Valuation!$C$25)*(1+Valuation!$C$31)^2/(1+$C40)^4+(Valuation!$C$25)*(1+Valuation!$C$31)^3/(1+$C40)^5)+(Valuation!$C$25)*(1+Valuation!$C$31)^4*(1-Valuation!$C$34/Valuation!$C$32)/($C40-Valuation!$C$34)/(1+$C40)^5+Valuation!$C$41)/Inputs!$B$6-1)+Valuation!D8*(((1-((Valuation!$D$25)/(Valuation!$D$24)-1)/Valuation!$D$32)*(Valuation!$D$24)/(1+$C40)+(1-Valuation!$D$31/Valuation!$D$32)*((Valuation!$D$25)/(1+$C40)^2+(Valuation!$D$25)*(1+Valuation!$D$31)/(1+$C40)^3+(Valuation!$D$25)*(1+Valuation!$D$31)^2/(1+$C40)^4+(Valuation!$D$25)*(1+Valuation!$D$31)^3/(1+$C40)^5)+(Valuation!$D$25)*(1+Valuation!$D$31)^4*(1-Valuation!$D$34/Valuation!$D$32)/($C40-Valuation!$D$34)/(1+$C40)^5+Valuation!$D$41)/Inputs!$B$6-1)+Valuation!E8*(((1-((Valuation!$E$25)/(Valuation!$E$24)-1)/Valuation!$E$32)*(Valuation!$E$24)/(1+$C40)+(1-Valuation!$E$31/Valuation!$E$32)*((Valuation!$E$25)/(1+$C40)^2+(Valuation!$E$25)*(1+Valuation!$E$31)/(1+$C40)^3+(Valuation!$E$25)*(1+Valuation!$E$31)^2/(1+$C40)^4+(Valuation!$E$25)*(1+Valuation!$E$31)^3/(1+$C40)^5)+(Valuation!$E$25)*(1+Valuation!$E$31)^4*(1-Valuation!$E$34/Valuation!$E$32)/($C40-Valuation!$E$34)/(1+$C40)^5+Valuation!$E$41)/Inputs!$B$6-1)) -> 0.21159359
A42: FY28 ACV EPS contribution (applied to all worlds)
A43: FY28 ACV contribution ($/sh) | B43: −$0.04 | C43: $0.00 | D43: +$0.02 | E43: +$0.04
A44: W2 FY28 EPS incl. ACV ($/sh) | B44: =Valuation!$C$12+-0.04 -> 1.5705834 | C44: =Valuation!$C$12+0 -> 1.6105834 | D44: =Valuation!$C$12+0.02 -> 1.6305834 | E44: =Valuation!$C$12+0.04 -> 1.6505834
A45: Base-case (W2) value ($/sh) | B45: =((1-((Valuation!$C$25+(-0.04-Valuation!$C$13)/2*(2+Valuation!$C$31))/(Valuation!$C$24+(-0.04-Valuation!$C$13)/2)-1)/Valuation!$C$32)*(Valuation!$C$24+(-0.04-Valuation!$C$13)/2)/(1+Valuation!$C$33)+(1-Valuation!$C$31/Valuation!$C$32)*((Valuation!$C$25+(-0.04-Valuation!$C$13)/2*(2+Valuation!$C$31))/(1+Valuation!$C$33)^2+(Valuation!$C$25+(-0.04-Valuation!$C$13)/2*(2+Valuation!$C$31))*(1+Valuation!$C$31)/(1+Valuation!$C$33)^3+(Valuation!$C$25+(-0.04-Valuation!$C$13)/2*(2+Valuation!$C$31))*(1+Valuation!$C$31)^2/(1+Valuation!$C$33)^4+(Valuation!$C$25+(-0.04-Valuation!$C$13)/2*(2+Valuation!$C$31))*(1+Valuation!$C$31)^3/(1+Valuation!$C$33)^5)+(Valuation!$C$25+(-0.04-Valuation!$C$13)/2*(2+Valuation!$C$31))*(1+Valuation!$C$31)^4*(1-Valuation!$C$34/Valuation!$C$32)/(Valuation!$C$33-Valuation!$C$34)/(1+Valuation!$C$33)^5+Valuation!$C$41) -> 22.466688 | C45: =((1-((Valuation!$C$25+(0-Valuation!$C$13)/2*(2+Valuation!$C$31))/(Valuation!$C$24+(0-Valuation!$C$13)/2)-1)/Valuation!$C$32)*(Valuation!$C$24+(0-Valuation!$C$13)/2)/(1+Valuation!$C$33)+(1-Valuation!$C$31/Valuation!$C$32)*((Valuation!$C$25+(0-Valuation!$C$13)/2*(2+Valuation!$C$31))/(1+Valuation!$C$33)^2+(Valuation!$C$25+(0-Valuation!$C$13)/2*(2+Valuation!$C$31))*(1+Valuation!$C$31)/(1+Valuation!$C$33)^3+(Valuation!$C$25+(0-Valuation!$C$13)/2*(2+Valuation!$C$31))*(1+Valuation!$C$31)^2/(1+Valuation!$C$33)^4+(Valuation!$C$25+(0-Valuation!$C$13)/2*(2+Valuation!$C$31))*(1+Valuation!$C$31)^3/(1+Valuation!$C$33)^5)+(Valuation!$C$25+(0-Valuation!$C$13)/2*(2+Valuation!$C$31))*(1+Valuation!$C$31)^4*(1-Valuation!$C$34/Valuation!$C$32)/(Valuation!$C$33-Valuation!$C$34)/(1+Valuation!$C$33)^5+Valuation!$C$41) -> 22.891475 | D45: =((1-((Valuation!$C$25+(0.02-Valuation!$C$13)/2*(2+Valuation!$C$31))/(Valuation!$C$24+(0.02-Valuation!$C$13)/2)-1)/Valuation!$C$32)*(Valuation!$C$24+(0.02-Valuation!$C$13)/2)/(1+Valuation!$C$33)+(1-Valuation!$C$31/Valuation!$C$32)*((Valuation!$C$25+(0.02-Valuation!$C$13)/2*(2+Valuation!$C$31))/(1+Valuation!$C$33)^2+(Valuation!$C$25+(0.02-Valuation!$C$13)/2*(2+Valuation!$C$31))*(1+Valuation!$C$31)/(1+Valuation!$C$33)^3+(Valuation!$C$25+(0.02-Valuation!$C$13)/2*(2+Valuation!$C$31))*(1+Valuation!$C$31)^2/(1+Valuation!$C$33)^4+(Valuation!$C$25+(0.02-Valuation!$C$13)/2*(2+Valuation!$C$31))*(1+Valuation!$C$31)^3/(1+Valuation!$C$33)^5)+(Valuation!$C$25+(0.02-Valuation!$C$13)/2*(2+Valuation!$C$31))*(1+Valuation!$C$31)^4*(1-Valuation!$C$34/Valuation!$C$32)/(Valuation!$C$33-Valuation!$C$34)/(1+Valuation!$C$33)^5+Valuation!$C$41) -> 23.103869 | E45: =((1-((Valuation!$C$25+(0.04-Valuation!$C$13)/2*(2+Valuation!$C$31))/(Valuation!$C$24+(0.04-Valuation!$C$13)/2)-1)/Valuation!$C$32)*(Valuation!$C$24+(0.04-Valuation!$C$13)/2)/(1+Valuation!$C$33)+(1-Valuation!$C$31/Valuation!$C$32)*((Valuation!$C$25+(0.04-Valuation!$C$13)/2*(2+Valuation!$C$31))/(1+Valuation!$C$33)^2+(Valuation!$C$25+(0.04-Valuation!$C$13)/2*(2+Valuation!$C$31))*(1+Valuation!$C$31)/(1+Valuation!$C$33)^3+(Valuation!$C$25+(0.04-Valuation!$C$13)/2*(2+Valuation!$C$31))*(1+Valuation!$C$31)^2/(1+Valuation!$C$33)^4+(Valuation!$C$25+(0.04-Valuation!$C$13)/2*(2+Valuation!$C$31))*(1+Valuation!$C$31)^3/(1+Valuation!$C$33)^5)+(Valuation!$C$25+(0.04-Valuation!$C$13)/2*(2+Valuation!$C$31))*(1+Valuation!$C$31)^4*(1-Valuation!$C$34/Valuation!$C$32)/(Valuation!$C$33-Valuation!$C$34)/(1+Valuation!$C$33)^5+Valuation!$C$41) -> 23.316262
A46: Expected short return | B46: =-(Valuation!B8*(((1-((Valuation!$B$25+(-0.04-Valuation!$B$13)/2*(2+Valuation!$B$31))/(Valuation!$B$24+(-0.04-Valuation!$B$13)/2)-1)/Valuation!$B$32)*(Valuation!$B$24+(-0.04-Valuation!$B$13)/2)/(1+Valuation!$B$33)+(1-Valuation!$B$31/Valuation!$B$32)*((Valuation!$B$25+(-0.04-Valuation!$B$13)/2*(2+Valuation!$B$31))/(1+Valuation!$B$33)^2+(Valuation!$B$25+(-0.04-Valuation!$B$13)/2*(2+Valuation!$B$31))*(1+Valuation!$B$31)/(1+Valuation!$B$33)^3+(Valuation!$B$25+(-0.04-Valuation!$B$13)/2*(2+Valuation!$B$31))*(1+Valuation!$B$31)^2/(1+Valuation!$B$33)^4+(Valuation!$B$25+(-0.04-Valuation!$B$13)/2*(2+Valuation!$B$31))*(1+Valuation!$B$31)^3/(1+Valuation!$B$33)^5)+(Valuation!$B$25+(-0.04-Valuation!$B$13)/2*(2+Valuation!$B$31))*(1+Valuation!$B$31)^4*(1-Valuation!$B$34/Valuation!$B$32)/(Valuation!$B$33-Valuation!$B$34)/(1+Valuation!$B$33)^5+Valuation!$B$41)/Inputs!$B$6-1)+Valuation!C8*(((1-((Valuation!$C$25+(-0.04-Valuation!$C$13)/2*(2+Valuation!$C$31))/(Valuation!$C$24+(-0.04-Valuation!$C$13)/2)-1)/Valuation!$C$32)*(Valuation!$C$24+(-0.04-Valuation!$C$13)/2)/(1+Valuation!$C$33)+(1-Valuation!$C$31/Valuation!$C$32)*((Valuation!$C$25+(-0.04-Valuation!$C$13)/2*(2+Valuation!$C$31))/(1+Valuation!$C$33)^2+(Valuation!$C$25+(-0.04-Valuation!$C$13)/2*(2+Valuation!$C$31))*(1+Valuation!$C$31)/(1+Valuation!$C$33)^3+(Valuation!$C$25+(-0.04-Valuation!$C$13)/2*(2+Valuation!$C$31))*(1+Valuation!$C$31)^2/(1+Valuation!$C$33)^4+(Valuation!$C$25+(-0.04-Valuation!$C$13)/2*(2+Valuation!$C$31))*(1+Valuation!$C$31)^3/(1+Valuation!$C$33)^5)+(Valuation!$C$25+(-0.04-Valuation!$C$13)/2*(2+Valuation!$C$31))*(1+Valuation!$C$31)^4*(1-Valuation!$C$34/Valuation!$C$32)/(Valuation!$C$33-Valuation!$C$34)/(1+Valuation!$C$33)^5+Valuation!$C$41)/Inputs!$B$6-1)+Valuation!D8*(((1-((Valuation!$D$25+(-0.04-Valuation!$D$13)/2*(2+Valuation!$D$31))/(Valuation!$D$24+(-0.04-Valuation!$D$13)/2)-1)/Valuation!$D$32)*(Valuation!$D$24+(-0.04-Valuation!$D$13)/2)/(1+Valuation!$D$33)+(1-Valuation!$D$31/Valuation!$D$32)*((Valuation!$D$25+(-0.04-Valuation!$D$13)/2*(2+Valuation!$D$31))/(1+Valuation!$D$33)^2+(Valuation!$D$25+(-0.04-Valuation!$D$13)/2*(2+Valuation!$D$31))*(1+Valuation!$D$31)/(1+Valuation!$D$33)^3+(Valuation!$D$25+(-0.04-Valuation!$D$13)/2*(2+Valuation!$D$31))*(1+Valuation!$D$31)^2/(1+Valuation!$D$33)^4+(Valuation!$D$25+(-0.04-Valuation!$D$13)/2*(2+Valuation!$D$31))*(1+Valuation!$D$31)^3/(1+Valuation!$D$33)^5)+(Valuation!$D$25+(-0.04-Valuation!$D$13)/2*(2+Valuation!$D$31))*(1+Valuation!$D$31)^4*(1-Valuation!$D$34/Valuation!$D$32)/(Valuation!$D$33-Valuation!$D$34)/(1+Valuation!$D$33)^5+Valuation!$D$41)/Inputs!$B$6-1)+Valuation!E8*(((1-((Valuation!$E$25+(-0.04-Valuation!$E$13)/2*(2+Valuation!$E$31))/(Valuation!$E$24+(-0.04-Valuation!$E$13)/2)-1)/Valuation!$E$32)*(Valuation!$E$24+(-0.04-Valuation!$E$13)/2)/(1+Valuation!$E$33)+(1-Valuation!$E$31/Valuation!$E$32)*((Valuation!$E$25+(-0.04-Valuation!$E$13)/2*(2+Valuation!$E$31))/(1+Valuation!$E$33)^2+(Valuation!$E$25+(-0.04-Valuation!$E$13)/2*(2+Valuation!$E$31))*(1+Valuation!$E$31)/(1+Valuation!$E$33)^3+(Valuation!$E$25+(-0.04-Valuation!$E$13)/2*(2+Valuation!$E$31))*(1+Valuation!$E$31)^2/(1+Valuation!$E$33)^4+(Valuation!$E$25+(-0.04-Valuation!$E$13)/2*(2+Valuation!$E$31))*(1+Valuation!$E$31)^3/(1+Valuation!$E$33)^5)+(Valuation!$E$25+(-0.04-Valuation!$E$13)/2*(2+Valuation!$E$31))*(1+Valuation!$E$31)^4*(1-Valuation!$E$34/Valuation!$E$32)/(Valuation!$E$33-Valuation!$E$34)/(1+Valuation!$E$33)^5+Valuation!$E$41)/Inputs!$B$6-1)) -> 0.12641071 | C46: =-(Valuation!B8*(((1-((Valuation!$B$25+(0-Valuation!$B$13)/2*(2+Valuation!$B$31))/(Valuation!$B$24+(0-Valuation!$B$13)/2)-1)/Valuation!$B$32)*(Valuation!$B$24+(0-Valuation!$B$13)/2)/(1+Valuation!$B$33)+(1-Valuation!$B$31/Valuation!$B$32)*((Valuation!$B$25+(0-Valuation!$B$13)/2*(2+Valuation!$B$31))/(1+Valuation!$B$33)^2+(Valuation!$B$25+(0-Valuation!$B$13)/2*(2+Valuation!$B$31))*(1+Valuation!$B$31)/(1+Valuation!$B$33)^3+(Valuation!$B$25+(0-Valuation!$B$13)/2*(2+Valuation!$B$31))*(1+Valuation!$B$31)^2/(1+Valuation!$B$33)^4+(Valuation!$B$25+(0-Valuation!$B$13)/2*(2+Valuation!$B$31))*(1+Valuation!$B$31)^3/(1+Valuation!$B$33)^5)+(Valuation!$B$25+(0-Valuation!$B$13)/2*(2+Valuation!$B$31))*(1+Valuation!$B$31)^4*(1-Valuation!$B$34/Valuation!$B$32)/(Valuation!$B$33-Valuation!$B$34)/(1+Valuation!$B$33)^5+Valuation!$B$41)/Inputs!$B$6-1)+Valuation!C8*(((1-((Valuation!$C$25+(0-Valuation!$C$13)/2*(2+Valuation!$C$31))/(Valuation!$C$24+(0-Valuation!$C$13)/2)-1)/Valuation!$C$32)*(Valuation!$C$24+(0-Valuation!$C$13)/2)/(1+Valuation!$C$33)+(1-Valuation!$C$31/Valuation!$C$32)*((Valuation!$C$25+(0-Valuation!$C$13)/2*(2+Valuation!$C$31))/(1+Valuation!$C$33)^2+(Valuation!$C$25+(0-Valuation!$C$13)/2*(2+Valuation!$C$31))*(1+Valuation!$C$31)/(1+Valuation!$C$33)^3+(Valuation!$C$25+(0-Valuation!$C$13)/2*(2+Valuation!$C$31))*(1+Valuation!$C$31)^2/(1+Valuation!$C$33)^4+(Valuation!$C$25+(0-Valuation!$C$13)/2*(2+Valuation!$C$31))*(1+Valuation!$C$31)^3/(1+Valuation!$C$33)^5)+(Valuation!$C$25+(0-Valuation!$C$13)/2*(2+Valuation!$C$31))*(1+Valuation!$C$31)^4*(1-Valuation!$C$34/Valuation!$C$32)/(Valuation!$C$33-Valuation!$C$34)/(1+Valuation!$C$33)^5+Valuation!$C$41)/Inputs!$B$6-1)+Valuation!D8*(((1-((Valuation!$D$25+(0-Valuation!$D$13)/2*(2+Valuation!$D$31))/(Valuation!$D$24+(0-Valuation!$D$13)/2)-1)/Valuation!$D$32)*(Valuation!$D$24+(0-Valuation!$D$13)/2)/(1+Valuation!$D$33)+(1-Valuation!$D$31/Valuation!$D$32)*((Valuation!$D$25+(0-Valuation!$D$13)/2*(2+Valuation!$D$31))/(1+Valuation!$D$33)^2+(Valuation!$D$25+(0-Valuation!$D$13)/2*(2+Valuation!$D$31))*(1+Valuation!$D$31)/(1+Valuation!$D$33)^3+(Valuation!$D$25+(0-Valuation!$D$13)/2*(2+Valuation!$D$31))*(1+Valuation!$D$31)^2/(1+Valuation!$D$33)^4+(Valuation!$D$25+(0-Valuation!$D$13)/2*(2+Valuation!$D$31))*(1+Valuation!$D$31)^3/(1+Valuation!$D$33)^5)+(Valuation!$D$25+(0-Valuation!$D$13)/2*(2+Valuation!$D$31))*(1+Valuation!$D$31)^4*(1-Valuation!$D$34/Valuation!$D$32)/(Valuation!$D$33-Valuation!$D$34)/(1+Valuation!$D$33)^5+Valuation!$D$41)/Inputs!$B$6-1)+Valuation!E8*(((1-((Valuation!$E$25+(0-Valuation!$E$13)/2*(2+Valuation!$E$31))/(Valuation!$E$24+(0-Valuation!$E$13)/2)-1)/Valuation!$E$32)*(Valuation!$E$24+(0-Valuation!$E$13)/2)/(1+Valuation!$E$33)+(1-Valuation!$E$31/Valuation!$E$32)*((Valuation!$E$25+(0-Valuation!$E$13)/2*(2+Valuation!$E$31))/(1+Valuation!$E$33)^2+(Valuation!$E$25+(0-Valuation!$E$13)/2*(2+Valuation!$E$31))*(1+Valuation!$E$31)/(1+Valuation!$E$33)^3+(Valuation!$E$25+(0-Valuation!$E$13)/2*(2+Valuation!$E$31))*(1+Valuation!$E$31)^2/(1+Valuation!$E$33)^4+(Valuation!$E$25+(0-Valuation!$E$13)/2*(2+Valuation!$E$31))*(1+Valuation!$E$31)^3/(1+Valuation!$E$33)^5)+(Valuation!$E$25+(0-Valuation!$E$13)/2*(2+Valuation!$E$31))*(1+Valuation!$E$31)^4*(1-Valuation!$E$34/Valuation!$E$32)/(Valuation!$E$33-Valuation!$E$34)/(1+Valuation!$E$33)^5+Valuation!$E$41)/Inputs!$B$6-1)) -> 0.11033444 | D46: =-(Valuation!B8*(((1-((Valuation!$B$25+(0.02-Valuation!$B$13)/2*(2+Valuation!$B$31))/(Valuation!$B$24+(0.02-Valuation!$B$13)/2)-1)/Valuation!$B$32)*(Valuation!$B$24+(0.02-Valuation!$B$13)/2)/(1+Valuation!$B$33)+(1-Valuation!$B$31/Valuation!$B$32)*((Valuation!$B$25+(0.02-Valuation!$B$13)/2*(2+Valuation!$B$31))/(1+Valuation!$B$33)^2+(Valuation!$B$25+(0.02-Valuation!$B$13)/2*(2+Valuation!$B$31))*(1+Valuation!$B$31)/(1+Valuation!$B$33)^3+(Valuation!$B$25+(0.02-Valuation!$B$13)/2*(2+Valuation!$B$31))*(1+Valuation!$B$31)^2/(1+Valuation!$B$33)^4+(Valuation!$B$25+(0.02-Valuation!$B$13)/2*(2+Valuation!$B$31))*(1+Valuation!$B$31)^3/(1+Valuation!$B$33)^5)+(Valuation!$B$25+(0.02-Valuation!$B$13)/2*(2+Valuation!$B$31))*(1+Valuation!$B$31)^4*(1-Valuation!$B$34/Valuation!$B$32)/(Valuation!$B$33-Valuation!$B$34)/(1+Valuation!$B$33)^5+Valuation!$B$41)/Inputs!$B$6-1)+Valuation!C8*(((1-((Valuation!$C$25+(0.02-Valuation!$C$13)/2*(2+Valuation!$C$31))/(Valuation!$C$24+(0.02-Valuation!$C$13)/2)-1)/Valuation!$C$32)*(Valuation!$C$24+(0.02-Valuation!$C$13)/2)/(1+Valuation!$C$33)+(1-Valuation!$C$31/Valuation!$C$32)*((Valuation!$C$25+(0.02-Valuation!$C$13)/2*(2+Valuation!$C$31))/(1+Valuation!$C$33)^2+(Valuation!$C$25+(0.02-Valuation!$C$13)/2*(2+Valuation!$C$31))*(1+Valuation!$C$31)/(1+Valuation!$C$33)^3+(Valuation!$C$25+(0.02-Valuation!$C$13)/2*(2+Valuation!$C$31))*(1+Valuation!$C$31)^2/(1+Valuation!$C$33)^4+(Valuation!$C$25+(0.02-Valuation!$C$13)/2*(2+Valuation!$C$31))*(1+Valuation!$C$31)^3/(1+Valuation!$C$33)^5)+(Valuation!$C$25+(0.02-Valuation!$C$13)/2*(2+Valuation!$C$31))*(1+Valuation!$C$31)^4*(1-Valuation!$C$34/Valuation!$C$32)/(Valuation!$C$33-Valuation!$C$34)/(1+Valuation!$C$33)^5+Valuation!$C$41)/Inputs!$B$6-1)+Valuation!D8*(((1-((Valuation!$D$25+(0.02-Valuation!$D$13)/2*(2+Valuation!$D$31))/(Valuation!$D$24+(0.02-Valuation!$D$13)/2)-1)/Valuation!$D$32)*(Valuation!$D$24+(0.02-Valuation!$D$13)/2)/(1+Valuation!$D$33)+(1-Valuation!$D$31/Valuation!$D$32)*((Valuation!$D$25+(0.02-Valuation!$D$13)/2*(2+Valuation!$D$31))/(1+Valuation!$D$33)^2+(Valuation!$D$25+(0.02-Valuation!$D$13)/2*(2+Valuation!$D$31))*(1+Valuation!$D$31)/(1+Valuation!$D$33)^3+(Valuation!$D$25+(0.02-Valuation!$D$13)/2*(2+Valuation!$D$31))*(1+Valuation!$D$31)^2/(1+Valuation!$D$33)^4+(Valuation!$D$25+(0.02-Valuation!$D$13)/2*(2+Valuation!$D$31))*(1+Valuation!$D$31)^3/(1+Valuation!$D$33)^5)+(Valuation!$D$25+(0.02-Valuation!$D$13)/2*(2+Valuation!$D$31))*(1+Valuation!$D$31)^4*(1-Valuation!$D$34/Valuation!$D$32)/(Valuation!$D$33-Valuation!$D$34)/(1+Valuation!$D$33)^5+Valuation!$D$41)/Inputs!$B$6-1)+Valuation!E8*(((1-((Valuation!$E$25+(0.02-Valuation!$E$13)/2*(2+Valuation!$E$31))/(Valuation!$E$24+(0.02-Valuation!$E$13)/2)-1)/Valuation!$E$32)*(Valuation!$E$24+(0.02-Valuation!$E$13)/2)/(1+Valuation!$E$33)+(1-Valuation!$E$31/Valuation!$E$32)*((Valuation!$E$25+(0.02-Valuation!$E$13)/2*(2+Valuation!$E$31))/(1+Valuation!$E$33)^2+(Valuation!$E$25+(0.02-Valuation!$E$13)/2*(2+Valuation!$E$31))*(1+Valuation!$E$31)/(1+Valuation!$E$33)^3+(Valuation!$E$25+(0.02-Valuation!$E$13)/2*(2+Valuation!$E$31))*(1+Valuation!$E$31)^2/(1+Valuation!$E$33)^4+(Valuation!$E$25+(0.02-Valuation!$E$13)/2*(2+Valuation!$E$31))*(1+Valuation!$E$31)^3/(1+Valuation!$E$33)^5)+(Valuation!$E$25+(0.02-Valuation!$E$13)/2*(2+Valuation!$E$31))*(1+Valuation!$E$31)^4*(1-Valuation!$E$34/Valuation!$E$32)/(Valuation!$E$33-Valuation!$E$34)/(1+Valuation!$E$33)^5+Valuation!$E$41)/Inputs!$B$6-1)) -> 0.1022963 | E46: =-(Valuation!B8*(((1-((Valuation!$B$25+(0.04-Valuation!$B$13)/2*(2+Valuation!$B$31))/(Valuation!$B$24+(0.04-Valuation!$B$13)/2)-1)/Valuation!$B$32)*(Valuation!$B$24+(0.04-Valuation!$B$13)/2)/(1+Valuation!$B$33)+(1-Valuation!$B$31/Valuation!$B$32)*((Valuation!$B$25+(0.04-Valuation!$B$13)/2*(2+Valuation!$B$31))/(1+Valuation!$B$33)^2+(Valuation!$B$25+(0.04-Valuation!$B$13)/2*(2+Valuation!$B$31))*(1+Valuation!$B$31)/(1+Valuation!$B$33)^3+(Valuation!$B$25+(0.04-Valuation!$B$13)/2*(2+Valuation!$B$31))*(1+Valuation!$B$31)^2/(1+Valuation!$B$33)^4+(Valuation!$B$25+(0.04-Valuation!$B$13)/2*(2+Valuation!$B$31))*(1+Valuation!$B$31)^3/(1+Valuation!$B$33)^5)+(Valuation!$B$25+(0.04-Valuation!$B$13)/2*(2+Valuation!$B$31))*(1+Valuation!$B$31)^4*(1-Valuation!$B$34/Valuation!$B$32)/(Valuation!$B$33-Valuation!$B$34)/(1+Valuation!$B$33)^5+Valuation!$B$41)/Inputs!$B$6-1)+Valuation!C8*(((1-((Valuation!$C$25+(0.04-Valuation!$C$13)/2*(2+Valuation!$C$31))/(Valuation!$C$24+(0.04-Valuation!$C$13)/2)-1)/Valuation!$C$32)*(Valuation!$C$24+(0.04-Valuation!$C$13)/2)/(1+Valuation!$C$33)+(1-Valuation!$C$31/Valuation!$C$32)*((Valuation!$C$25+(0.04-Valuation!$C$13)/2*(2+Valuation!$C$31))/(1+Valuation!$C$33)^2+(Valuation!$C$25+(0.04-Valuation!$C$13)/2*(2+Valuation!$C$31))*(1+Valuation!$C$31)/(1+Valuation!$C$33)^3+(Valuation!$C$25+(0.04-Valuation!$C$13)/2*(2+Valuation!$C$31))*(1+Valuation!$C$31)^2/(1+Valuation!$C$33)^4+(Valuation!$C$25+(0.04-Valuation!$C$13)/2*(2+Valuation!$C$31))*(1+Valuation!$C$31)^3/(1+Valuation!$C$33)^5)+(Valuation!$C$25+(0.04-Valuation!$C$13)/2*(2+Valuation!$C$31))*(1+Valuation!$C$31)^4*(1-Valuation!$C$34/Valuation!$C$32)/(Valuation!$C$33-Valuation!$C$34)/(1+Valuation!$C$33)^5+Valuation!$C$41)/Inputs!$B$6-1)+Valuation!D8*(((1-((Valuation!$D$25+(0.04-Valuation!$D$13)/2*(2+Valuation!$D$31))/(Valuation!$D$24+(0.04-Valuation!$D$13)/2)-1)/Valuation!$D$32)*(Valuation!$D$24+(0.04-Valuation!$D$13)/2)/(1+Valuation!$D$33)+(1-Valuation!$D$31/Valuation!$D$32)*((Valuation!$D$25+(0.04-Valuation!$D$13)/2*(2+Valuation!$D$31))/(1+Valuation!$D$33)^2+(Valuation!$D$25+(0.04-Valuation!$D$13)/2*(2+Valuation!$D$31))*(1+Valuation!$D$31)/(1+Valuation!$D$33)^3+(Valuation!$D$25+(0.04-Valuation!$D$13)/2*(2+Valuation!$D$31))*(1+Valuation!$D$31)^2/(1+Valuation!$D$33)^4+(Valuation!$D$25+(0.04-Valuation!$D$13)/2*(2+Valuation!$D$31))*(1+Valuation!$D$31)^3/(1+Valuation!$D$33)^5)+(Valuation!$D$25+(0.04-Valuation!$D$13)/2*(2+Valuation!$D$31))*(1+Valuation!$D$31)^4*(1-Valuation!$D$34/Valuation!$D$32)/(Valuation!$D$33-Valuation!$D$34)/(1+Valuation!$D$33)^5+Valuation!$D$41)/Inputs!$B$6-1)+Valuation!E8*(((1-((Valuation!$E$25+(0.04-Valuation!$E$13)/2*(2+Valuation!$E$31))/(Valuation!$E$24+(0.04-Valuation!$E$13)/2)-1)/Valuation!$E$32)*(Valuation!$E$24+(0.04-Valuation!$E$13)/2)/(1+Valuation!$E$33)+(1-Valuation!$E$31/Valuation!$E$32)*((Valuation!$E$25+(0.04-Valuation!$E$13)/2*(2+Valuation!$E$31))/(1+Valuation!$E$33)^2+(Valuation!$E$25+(0.04-Valuation!$E$13)/2*(2+Valuation!$E$31))*(1+Valuation!$E$31)/(1+Valuation!$E$33)^3+(Valuation!$E$25+(0.04-Valuation!$E$13)/2*(2+Valuation!$E$31))*(1+Valuation!$E$31)^2/(1+Valuation!$E$33)^4+(Valuation!$E$25+(0.04-Valuation!$E$13)/2*(2+Valuation!$E$31))*(1+Valuation!$E$31)^3/(1+Valuation!$E$33)^5)+(Valuation!$E$25+(0.04-Valuation!$E$13)/2*(2+Valuation!$E$31))*(1+Valuation!$E$31)^4*(1-Valuation!$E$34/Valuation!$E$32)/(Valuation!$E$33-Valuation!$E$34)/(1+Valuation!$E$33)^5+Valuation!$E$41)/Inputs!$B$6-1)) -> 0.094258164
A47: FY28 ACV changes NTM through Q1-Q2 FY28 (half) and year 2 in full. Base: W1 $0.00, W2 +$0.02, W3 +$0.04, W4 +$0.02.
A49: ACV closing date (W2 FY27 GAAP EPS; ex-ACV thesis unaffected)
A50: Closing timing | B50: Share of Q2 consolidated | C50: FY27 GAAP EPS | D50: vs model base | E50: Value impact
A51: Early Q2 (~Nov 1, 2026) | B51: 1 | C51: =Valuation!$C$11+(B51-Inputs!$B$16)*((Scenarios!$C$11-Scenarios!$C$10)+(Scenarios!$C$12-Inputs!$B$12))*(1-Inputs!$B$8)/Inputs!$B$7 -> 1.369169 | D51: =C51-Valuation!$C$11 -> -0.013819742 | E51: None
A52: Mid Q2 (~Dec 15, 2026; model base) | B52: 0.5 | C52: =Valuation!$C$11+(B52-Inputs!$B$16)*((Scenarios!$C$11-Scenarios!$C$10)+(Scenarios!$C$12-Inputs!$B$12))*(1-Inputs!$B$8)/Inputs!$B$7 -> 1.3829887 | D52: =C52-Valuation!$C$11 -> 0 | E52: None
A53: Late Q2 / calendar year-end (~Dec 31, 2026) | B53: 0.33333333 | C53: =Valuation!$C$11+(B53-Inputs!$B$16)*((Scenarios!$C$11-Scenarios!$C$10)+(Scenarios!$C$12-Inputs!$B$12))*(1-Inputs!$B$8)/Inputs!$B$7 -> 1.3875953 | D53: =C53-Valuation!$C$11 -> 0.0046065808 | E53: None
A54: Model assumes closing during Q2 FY27; company guidance is close by calendar year-end 2026. Q3 onward is fully consolidated in all cases, so the mid-Feb valuation is unaffected.
A56: Probability shifts (scenario values unchanged)
A57: Probability set (W1 / W2 / W3 / W4) | B57: Expected short return | E57: Note
A58: Base 20 / 45 / 20 / 15 | B58: =-(0.2*Valuation!B43+0.45*Valuation!C43+0.2*Valuation!D43+0.15*Valuation!E43) -> 0.10164201 | E58: Governing
A59: Bearish tilt 30 / 45 / 15 / 10 | B59: =-(0.3*Valuation!B43+0.45*Valuation!C43+0.15*Valuation!D43+0.1*Valuation!E43) -> 0.15000887 | E59: More weight to loss broadening
A60: Bullish tilt 15 / 40 / 25 / 20 | B60: =-(0.15*Valuation!B43+0.4*Valuation!C43+0.25*Valuation!D43+0.2*Valuation!E43) -> 0.063833256 | E60: More weight to recovery
A62: Beta cross-check
A63: Item | B63: Cost of equity | C63: Base-case value | D63: Exp. short return | E63: Note
A64: Beta 1.03 (Yahoo, secondary) instead of 0.90 | B64: =Inputs!$B$29+1.03*Inputs!$B$31 -> 0.1039 | C64: =((1-((Valuation!$C$25)/(Valuation!$C$24)-1)/Valuation!$C$32)*(Valuation!$C$24)/(1+$B64)+(1-Valuation!$C$31/Valuation!$C$32)*((Valuation!$C$25)/(1+$B64)^2+(Valuation!$C$25)*(1+Valuation!$C$31)/(1+$B64)^3+(Valuation!$C$25)*(1+Valuation!$C$31)^2/(1+$B64)^4+(Valuation!$C$25)*(1+Valuation!$C$31)^3/(1+$B64)^5)+(Valuation!$C$25)*(1+Valuation!$C$31)^4*(1-Valuation!$C$34/Valuation!$C$32)/($B64-Valuation!$C$34)/(1+$B64)^5+Valuation!$C$41) -> 21.211015 | D64: =-(Valuation!B8*(((1-((Valuation!$B$25)/(Valuation!$B$24)-1)/Valuation!$B$32)*(Valuation!$B$24)/(1+$B64)+(1-Valuation!$B$31/Valuation!$B$32)*((Valuation!$B$25)/(1+$B64)^2+(Valuation!$B$25)*(1+Valuation!$B$31)/(1+$B64)^3+(Valuation!$B$25)*(1+Valuation!$B$31)^2/(1+$B64)^4+(Valuation!$B$25)*(1+Valuation!$B$31)^3/(1+$B64)^5)+(Valuation!$B$25)*(1+Valuation!$B$31)^4*(1-Valuation!$B$34/Valuation!$B$32)/($B64-Valuation!$B$34)/(1+$B64)^5+Valuation!$B$41)/Inputs!$B$6-1)+Valuation!C8*(((1-((Valuation!$C$25)/(Valuation!$C$24)-1)/Valuation!$C$32)*(Valuation!$C$24)/(1+$B64)+(1-Valuation!$C$31/Valuation!$C$32)*((Valuation!$C$25)/(1+$B64)^2+(Valuation!$C$25)*(1+Valuation!$C$31)/(1+$B64)^3+(Valuation!$C$25)*(1+Valuation!$C$31)^2/(1+$B64)^4+(Valuation!$C$25)*(1+Valuation!$C$31)^3/(1+$B64)^5)+(Valuation!$C$25)*(1+Valuation!$C$31)^4*(1-Valuation!$C$34/Valuation!$C$32)/($B64-Valuation!$C$34)/(1+$B64)^5+Valuation!$C$41)/Inputs!$B$6-1)+Valuation!D8*(((1-((Valuation!$D$25)/(Valuation!$D$24)-1)/Valuation!$D$32)*(Valuation!$D$24)/(1+$B64)+(1-Valuation!$D$31/Valuation!$D$32)*((Valuation!$D$25)/(1+$B64)^2+(Valuation!$D$25)*(1+Valuation!$D$31)/(1+$B64)^3+(Valuation!$D$25)*(1+Valuation!$D$31)^2/(1+$B64)^4+(Valuation!$D$25)*(1+Valuation!$D$31)^3/(1+$B64)^5)+(Valuation!$D$25)*(1+Valuation!$D$31)^4*(1-Valuation!$D$34/Valuation!$D$32)/($B64-Valuation!$D$34)/(1+$B64)^5+Valuation!$D$41)/Inputs!$B$6-1)+Valuation!E8*(((1-((Valuation!$E$25)/(Valuation!$E$24)-1)/Valuation!$E$32)*(Valuation!$E$24)/(1+$B64)+(1-Valuation!$E$31/Valuation!$E$32)*((Valuation!$E$25)/(1+$B64)^2+(Valuation!$E$25)*(1+Valuation!$E$31)/(1+$B64)^3+(Valuation!$E$25)*(1+Valuation!$E$31)^2/(1+$B64)^4+(Valuation!$E$25)*(1+Valuation!$E$31)^3/(1+$B64)^5)+(Valuation!$E$25)*(1+Valuation!$E$31)^4*(1-Valuation!$E$34/Valuation!$E$32)/($B64-Valuation!$E$34)/(1+$B64)^5+Valuation!$E$41)/Inputs!$B$6-1)) -> 0.17654389 | E64: Higher beta raises the cost of equity (short return rises)
A66: Downside reference (from Valuation)
A67: Item | B67: Value
A68: W4 adverse-case short loss | B68: =Valuation!$B$55 -> 0.14696287
A69: Rate-cut stress (10Y to 3.5%) short loss | B69: =Valuation!$B$65 -> 0.47072059
A71: W2 sensitivity engine: replay of EPS_Build W2 with the drivers in blue changed (feeds the tables above)
A72: Case | B72: Run-rate drag | C72: Fixed share | D72: Shares (m) | E72: Core Q1 | F72: Core Q2 | G72: Core Q3 | H72: Core Q4 | I72: Q1 EPS ex-ACV | J72: FY27 EPS ex-ACV | K72: NTM ex-int | L72: Year 2 ex-int | M72: Value ($/sh)
A73: Drag 10%, fixed 45% | B73: -0.1 | C73: 0.45 | D73: 932 | E73: =((Inputs!$B$47*(1+(Inputs!$B$39*(Scenarios!$C$6+((1+$B73)/(1-Inputs!$B$55)-1))+(1-Inputs!$B$39)*Inputs!$B$41))*(1+Scenarios!$C$8)+(Inputs!$B$48-Inputs!$B$50)*(1+Inputs!$B$42)-(Inputs!$B$49*$C73*(1+Scenarios!$C$9)+Inputs!$B$49*(1-$C73)*(1+(Inputs!$B$39*(Scenarios!$C$6+((1+$B73)/(1-Inputs!$B$55)-1))+(1-Inputs!$B$39)*Inputs!$B$41)))-Inputs!$B$51*(1+Inputs!$B$42))+Inputs!$B$52*(1+Inputs!$B$43))*(1-Inputs!$B$8)/$D73 -> 0.35299006 | F73: =((Inputs!$C$47*(1+(Inputs!$B$39*(Scenarios!$C$6+((1+$B73)/(1-Inputs!$C$55)-1))+(1-Inputs!$B$39)*Inputs!$B$41))*(1+Scenarios!$C$8)+(Inputs!$C$48-Inputs!$C$50)*(1+Inputs!$B$42)-(Inputs!$C$49*$C73*(1+Scenarios!$C$9)+Inputs!$C$49*(1-$C73)*(1+(Inputs!$B$39*(Scenarios!$C$6+((1+$B73)/(1-Inputs!$C$55)-1))+(1-Inputs!$B$39)*Inputs!$B$41)))-Inputs!$C$51*(1+Inputs!$B$42))+Inputs!$C$52*(1+Inputs!$B$43))*(1-Inputs!$B$8)/$D73 -> 0.31691934 | G73: =((Inputs!$D$47*(1+(Inputs!$B$39*(Scenarios!$C$6+((1+$B73)/(1-Inputs!$D$55)-1))+(1-Inputs!$B$39)*Inputs!$B$41))*(1+Scenarios!$C$8)+(Inputs!$D$48-Inputs!$D$50)*(1+Inputs!$B$42)-(Inputs!$D$49*$C73*(1+Scenarios!$C$9)+Inputs!$D$49*(1-$C73)*(1+(Inputs!$B$39*(Scenarios!$C$6+((1+$B73)/(1-Inputs!$D$55)-1))+(1-Inputs!$B$39)*Inputs!$B$41)))-Inputs!$D$51*(1+Inputs!$B$42))+Inputs!$D$52*(1+Inputs!$B$43))*(1-Inputs!$B$8)/$D73 -> 0.38258341 | H73: =((Inputs!$E$47*(1+(Inputs!$B$39*(Scenarios!$C$6+((1+$B73)/(1-Inputs!$E$55)-1))+(1-Inputs!$B$39)*Inputs!$B$41))*(1+Scenarios!$C$8)+(Inputs!$E$48-Inputs!$E$50)*(1+Inputs!$B$42)-(Inputs!$E$49*$C73*(1+Scenarios!$C$9)+Inputs!$E$49*(1-$C73)*(1+(Inputs!$B$39*(Scenarios!$C$6+((1+$B73)/(1-Inputs!$E$55)-1))+(1-Inputs!$B$39)*Inputs!$B$41)))-Inputs!$E$51*(1+Inputs!$B$42))+Inputs!$E$52*(1+Inputs!$B$43))*(1-Inputs!$B$8)/$D73 -> 0.34011096 | I73: =E73+(Inputs!$B$12+(-(Inputs!$B$7-$D73)*Inputs!$B$6*(Inputs!$B$12*4/(Inputs!$B$9*1000))/4))*(1-Inputs!$B$8)/$D73 -> 0.38581195 | J73: =SUM(E73:H73)+4*(Inputs!$B$12+(-(Inputs!$B$7-$D73)*Inputs!$B$6*(Inputs!$B$12*4/(Inputs!$B$9*1000))/4))*(1-Inputs!$B$8)/$D73 -> 1.5238913 | K73: =G73+H73+2*(Scenarios!$C$11-Scenarios!$C$10)*(1-Inputs!$B$8)/$D73+(E73*(1+Scenarios!$C$15)+((Scenarios!$C$13+(Inputs!$B$12-Scenarios!$C$12)*4*(1-Inputs!$B$8)/$D73)/4))+(F73*(1+Scenarios!$C$15)+((Scenarios!$C$13+(Inputs!$B$12-Scenarios!$C$12)*4*(1-Inputs!$B$8)/$D73)/4)) -> 1.4726281 | L73: =(G73+H73)*(1+Scenarios!$C$15)+2*((Scenarios!$C$13+(Inputs!$B$12-Scenarios!$C$12)*4*(1-Inputs!$B$8)/$D73)/4)+((E73*(1+Scenarios!$C$15)+((Scenarios!$C$13+(Inputs!$B$12-Scenarios!$C$12)*4*(1-Inputs!$B$8)/$D73)/4))+(F73*(1+Scenarios!$C$15)+((Scenarios!$C$13+(Inputs!$B$12-Scenarios!$C$12)*4*(1-Inputs!$B$8)/$D73)/4)))*(1+Scenarios!$C$16) -> 1.6715957 | M73: =(1-(L73/K73-1)/Valuation!$C$32)*K73/(1+Valuation!$C$33)+(1-Valuation!$C$31/Valuation!$C$32)*(L73/(1+Valuation!$C$33)^2+L73*(1+Valuation!$C$31)/(1+Valuation!$C$33)^3+L73*(1+Valuation!$C$31)^2/(1+Valuation!$C$33)^4+L73*(1+Valuation!$C$31)^3/(1+Valuation!$C$33)^5)+L73*(1+Valuation!$C$31)^4*(1-Valuation!$C$34/Valuation!$C$32)/(Valuation!$C$33-Valuation!$C$34)/(1+Valuation!$C$33)^5+(Inputs!$B$10-(Inputs!$B$7-$D73)*Inputs!$B$6/1000)*1000/$D73 -> 24.154434
A74: Drag 10%, fixed 55% | B74: -0.1 | C74: 0.55 | D74: 932 | E74: =((Inputs!$B$47*(1+(Inputs!$B$39*(Scenarios!$C$6+((1+$B74)/(1-Inputs!$B$55)-1))+(1-Inputs!$B$39)*Inputs!$B$41))*(1+Scenarios!$C$8)+(Inputs!$B$48-Inputs!$B$50)*(1+Inputs!$B$42)-(Inputs!$B$49*$C74*(1+Scenarios!$C$9)+Inputs!$B$49*(1-$C74)*(1+(Inputs!$B$39*(Scenarios!$C$6+((1+$B74)/(1-Inputs!$B$55)-1))+(1-Inputs!$B$39)*Inputs!$B$41)))-Inputs!$B$51*(1+Inputs!$B$42))+Inputs!$B$52*(1+Inputs!$B$43))*(1-Inputs!$B$8)/$D74 -> 0.34847419 | F74: =((Inputs!$C$47*(1+(Inputs!$B$39*(Scenarios!$C$6+((1+$B74)/(1-Inputs!$C$55)-1))+(1-Inputs!$B$39)*Inputs!$B$41))*(1+Scenarios!$C$8)+(Inputs!$C$48-Inputs!$C$50)*(1+Inputs!$B$42)-(Inputs!$C$49*$C74*(1+Scenarios!$C$9)+Inputs!$C$49*(1-$C74)*(1+(Inputs!$B$39*(Scenarios!$C$6+((1+$B74)/(1-Inputs!$C$55)-1))+(1-Inputs!$B$39)*Inputs!$B$41)))-Inputs!$C$51*(1+Inputs!$B$42))+Inputs!$C$52*(1+Inputs!$B$43))*(1-Inputs!$B$8)/$D74 -> 0.31243859 | G74: =((Inputs!$D$47*(1+(Inputs!$B$39*(Scenarios!$C$6+((1+$B74)/(1-Inputs!$D$55)-1))+(1-Inputs!$B$39)*Inputs!$B$41))*(1+Scenarios!$C$8)+(Inputs!$D$48-Inputs!$D$50)*(1+Inputs!$B$42)-(Inputs!$D$49*$C74*(1+Scenarios!$C$9)+Inputs!$D$49*(1-$C74)*(1+(Inputs!$B$39*(Scenarios!$C$6+((1+$B74)/(1-Inputs!$D$55)-1))+(1-Inputs!$B$39)*Inputs!$B$41)))-Inputs!$D$51*(1+Inputs!$B$42))+Inputs!$D$52*(1+Inputs!$B$43))*(1-Inputs!$B$8)/$D74 -> 0.37782729 | H74: =((Inputs!$E$47*(1+(Inputs!$B$39*(Scenarios!$C$6+((1+$B74)/(1-Inputs!$E$55)-1))+(1-Inputs!$B$39)*Inputs!$B$41))*(1+Scenarios!$C$8)+(Inputs!$E$48-Inputs!$E$50)*(1+Inputs!$B$42)-(Inputs!$E$49*$C74*(1+Scenarios!$C$9)+Inputs!$E$49*(1-$C74)*(1+(Inputs!$B$39*(Scenarios!$C$6+((1+$B74)/(1-Inputs!$E$55)-1))+(1-Inputs!$B$39)*Inputs!$B$41)))-Inputs!$E$51*(1+Inputs!$B$42))+Inputs!$E$52*(1+Inputs!$B$43))*(1-Inputs!$B$8)/$D74 -> 0.33804341 | I74: =E74+(Inputs!$B$12+(-(Inputs!$B$7-$D74)*Inputs!$B$6*(Inputs!$B$12*4/(Inputs!$B$9*1000))/4))*(1-Inputs!$B$8)/$D74 -> 0.38129607 | J74: =SUM(E74:H74)+4*(Inputs!$B$12+(-(Inputs!$B$7-$D74)*Inputs!$B$6*(Inputs!$B$12*4/(Inputs!$B$9*1000))/4))*(1-Inputs!$B$8)/$D74 -> 1.508071 | K74: =G74+H74+2*(Scenarios!$C$11-Scenarios!$C$10)*(1-Inputs!$B$8)/$D74+(E74*(1+Scenarios!$C$15)+((Scenarios!$C$13+(Inputs!$B$12-Scenarios!$C$12)*4*(1-Inputs!$B$8)/$D74)/4))+(F74*(1+Scenarios!$C$15)+((Scenarios!$C$13+(Inputs!$B$12-Scenarios!$C$12)*4*(1-Inputs!$B$8)/$D74)/4)) -> 1.4557282 | L74: =(G74+H74)*(1+Scenarios!$C$15)+2*((Scenarios!$C$13+(Inputs!$B$12-Scenarios!$C$12)*4*(1-Inputs!$B$8)/$D74)/4)+((E74*(1+Scenarios!$C$15)+((Scenarios!$C$13+(Inputs!$B$12-Scenarios!$C$12)*4*(1-Inputs!$B$8)/$D74)/4))+(F74*(1+Scenarios!$C$15)+((Scenarios!$C$13+(Inputs!$B$12-Scenarios!$C$12)*4*(1-Inputs!$B$8)/$D74)/4)))*(1+Scenarios!$C$16) -> 1.6532724 | M74: =(1-(L74/K74-1)/Valuation!$C$32)*K74/(1+Valuation!$C$33)+(1-Valuation!$C$31/Valuation!$C$32)*(L74/(1+Valuation!$C$33)^2+L74*(1+Valuation!$C$31)/(1+Valuation!$C$33)^3+L74*(1+Valuation!$C$31)^2/(1+Valuation!$C$33)^4+L74*(1+Valuation!$C$31)^3/(1+Valuation!$C$33)^5)+L74*(1+Valuation!$C$31)^4*(1-Valuation!$C$34/Valuation!$C$32)/(Valuation!$C$33-Valuation!$C$34)/(1+Valuation!$C$33)^5+(Inputs!$B$10-(Inputs!$B$7-$D74)*Inputs!$B$6/1000)*1000/$D74 -> 23.921746
A75: Drag 10%, fixed 65% | B75: -0.1 | C75: 0.65 | D75: 932 | E75: =((Inputs!$B$47*(1+(Inputs!$B$39*(Scenarios!$C$6+((1+$B75)/(1-Inputs!$B$55)-1))+(1-Inputs!$B$39)*Inputs!$B$41))*(1+Scenarios!$C$8)+(Inputs!$B$48-Inputs!$B$50)*(1+Inputs!$B$42)-(Inputs!$B$49*$C75*(1+Scenarios!$C$9)+Inputs!$B$49*(1-$C75)*(1+(Inputs!$B$39*(Scenarios!$C$6+((1+$B75)/(1-Inputs!$B$55)-1))+(1-Inputs!$B$39)*Inputs!$B$41)))-Inputs!$B$51*(1+Inputs!$B$42))+Inputs!$B$52*(1+Inputs!$B$43))*(1-Inputs!$B$8)/$D75 -> 0.34395831 | F75: =((Inputs!$C$47*(1+(Inputs!$B$39*(Scenarios!$C$6+((1+$B75)/(1-Inputs!$C$55)-1))+(1-Inputs!$B$39)*Inputs!$B$41))*(1+Scenarios!$C$8)+(Inputs!$C$48-Inputs!$C$50)*(1+Inputs!$B$42)-(Inputs!$C$49*$C75*(1+Scenarios!$C$9)+Inputs!$C$49*(1-$C75)*(1+(Inputs!$B$39*(Scenarios!$C$6+((1+$B75)/(1-Inputs!$C$55)-1))+(1-Inputs!$B$39)*Inputs!$B$41)))-Inputs!$C$51*(1+Inputs!$B$42))+Inputs!$C$52*(1+Inputs!$B$43))*(1-Inputs!$B$8)/$D75 -> 0.30795785 | G75: =((Inputs!$D$47*(1+(Inputs!$B$39*(Scenarios!$C$6+((1+$B75)/(1-Inputs!$D$55)-1))+(1-Inputs!$B$39)*Inputs!$B$41))*(1+Scenarios!$C$8)+(Inputs!$D$48-Inputs!$D$50)*(1+Inputs!$B$42)-(Inputs!$D$49*$C75*(1+Scenarios!$C$9)+Inputs!$D$49*(1-$C75)*(1+(Inputs!$B$39*(Scenarios!$C$6+((1+$B75)/(1-Inputs!$D$55)-1))+(1-Inputs!$B$39)*Inputs!$B$41)))-Inputs!$D$51*(1+Inputs!$B$42))+Inputs!$D$52*(1+Inputs!$B$43))*(1-Inputs!$B$8)/$D75 -> 0.37307117 | H75: =((Inputs!$E$47*(1+(Inputs!$B$39*(Scenarios!$C$6+((1+$B75)/(1-Inputs!$E$55)-1))+(1-Inputs!$B$39)*Inputs!$B$41))*(1+Scenarios!$C$8)+(Inputs!$E$48-Inputs!$E$50)*(1+Inputs!$B$42)-(Inputs!$E$49*$C75*(1+Scenarios!$C$9)+Inputs!$E$49*(1-$C75)*(1+(Inputs!$B$39*(Scenarios!$C$6+((1+$B75)/(1-Inputs!$E$55)-1))+(1-Inputs!$B$39)*Inputs!$B$41)))-Inputs!$E$51*(1+Inputs!$B$42))+Inputs!$E$52*(1+Inputs!$B$43))*(1-Inputs!$B$8)/$D75 -> 0.33597587 | I75: =E75+(Inputs!$B$12+(-(Inputs!$B$7-$D75)*Inputs!$B$6*(Inputs!$B$12*4/(Inputs!$B$9*1000))/4))*(1-Inputs!$B$8)/$D75 -> 0.3767802 | J75: =SUM(E75:H75)+4*(Inputs!$B$12+(-(Inputs!$B$7-$D75)*Inputs!$B$6*(Inputs!$B$12*4/(Inputs!$B$9*1000))/4))*(1-Inputs!$B$8)/$D75 -> 1.4922508 | K75: =G75+H75+2*(Scenarios!$C$11-Scenarios!$C$10)*(1-Inputs!$B$8)/$D75+(E75*(1+Scenarios!$C$15)+((Scenarios!$C$13+(Inputs!$B$12-Scenarios!$C$12)*4*(1-Inputs!$B$8)/$D75)/4))+(F75*(1+Scenarios!$C$15)+((Scenarios!$C$13+(Inputs!$B$12-Scenarios!$C$12)*4*(1-Inputs!$B$8)/$D75)/4)) -> 1.4388283 | L75: =(G75+H75)*(1+Scenarios!$C$15)+2*((Scenarios!$C$13+(Inputs!$B$12-Scenarios!$C$12)*4*(1-Inputs!$B$8)/$D75)/4)+((E75*(1+Scenarios!$C$15)+((Scenarios!$C$13+(Inputs!$B$12-Scenarios!$C$12)*4*(1-Inputs!$B$8)/$D75)/4))+(F75*(1+Scenarios!$C$15)+((Scenarios!$C$13+(Inputs!$B$12-Scenarios!$C$12)*4*(1-Inputs!$B$8)/$D75)/4)))*(1+Scenarios!$C$16) -> 1.6349491 | M75: =(1-(L75/K75-1)/Valuation!$C$32)*K75/(1+Valuation!$C$33)+(1-Valuation!$C$31/Valuation!$C$32)*(L75/(1+Valuation!$C$33)^2+L75*(1+Valuation!$C$31)/(1+Valuation!$C$33)^3+L75*(1+Valuation!$C$31)^2/(1+Valuation!$C$33)^4+L75*(1+Valuation!$C$31)^3/(1+Valuation!$C$33)^5)+L75*(1+Valuation!$C$31)^4*(1-Valuation!$C$34/Valuation!$C$32)/(Valuation!$C$33-Valuation!$C$34)/(1+Valuation!$C$33)^5+(Inputs!$B$10-(Inputs!$B$7-$D75)*Inputs!$B$6/1000)*1000/$D75 -> 23.689059
A76: Drag 13%, fixed 45% | B76: -0.13 | C76: 0.45 | D76: 932 | E76: =((Inputs!$B$47*(1+(Inputs!$B$39*(Scenarios!$C$6+((1+$B76)/(1-Inputs!$B$55)-1))+(1-Inputs!$B$39)*Inputs!$B$41))*(1+Scenarios!$C$8)+(Inputs!$B$48-Inputs!$B$50)*(1+Inputs!$B$42)-(Inputs!$B$49*$C76*(1+Scenarios!$C$9)+Inputs!$B$49*(1-$C76)*(1+(Inputs!$B$39*(Scenarios!$C$6+((1+$B76)/(1-Inputs!$B$55)-1))+(1-Inputs!$B$39)*Inputs!$B$41)))-Inputs!$B$51*(1+Inputs!$B$42))+Inputs!$B$52*(1+Inputs!$B$43))*(1-Inputs!$B$8)/$D76 -> 0.33986917 | F76: =((Inputs!$C$47*(1+(Inputs!$B$39*(Scenarios!$C$6+((1+$B76)/(1-Inputs!$C$55)-1))+(1-Inputs!$B$39)*Inputs!$B$41))*(1+Scenarios!$C$8)+(Inputs!$C$48-Inputs!$C$50)*(1+Inputs!$B$42)-(Inputs!$C$49*$C76*(1+Scenarios!$C$9)+Inputs!$C$49*(1-$C76)*(1+(Inputs!$B$39*(Scenarios!$C$6+((1+$B76)/(1-Inputs!$C$55)-1))+(1-Inputs!$B$39)*Inputs!$B$41)))-Inputs!$C$51*(1+Inputs!$B$42))+Inputs!$C$52*(1+Inputs!$B$43))*(1-Inputs!$B$8)/$D76 -> 0.30449863 | G76: =((Inputs!$D$47*(1+(Inputs!$B$39*(Scenarios!$C$6+((1+$B76)/(1-Inputs!$D$55)-1))+(1-Inputs!$B$39)*Inputs!$B$41))*(1+Scenarios!$C$8)+(Inputs!$D$48-Inputs!$D$50)*(1+Inputs!$B$42)-(Inputs!$D$49*$C76*(1+Scenarios!$C$9)+Inputs!$D$49*(1-$C76)*(1+(Inputs!$B$39*(Scenarios!$C$6+((1+$B76)/(1-Inputs!$D$55)-1))+(1-Inputs!$B$39)*Inputs!$B$41)))-Inputs!$D$51*(1+Inputs!$B$42))+Inputs!$D$52*(1+Inputs!$B$43))*(1-Inputs!$B$8)/$D76 -> 0.36887684 | H76: =((Inputs!$E$47*(1+(Inputs!$B$39*(Scenarios!$C$6+((1+$B76)/(1-Inputs!$E$55)-1))+(1-Inputs!$B$39)*Inputs!$B$41))*(1+Scenarios!$C$8)+(Inputs!$E$48-Inputs!$E$50)*(1+Inputs!$B$42)-(Inputs!$E$49*$C76*(1+Scenarios!$C$9)+Inputs!$E$49*(1-$C76)*(1+(Inputs!$B$39*(Scenarios!$C$6+((1+$B76)/(1-Inputs!$E$55)-1))+(1-Inputs!$B$39)*Inputs!$B$41)))-Inputs!$E$51*(1+Inputs!$B$42))+Inputs!$E$52*(1+Inputs!$B$43))*(1-Inputs!$B$8)/$D76 -> 0.32668419 | I76: =E76+(Inputs!$B$12+(-(Inputs!$B$7-$D76)*Inputs!$B$6*(Inputs!$B$12*4/(Inputs!$B$9*1000))/4))*(1-Inputs!$B$8)/$D76 -> 0.37269106 | J76: =SUM(E76:H76)+4*(Inputs!$B$12+(-(Inputs!$B$7-$D76)*Inputs!$B$6*(Inputs!$B$12*4/(Inputs!$B$9*1000))/4))*(1-Inputs!$B$8)/$D76 -> 1.4712164 | K76: =G76+H76+2*(Scenarios!$C$11-Scenarios!$C$10)*(1-Inputs!$B$8)/$D76+(E76*(1+Scenarios!$C$15)+((Scenarios!$C$13+(Inputs!$B$12-Scenarios!$C$12)*4*(1-Inputs!$B$8)/$D76)/4))+(F76*(1+Scenarios!$C$15)+((Scenarios!$C$13+(Inputs!$B$12-Scenarios!$C$12)*4*(1-Inputs!$B$8)/$D76)/4)) -> 1.4168882 | L76: =(G76+H76)*(1+Scenarios!$C$15)+2*((Scenarios!$C$13+(Inputs!$B$12-Scenarios!$C$12)*4*(1-Inputs!$B$8)/$D76)/4)+((E76*(1+Scenarios!$C$15)+((Scenarios!$C$13+(Inputs!$B$12-Scenarios!$C$12)*4*(1-Inputs!$B$8)/$D76)/4))+(F76*(1+Scenarios!$C$15)+((Scenarios!$C$13+(Inputs!$B$12-Scenarios!$C$12)*4*(1-Inputs!$B$8)/$D76)/4)))*(1+Scenarios!$C$16) -> 1.6108834 | M76: =(1-(L76/K76-1)/Valuation!$C$32)*K76/(1+Valuation!$C$33)+(1-Valuation!$C$31/Valuation!$C$32)*(L76/(1+Valuation!$C$33)^2+L76*(1+Valuation!$C$31)/(1+Valuation!$C$33)^3+L76*(1+Valuation!$C$31)^2/(1+Valuation!$C$33)^4+L76*(1+Valuation!$C$31)^3/(1+Valuation!$C$33)^5)+L76*(1+Valuation!$C$31)^4*(1-Valuation!$C$34/Valuation!$C$32)/(Valuation!$C$33-Valuation!$C$34)/(1+Valuation!$C$33)^5+(Inputs!$B$10-(Inputs!$B$7-$D76)*Inputs!$B$6/1000)*1000/$D76 -> 23.384848
A77: Drag 13%, fixed 55% | B77: -0.13 | C77: 0.55 | D77: 932 | E77: =((Inputs!$B$47*(1+(Inputs!$B$39*(Scenarios!$C$6+((1+$B77)/(1-Inputs!$B$55)-1))+(1-Inputs!$B$39)*Inputs!$B$41))*(1+Scenarios!$C$8)+(Inputs!$B$48-Inputs!$B$50)*(1+Inputs!$B$42)-(Inputs!$B$49*$C77*(1+Scenarios!$C$9)+Inputs!$B$49*(1-$C77)*(1+(Inputs!$B$39*(Scenarios!$C$6+((1+$B77)/(1-Inputs!$B$55)-1))+(1-Inputs!$B$39)*Inputs!$B$41)))-Inputs!$B$51*(1+Inputs!$B$42))+Inputs!$B$52*(1+Inputs!$B$43))*(1-Inputs!$B$8)/$D77 -> 0.33456852 | F77: =((Inputs!$C$47*(1+(Inputs!$B$39*(Scenarios!$C$6+((1+$B77)/(1-Inputs!$C$55)-1))+(1-Inputs!$B$39)*Inputs!$B$41))*(1+Scenarios!$C$8)+(Inputs!$C$48-Inputs!$C$50)*(1+Inputs!$B$42)-(Inputs!$C$49*$C77*(1+Scenarios!$C$9)+Inputs!$C$49*(1-$C77)*(1+(Inputs!$B$39*(Scenarios!$C$6+((1+$B77)/(1-Inputs!$C$55)-1))+(1-Inputs!$B$39)*Inputs!$B$41)))-Inputs!$C$51*(1+Inputs!$B$42))+Inputs!$C$52*(1+Inputs!$B$43))*(1-Inputs!$B$8)/$D77 -> 0.29923922 | G77: =((Inputs!$D$47*(1+(Inputs!$B$39*(Scenarios!$C$6+((1+$B77)/(1-Inputs!$D$55)-1))+(1-Inputs!$B$39)*Inputs!$B$41))*(1+Scenarios!$C$8)+(Inputs!$D$48-Inputs!$D$50)*(1+Inputs!$B$42)-(Inputs!$D$49*$C77*(1+Scenarios!$C$9)+Inputs!$D$49*(1-$C77)*(1+(Inputs!$B$39*(Scenarios!$C$6+((1+$B77)/(1-Inputs!$D$55)-1))+(1-Inputs!$B$39)*Inputs!$B$41)))-Inputs!$D$51*(1+Inputs!$B$42))+Inputs!$D$52*(1+Inputs!$B$43))*(1-Inputs!$B$8)/$D77 -> 0.3632942 | H77: =((Inputs!$E$47*(1+(Inputs!$B$39*(Scenarios!$C$6+((1+$B77)/(1-Inputs!$E$55)-1))+(1-Inputs!$B$39)*Inputs!$B$41))*(1+Scenarios!$C$8)+(Inputs!$E$48-Inputs!$E$50)*(1+Inputs!$B$42)-(Inputs!$E$49*$C77*(1+Scenarios!$C$9)+Inputs!$E$49*(1-$C77)*(1+(Inputs!$B$39*(Scenarios!$C$6+((1+$B77)/(1-Inputs!$E$55)-1))+(1-Inputs!$B$39)*Inputs!$B$41)))-Inputs!$E$51*(1+Inputs!$B$42))+Inputs!$E$52*(1+Inputs!$B$43))*(1-Inputs!$B$8)/$D77 -> 0.32369793 | I77: =E77+(Inputs!$B$12+(-(Inputs!$B$7-$D77)*Inputs!$B$6*(Inputs!$B$12*4/(Inputs!$B$9*1000))/4))*(1-Inputs!$B$8)/$D77 -> 0.36739041 | J77: =SUM(E77:H77)+4*(Inputs!$B$12+(-(Inputs!$B$7-$D77)*Inputs!$B$6*(Inputs!$B$12*4/(Inputs!$B$9*1000))/4))*(1-Inputs!$B$8)/$D77 -> 1.4520874 | K77: =G77+H77+2*(Scenarios!$C$11-Scenarios!$C$10)*(1-Inputs!$B$8)/$D77+(E77*(1+Scenarios!$C$15)+((Scenarios!$C$13+(Inputs!$B$12-Scenarios!$C$12)*4*(1-Inputs!$B$8)/$D77)/4))+(F77*(1+Scenarios!$C$15)+((Scenarios!$C$13+(Inputs!$B$12-Scenarios!$C$12)*4*(1-Inputs!$B$8)/$D77)/4)) -> 1.396492 | L77: =(G77+H77)*(1+Scenarios!$C$15)+2*((Scenarios!$C$13+(Inputs!$B$12-Scenarios!$C$12)*4*(1-Inputs!$B$8)/$D77)/4)+((E77*(1+Scenarios!$C$15)+((Scenarios!$C$13+(Inputs!$B$12-Scenarios!$C$12)*4*(1-Inputs!$B$8)/$D77)/4))+(F77*(1+Scenarios!$C$15)+((Scenarios!$C$13+(Inputs!$B$12-Scenarios!$C$12)*4*(1-Inputs!$B$8)/$D77)/4)))*(1+Scenarios!$C$16) -> 1.5887493 | M77: =(1-(L77/K77-1)/Valuation!$C$32)*K77/(1+Valuation!$C$33)+(1-Valuation!$C$31/Valuation!$C$32)*(L77/(1+Valuation!$C$33)^2+L77*(1+Valuation!$C$31)/(1+Valuation!$C$33)^3+L77*(1+Valuation!$C$31)^2/(1+Valuation!$C$33)^4+L77*(1+Valuation!$C$31)^3/(1+Valuation!$C$33)^5)+L77*(1+Valuation!$C$31)^4*(1-Valuation!$C$34/Valuation!$C$32)/(Valuation!$C$33-Valuation!$C$34)/(1+Valuation!$C$33)^5+(Inputs!$B$10-(Inputs!$B$7-$D77)*Inputs!$B$6/1000)*1000/$D77 -> 23.103869
A78: Drag 13%, fixed 65% | B78: -0.13 | C78: 0.65 | D78: 932 | E78: =((Inputs!$B$47*(1+(Inputs!$B$39*(Scenarios!$C$6+((1+$B78)/(1-Inputs!$B$55)-1))+(1-Inputs!$B$39)*Inputs!$B$41))*(1+Scenarios!$C$8)+(Inputs!$B$48-Inputs!$B$50)*(1+Inputs!$B$42)-(Inputs!$B$49*$C78*(1+Scenarios!$C$9)+Inputs!$B$49*(1-$C78)*(1+(Inputs!$B$39*(Scenarios!$C$6+((1+$B78)/(1-Inputs!$B$55)-1))+(1-Inputs!$B$39)*Inputs!$B$41)))-Inputs!$B$51*(1+Inputs!$B$42))+Inputs!$B$52*(1+Inputs!$B$43))*(1-Inputs!$B$8)/$D78 -> 0.32926787 | F78: =((Inputs!$C$47*(1+(Inputs!$B$39*(Scenarios!$C$6+((1+$B78)/(1-Inputs!$C$55)-1))+(1-Inputs!$B$39)*Inputs!$B$41))*(1+Scenarios!$C$8)+(Inputs!$C$48-Inputs!$C$50)*(1+Inputs!$B$42)-(Inputs!$C$49*$C78*(1+Scenarios!$C$9)+Inputs!$C$49*(1-$C78)*(1+(Inputs!$B$39*(Scenarios!$C$6+((1+$B78)/(1-Inputs!$C$55)-1))+(1-Inputs!$B$39)*Inputs!$B$41)))-Inputs!$C$51*(1+Inputs!$B$42))+Inputs!$C$52*(1+Inputs!$B$43))*(1-Inputs!$B$8)/$D78 -> 0.29397981 | G78: =((Inputs!$D$47*(1+(Inputs!$B$39*(Scenarios!$C$6+((1+$B78)/(1-Inputs!$D$55)-1))+(1-Inputs!$B$39)*Inputs!$B$41))*(1+Scenarios!$C$8)+(Inputs!$D$48-Inputs!$D$50)*(1+Inputs!$B$42)-(Inputs!$D$49*$C78*(1+Scenarios!$C$9)+Inputs!$D$49*(1-$C78)*(1+(Inputs!$B$39*(Scenarios!$C$6+((1+$B78)/(1-Inputs!$D$55)-1))+(1-Inputs!$B$39)*Inputs!$B$41)))-Inputs!$D$51*(1+Inputs!$B$42))+Inputs!$D$52*(1+Inputs!$B$43))*(1-Inputs!$B$8)/$D78 -> 0.35771156 | H78: =((Inputs!$E$47*(1+(Inputs!$B$39*(Scenarios!$C$6+((1+$B78)/(1-Inputs!$E$55)-1))+(1-Inputs!$B$39)*Inputs!$B$41))*(1+Scenarios!$C$8)+(Inputs!$E$48-Inputs!$E$50)*(1+Inputs!$B$42)-(Inputs!$E$49*$C78*(1+Scenarios!$C$9)+Inputs!$E$49*(1-$C78)*(1+(Inputs!$B$39*(Scenarios!$C$6+((1+$B78)/(1-Inputs!$E$55)-1))+(1-Inputs!$B$39)*Inputs!$B$41)))-Inputs!$E$51*(1+Inputs!$B$42))+Inputs!$E$52*(1+Inputs!$B$43))*(1-Inputs!$B$8)/$D78 -> 0.32071166 | I78: =E78+(Inputs!$B$12+(-(Inputs!$B$7-$D78)*Inputs!$B$6*(Inputs!$B$12*4/(Inputs!$B$9*1000))/4))*(1-Inputs!$B$8)/$D78 -> 0.36208976 | J78: =SUM(E78:H78)+4*(Inputs!$B$12+(-(Inputs!$B$7-$D78)*Inputs!$B$6*(Inputs!$B$12*4/(Inputs!$B$9*1000))/4))*(1-Inputs!$B$8)/$D78 -> 1.4329585 | K78: =G78+H78+2*(Scenarios!$C$11-Scenarios!$C$10)*(1-Inputs!$B$8)/$D78+(E78*(1+Scenarios!$C$15)+((Scenarios!$C$13+(Inputs!$B$12-Scenarios!$C$12)*4*(1-Inputs!$B$8)/$D78)/4))+(F78*(1+Scenarios!$C$15)+((Scenarios!$C$13+(Inputs!$B$12-Scenarios!$C$12)*4*(1-Inputs!$B$8)/$D78)/4)) -> 1.3760958 | L78: =(G78+H78)*(1+Scenarios!$C$15)+2*((Scenarios!$C$13+(Inputs!$B$12-Scenarios!$C$12)*4*(1-Inputs!$B$8)/$D78)/4)+((E78*(1+Scenarios!$C$15)+((Scenarios!$C$13+(Inputs!$B$12-Scenarios!$C$12)*4*(1-Inputs!$B$8)/$D78)/4))+(F78*(1+Scenarios!$C$15)+((Scenarios!$C$13+(Inputs!$B$12-Scenarios!$C$12)*4*(1-Inputs!$B$8)/$D78)/4)))*(1+Scenarios!$C$16) -> 1.5666152 | M78: =(1-(L78/K78-1)/Valuation!$C$32)*K78/(1+Valuation!$C$33)+(1-Valuation!$C$31/Valuation!$C$32)*(L78/(1+Valuation!$C$33)^2+L78*(1+Valuation!$C$31)/(1+Valuation!$C$33)^3+L78*(1+Valuation!$C$31)^2/(1+Valuation!$C$33)^4+L78*(1+Valuation!$C$31)^3/(1+Valuation!$C$33)^5)+L78*(1+Valuation!$C$31)^4*(1-Valuation!$C$34/Valuation!$C$32)/(Valuation!$C$33-Valuation!$C$34)/(1+Valuation!$C$33)^5+(Inputs!$B$10-(Inputs!$B$7-$D78)*Inputs!$B$6/1000)*1000/$D78 -> 22.822889
A79: Drag 16%, fixed 45% | B79: -0.16 | C79: 0.45 | D79: 932 | E79: =((Inputs!$B$47*(1+(Inputs!$B$39*(Scenarios!$C$6+((1+$B79)/(1-Inputs!$B$55)-1))+(1-Inputs!$B$39)*Inputs!$B$41))*(1+Scenarios!$C$8)+(Inputs!$B$48-Inputs!$B$50)*(1+Inputs!$B$42)-(Inputs!$B$49*$C79*(1+Scenarios!$C$9)+Inputs!$B$49*(1-$C79)*(1+(Inputs!$B$39*(Scenarios!$C$6+((1+$B79)/(1-Inputs!$B$55)-1))+(1-Inputs!$B$39)*Inputs!$B$41)))-Inputs!$B$51*(1+Inputs!$B$42))+Inputs!$B$52*(1+Inputs!$B$43))*(1-Inputs!$B$8)/$D79 -> 0.32674827 | F79: =((Inputs!$C$47*(1+(Inputs!$B$39*(Scenarios!$C$6+((1+$B79)/(1-Inputs!$C$55)-1))+(1-Inputs!$B$39)*Inputs!$B$41))*(1+Scenarios!$C$8)+(Inputs!$C$48-Inputs!$C$50)*(1+Inputs!$B$42)-(Inputs!$C$49*$C79*(1+Scenarios!$C$9)+Inputs!$C$49*(1-$C79)*(1+(Inputs!$B$39*(Scenarios!$C$6+((1+$B79)/(1-Inputs!$C$55)-1))+(1-Inputs!$B$39)*Inputs!$B$41)))-Inputs!$C$51*(1+Inputs!$B$42))+Inputs!$C$52*(1+Inputs!$B$43))*(1-Inputs!$B$8)/$D79 -> 0.29207793 | G79: =((Inputs!$D$47*(1+(Inputs!$B$39*(Scenarios!$C$6+((1+$B79)/(1-Inputs!$D$55)-1))+(1-Inputs!$B$39)*Inputs!$B$41))*(1+Scenarios!$C$8)+(Inputs!$D$48-Inputs!$D$50)*(1+Inputs!$B$42)-(Inputs!$D$49*$C79*(1+Scenarios!$C$9)+Inputs!$D$49*(1-$C79)*(1+(Inputs!$B$39*(Scenarios!$C$6+((1+$B79)/(1-Inputs!$D$55)-1))+(1-Inputs!$B$39)*Inputs!$B$41)))-Inputs!$D$51*(1+Inputs!$B$42))+Inputs!$D$52*(1+Inputs!$B$43))*(1-Inputs!$B$8)/$D79 -> 0.35517027 | H79: =((Inputs!$E$47*(1+(Inputs!$B$39*(Scenarios!$C$6+((1+$B79)/(1-Inputs!$E$55)-1))+(1-Inputs!$B$39)*Inputs!$B$41))*(1+Scenarios!$C$8)+(Inputs!$E$48-Inputs!$E$50)*(1+Inputs!$B$42)-(Inputs!$E$49*$C79*(1+Scenarios!$C$9)+Inputs!$E$49*(1-$C79)*(1+(Inputs!$B$39*(Scenarios!$C$6+((1+$B79)/(1-Inputs!$E$55)-1))+(1-Inputs!$B$39)*Inputs!$B$41)))-Inputs!$E$51*(1+Inputs!$B$42))+Inputs!$E$52*(1+Inputs!$B$43))*(1-Inputs!$B$8)/$D79 -> 0.31325743 | I79: =E79+(Inputs!$B$12+(-(Inputs!$B$7-$D79)*Inputs!$B$6*(Inputs!$B$12*4/(Inputs!$B$9*1000))/4))*(1-Inputs!$B$8)/$D79 -> 0.35957016 | J79: =SUM(E79:H79)+4*(Inputs!$B$12+(-(Inputs!$B$7-$D79)*Inputs!$B$6*(Inputs!$B$12*4/(Inputs!$B$9*1000))/4))*(1-Inputs!$B$8)/$D79 -> 1.4185415 | K79: =G79+H79+2*(Scenarios!$C$11-Scenarios!$C$10)*(1-Inputs!$B$8)/$D79+(E79*(1+Scenarios!$C$15)+((Scenarios!$C$13+(Inputs!$B$12-Scenarios!$C$12)*4*(1-Inputs!$B$8)/$D79)/4))+(F79*(1+Scenarios!$C$15)+((Scenarios!$C$13+(Inputs!$B$12-Scenarios!$C$12)*4*(1-Inputs!$B$8)/$D79)/4)) -> 1.3611482 | L79: =(G79+H79)*(1+Scenarios!$C$15)+2*((Scenarios!$C$13+(Inputs!$B$12-Scenarios!$C$12)*4*(1-Inputs!$B$8)/$D79)/4)+((E79*(1+Scenarios!$C$15)+((Scenarios!$C$13+(Inputs!$B$12-Scenarios!$C$12)*4*(1-Inputs!$B$8)/$D79)/4))+(F79*(1+Scenarios!$C$15)+((Scenarios!$C$13+(Inputs!$B$12-Scenarios!$C$12)*4*(1-Inputs!$B$8)/$D79)/4)))*(1+Scenarios!$C$16) -> 1.5501711 | M79: =(1-(L79/K79-1)/Valuation!$C$32)*K79/(1+Valuation!$C$33)+(1-Valuation!$C$31/Valuation!$C$32)*(L79/(1+Valuation!$C$33)^2+L79*(1+Valuation!$C$31)/(1+Valuation!$C$33)^3+L79*(1+Valuation!$C$31)^2/(1+Valuation!$C$33)^4+L79*(1+Valuation!$C$31)^3/(1+Valuation!$C$33)^5)+L79*(1+Valuation!$C$31)^4*(1-Valuation!$C$34/Valuation!$C$32)/(Valuation!$C$33-Valuation!$C$34)/(1+Valuation!$C$33)^5+(Inputs!$B$10-(Inputs!$B$7-$D79)*Inputs!$B$6/1000)*1000/$D79 -> 22.615263
A80: Drag 16%, fixed 55% | B80: -0.16 | C80: 0.55 | D80: 932 | E80: =((Inputs!$B$47*(1+(Inputs!$B$39*(Scenarios!$C$6+((1+$B80)/(1-Inputs!$B$55)-1))+(1-Inputs!$B$39)*Inputs!$B$41))*(1+Scenarios!$C$8)+(Inputs!$B$48-Inputs!$B$50)*(1+Inputs!$B$42)-(Inputs!$B$49*$C80*(1+Scenarios!$C$9)+Inputs!$B$49*(1-$C80)*(1+(Inputs!$B$39*(Scenarios!$C$6+((1+$B80)/(1-Inputs!$B$55)-1))+(1-Inputs!$B$39)*Inputs!$B$41)))-Inputs!$B$51*(1+Inputs!$B$42))+Inputs!$B$52*(1+Inputs!$B$43))*(1-Inputs!$B$8)/$D80 -> 0.32066285 | F80: =((Inputs!$C$47*(1+(Inputs!$B$39*(Scenarios!$C$6+((1+$B80)/(1-Inputs!$C$55)-1))+(1-Inputs!$B$39)*Inputs!$B$41))*(1+Scenarios!$C$8)+(Inputs!$C$48-Inputs!$C$50)*(1+Inputs!$B$42)-(Inputs!$C$49*$C80*(1+Scenarios!$C$9)+Inputs!$C$49*(1-$C80)*(1+(Inputs!$B$39*(Scenarios!$C$6+((1+$B80)/(1-Inputs!$C$55)-1))+(1-Inputs!$B$39)*Inputs!$B$41)))-Inputs!$C$51*(1+Inputs!$B$42))+Inputs!$C$52*(1+Inputs!$B$43))*(1-Inputs!$B$8)/$D80 -> 0.28603985 | G80: =((Inputs!$D$47*(1+(Inputs!$B$39*(Scenarios!$C$6+((1+$B80)/(1-Inputs!$D$55)-1))+(1-Inputs!$B$39)*Inputs!$B$41))*(1+Scenarios!$C$8)+(Inputs!$D$48-Inputs!$D$50)*(1+Inputs!$B$42)-(Inputs!$D$49*$C80*(1+Scenarios!$C$9)+Inputs!$D$49*(1-$C80)*(1+(Inputs!$B$39*(Scenarios!$C$6+((1+$B80)/(1-Inputs!$D$55)-1))+(1-Inputs!$B$39)*Inputs!$B$41)))-Inputs!$D$51*(1+Inputs!$B$42))+Inputs!$D$52*(1+Inputs!$B$43))*(1-Inputs!$B$8)/$D80 -> 0.34876111 | H80: =((Inputs!$E$47*(1+(Inputs!$B$39*(Scenarios!$C$6+((1+$B80)/(1-Inputs!$E$55)-1))+(1-Inputs!$B$39)*Inputs!$B$41))*(1+Scenarios!$C$8)+(Inputs!$E$48-Inputs!$E$50)*(1+Inputs!$B$42)-(Inputs!$E$49*$C80*(1+Scenarios!$C$9)+Inputs!$E$49*(1-$C80)*(1+(Inputs!$B$39*(Scenarios!$C$6+((1+$B80)/(1-Inputs!$E$55)-1))+(1-Inputs!$B$39)*Inputs!$B$41)))-Inputs!$E$51*(1+Inputs!$B$42))+Inputs!$E$52*(1+Inputs!$B$43))*(1-Inputs!$B$8)/$D80 -> 0.30935244 | I80: =E80+(Inputs!$B$12+(-(Inputs!$B$7-$D80)*Inputs!$B$6*(Inputs!$B$12*4/(Inputs!$B$9*1000))/4))*(1-Inputs!$B$8)/$D80 -> 0.35348474 | J80: =SUM(E80:H80)+4*(Inputs!$B$12+(-(Inputs!$B$7-$D80)*Inputs!$B$6*(Inputs!$B$12*4/(Inputs!$B$9*1000))/4))*(1-Inputs!$B$8)/$D80 -> 1.3961038 | K80: =G80+H80+2*(Scenarios!$C$11-Scenarios!$C$10)*(1-Inputs!$B$8)/$D80+(E80*(1+Scenarios!$C$15)+((Scenarios!$C$13+(Inputs!$B$12-Scenarios!$C$12)*4*(1-Inputs!$B$8)/$D80)/4))+(F80*(1+Scenarios!$C$15)+((Scenarios!$C$13+(Inputs!$B$12-Scenarios!$C$12)*4*(1-Inputs!$B$8)/$D80)/4)) -> 1.3372558 | L80: =(G80+H80)*(1+Scenarios!$C$15)+2*((Scenarios!$C$13+(Inputs!$B$12-Scenarios!$C$12)*4*(1-Inputs!$B$8)/$D80)/4)+((E80*(1+Scenarios!$C$15)+((Scenarios!$C$13+(Inputs!$B$12-Scenarios!$C$12)*4*(1-Inputs!$B$8)/$D80)/4))+(F80*(1+Scenarios!$C$15)+((Scenarios!$C$13+(Inputs!$B$12-Scenarios!$C$12)*4*(1-Inputs!$B$8)/$D80)/4)))*(1+Scenarios!$C$16) -> 1.5242262 | M80: =(1-(L80/K80-1)/Valuation!$C$32)*K80/(1+Valuation!$C$33)+(1-Valuation!$C$31/Valuation!$C$32)*(L80/(1+Valuation!$C$33)^2+L80*(1+Valuation!$C$31)/(1+Valuation!$C$33)^3+L80*(1+Valuation!$C$31)^2/(1+Valuation!$C$33)^4+L80*(1+Valuation!$C$31)^3/(1+Valuation!$C$33)^5)+L80*(1+Valuation!$C$31)^4*(1-Valuation!$C$34/Valuation!$C$32)/(Valuation!$C$33-Valuation!$C$34)/(1+Valuation!$C$33)^5+(Inputs!$B$10-(Inputs!$B$7-$D80)*Inputs!$B$6/1000)*1000/$D80 -> 22.285991
A81: Drag 16%, fixed 65% | B81: -0.16 | C81: 0.65 | D81: 932 | E81: =((Inputs!$B$47*(1+(Inputs!$B$39*(Scenarios!$C$6+((1+$B81)/(1-Inputs!$B$55)-1))+(1-Inputs!$B$39)*Inputs!$B$41))*(1+Scenarios!$C$8)+(Inputs!$B$48-Inputs!$B$50)*(1+Inputs!$B$42)-(Inputs!$B$49*$C81*(1+Scenarios!$C$9)+Inputs!$B$49*(1-$C81)*(1+(Inputs!$B$39*(Scenarios!$C$6+((1+$B81)/(1-Inputs!$B$55)-1))+(1-Inputs!$B$39)*Inputs!$B$41)))-Inputs!$B$51*(1+Inputs!$B$42))+Inputs!$B$52*(1+Inputs!$B$43))*(1-Inputs!$B$8)/$D81 -> 0.31457743 | F81: =((Inputs!$C$47*(1+(Inputs!$B$39*(Scenarios!$C$6+((1+$B81)/(1-Inputs!$C$55)-1))+(1-Inputs!$B$39)*Inputs!$B$41))*(1+Scenarios!$C$8)+(Inputs!$C$48-Inputs!$C$50)*(1+Inputs!$B$42)-(Inputs!$C$49*$C81*(1+Scenarios!$C$9)+Inputs!$C$49*(1-$C81)*(1+(Inputs!$B$39*(Scenarios!$C$6+((1+$B81)/(1-Inputs!$C$55)-1))+(1-Inputs!$B$39)*Inputs!$B$41)))-Inputs!$C$51*(1+Inputs!$B$42))+Inputs!$C$52*(1+Inputs!$B$43))*(1-Inputs!$B$8)/$D81 -> 0.28000177 | G81: =((Inputs!$D$47*(1+(Inputs!$B$39*(Scenarios!$C$6+((1+$B81)/(1-Inputs!$D$55)-1))+(1-Inputs!$B$39)*Inputs!$B$41))*(1+Scenarios!$C$8)+(Inputs!$D$48-Inputs!$D$50)*(1+Inputs!$B$42)-(Inputs!$D$49*$C81*(1+Scenarios!$C$9)+Inputs!$D$49*(1-$C81)*(1+(Inputs!$B$39*(Scenarios!$C$6+((1+$B81)/(1-Inputs!$D$55)-1))+(1-Inputs!$B$39)*Inputs!$B$41)))-Inputs!$D$51*(1+Inputs!$B$42))+Inputs!$D$52*(1+Inputs!$B$43))*(1-Inputs!$B$8)/$D81 -> 0.34235195 | H81: =((Inputs!$E$47*(1+(Inputs!$B$39*(Scenarios!$C$6+((1+$B81)/(1-Inputs!$E$55)-1))+(1-Inputs!$B$39)*Inputs!$B$41))*(1+Scenarios!$C$8)+(Inputs!$E$48-Inputs!$E$50)*(1+Inputs!$B$42)-(Inputs!$E$49*$C81*(1+Scenarios!$C$9)+Inputs!$E$49*(1-$C81)*(1+(Inputs!$B$39*(Scenarios!$C$6+((1+$B81)/(1-Inputs!$E$55)-1))+(1-Inputs!$B$39)*Inputs!$B$41)))-Inputs!$E$51*(1+Inputs!$B$42))+Inputs!$E$52*(1+Inputs!$B$43))*(1-Inputs!$B$8)/$D81 -> 0.30544745 | I81: =E81+(Inputs!$B$12+(-(Inputs!$B$7-$D81)*Inputs!$B$6*(Inputs!$B$12*4/(Inputs!$B$9*1000))/4))*(1-Inputs!$B$8)/$D81 -> 0.34739932 | J81: =SUM(E81:H81)+4*(Inputs!$B$12+(-(Inputs!$B$7-$D81)*Inputs!$B$6*(Inputs!$B$12*4/(Inputs!$B$9*1000))/4))*(1-Inputs!$B$8)/$D81 -> 1.3736662 | K81: =G81+H81+2*(Scenarios!$C$11-Scenarios!$C$10)*(1-Inputs!$B$8)/$D81+(E81*(1+Scenarios!$C$15)+((Scenarios!$C$13+(Inputs!$B$12-Scenarios!$C$12)*4*(1-Inputs!$B$8)/$D81)/4))+(F81*(1+Scenarios!$C$15)+((Scenarios!$C$13+(Inputs!$B$12-Scenarios!$C$12)*4*(1-Inputs!$B$8)/$D81)/4)) -> 1.3133633 | L81: =(G81+H81)*(1+Scenarios!$C$15)+2*((Scenarios!$C$13+(Inputs!$B$12-Scenarios!$C$12)*4*(1-Inputs!$B$8)/$D81)/4)+((E81*(1+Scenarios!$C$15)+((Scenarios!$C$13+(Inputs!$B$12-Scenarios!$C$12)*4*(1-Inputs!$B$8)/$D81)/4))+(F81*(1+Scenarios!$C$15)+((Scenarios!$C$13+(Inputs!$B$12-Scenarios!$C$12)*4*(1-Inputs!$B$8)/$D81)/4)))*(1+Scenarios!$C$16) -> 1.4982814 | M81: =(1-(L81/K81-1)/Valuation!$C$32)*K81/(1+Valuation!$C$33)+(1-Valuation!$C$31/Valuation!$C$32)*(L81/(1+Valuation!$C$33)^2+L81*(1+Valuation!$C$31)/(1+Valuation!$C$33)^3+L81*(1+Valuation!$C$31)^2/(1+Valuation!$C$33)^4+L81*(1+Valuation!$C$31)^3/(1+Valuation!$C$33)^5)+L81*(1+Valuation!$C$31)^4*(1-Valuation!$C$34/Valuation!$C$32)/(Valuation!$C$33-Valuation!$C$34)/(1+Valuation!$C$33)^5+(Inputs!$B$10-(Inputs!$B$7-$D81)*Inputs!$B$6/1000)*1000/$D81 -> 21.956719
A82: Shares 940m | B82: -0.13 | C82: 0.55 | D82: 940 | E82: =((Inputs!$B$47*(1+(Inputs!$B$39*(Scenarios!$C$6+((1+$B82)/(1-Inputs!$B$55)-1))+(1-Inputs!$B$39)*Inputs!$B$41))*(1+Scenarios!$C$8)+(Inputs!$B$48-Inputs!$B$50)*(1+Inputs!$B$42)-(Inputs!$B$49*$C82*(1+Scenarios!$C$9)+Inputs!$B$49*(1-$C82)*(1+(Inputs!$B$39*(Scenarios!$C$6+((1+$B82)/(1-Inputs!$B$55)-1))+(1-Inputs!$B$39)*Inputs!$B$41)))-Inputs!$B$51*(1+Inputs!$B$42))+Inputs!$B$52*(1+Inputs!$B$43))*(1-Inputs!$B$8)/$D82 -> 0.33172113 | F82: =((Inputs!$C$47*(1+(Inputs!$B$39*(Scenarios!$C$6+((1+$B82)/(1-Inputs!$C$55)-1))+(1-Inputs!$B$39)*Inputs!$B$41))*(1+Scenarios!$C$8)+(Inputs!$C$48-Inputs!$C$50)*(1+Inputs!$B$42)-(Inputs!$C$49*$C82*(1+Scenarios!$C$9)+Inputs!$C$49*(1-$C82)*(1+(Inputs!$B$39*(Scenarios!$C$6+((1+$B82)/(1-Inputs!$C$55)-1))+(1-Inputs!$B$39)*Inputs!$B$41)))-Inputs!$C$51*(1+Inputs!$B$42))+Inputs!$C$52*(1+Inputs!$B$43))*(1-Inputs!$B$8)/$D82 -> 0.2966925 | G82: =((Inputs!$D$47*(1+(Inputs!$B$39*(Scenarios!$C$6+((1+$B82)/(1-Inputs!$D$55)-1))+(1-Inputs!$B$39)*Inputs!$B$41))*(1+Scenarios!$C$8)+(Inputs!$D$48-Inputs!$D$50)*(1+Inputs!$B$42)-(Inputs!$D$49*$C82*(1+Scenarios!$C$9)+Inputs!$D$49*(1-$C82)*(1+(Inputs!$B$39*(Scenarios!$C$6+((1+$B82)/(1-Inputs!$D$55)-1))+(1-Inputs!$B$39)*Inputs!$B$41)))-Inputs!$D$51*(1+Inputs!$B$42))+Inputs!$D$52*(1+Inputs!$B$43))*(1-Inputs!$B$8)/$D82 -> 0.36020234 | H82: =((Inputs!$E$47*(1+(Inputs!$B$39*(Scenarios!$C$6+((1+$B82)/(1-Inputs!$E$55)-1))+(1-Inputs!$B$39)*Inputs!$B$41))*(1+Scenarios!$C$8)+(Inputs!$E$48-Inputs!$E$50)*(1+Inputs!$B$42)-(Inputs!$E$49*$C82*(1+Scenarios!$C$9)+Inputs!$E$49*(1-$C82)*(1+(Inputs!$B$39*(Scenarios!$C$6+((1+$B82)/(1-Inputs!$E$55)-1))+(1-Inputs!$B$39)*Inputs!$B$41)))-Inputs!$E$51*(1+Inputs!$B$42))+Inputs!$E$52*(1+Inputs!$B$43))*(1-Inputs!$B$8)/$D82 -> 0.32094305 | I82: =E82+(Inputs!$B$12+(-(Inputs!$B$7-$D82)*Inputs!$B$6*(Inputs!$B$12*4/(Inputs!$B$9*1000))/4))*(1-Inputs!$B$8)/$D82 -> 0.36584602 | J82: =SUM(E82:H82)+4*(Inputs!$B$12+(-(Inputs!$B$7-$D82)*Inputs!$B$6*(Inputs!$B$12*4/(Inputs!$B$9*1000))/4))*(1-Inputs!$B$8)/$D82 -> 1.4460586 | K82: =G82+H82+2*(Scenarios!$C$11-Scenarios!$C$10)*(1-Inputs!$B$8)/$D82+(E82*(1+Scenarios!$C$15)+((Scenarios!$C$13+(Inputs!$B$12-Scenarios!$C$12)*4*(1-Inputs!$B$8)/$D82)/4))+(F82*(1+Scenarios!$C$15)+((Scenarios!$C$13+(Inputs!$B$12-Scenarios!$C$12)*4*(1-Inputs!$B$8)/$D82)/4)) -> 1.3846921 | L82: =(G82+H82)*(1+Scenarios!$C$15)+2*((Scenarios!$C$13+(Inputs!$B$12-Scenarios!$C$12)*4*(1-Inputs!$B$8)/$D82)/4)+((E82*(1+Scenarios!$C$15)+((Scenarios!$C$13+(Inputs!$B$12-Scenarios!$C$12)*4*(1-Inputs!$B$8)/$D82)/4))+(F82*(1+Scenarios!$C$15)+((Scenarios!$C$13+(Inputs!$B$12-Scenarios!$C$12)*4*(1-Inputs!$B$8)/$D82)/4)))*(1+Scenarios!$C$16) -> 1.5754034 | M82: =(1-(L82/K82-1)/Valuation!$C$32)*K82/(1+Valuation!$C$33)+(1-Valuation!$C$31/Valuation!$C$32)*(L82/(1+Valuation!$C$33)^2+L82*(1+Valuation!$C$31)/(1+Valuation!$C$33)^3+L82*(1+Valuation!$C$31)^2/(1+Valuation!$C$33)^4+L82*(1+Valuation!$C$31)^3/(1+Valuation!$C$33)^5)+L82*(1+Valuation!$C$31)^4*(1-Valuation!$C$34/Valuation!$C$32)/(Valuation!$C$33-Valuation!$C$34)/(1+Valuation!$C$33)^5+(Inputs!$B$10-(Inputs!$B$7-$D82)*Inputs!$B$6/1000)*1000/$D82 -> 23.141303
A83: Shares 932m | B83: -0.13 | C83: 0.55 | D83: 932 | E83: =((Inputs!$B$47*(1+(Inputs!$B$39*(Scenarios!$C$6+((1+$B83)/(1-Inputs!$B$55)-1))+(1-Inputs!$B$39)*Inputs!$B$41))*(1+Scenarios!$C$8)+(Inputs!$B$48-Inputs!$B$50)*(1+Inputs!$B$42)-(Inputs!$B$49*$C83*(1+Scenarios!$C$9)+Inputs!$B$49*(1-$C83)*(1+(Inputs!$B$39*(Scenarios!$C$6+((1+$B83)/(1-Inputs!$B$55)-1))+(1-Inputs!$B$39)*Inputs!$B$41)))-Inputs!$B$51*(1+Inputs!$B$42))+Inputs!$B$52*(1+Inputs!$B$43))*(1-Inputs!$B$8)/$D83 -> 0.33456852 | F83: =((Inputs!$C$47*(1+(Inputs!$B$39*(Scenarios!$C$6+((1+$B83)/(1-Inputs!$C$55)-1))+(1-Inputs!$B$39)*Inputs!$B$41))*(1+Scenarios!$C$8)+(Inputs!$C$48-Inputs!$C$50)*(1+Inputs!$B$42)-(Inputs!$C$49*$C83*(1+Scenarios!$C$9)+Inputs!$C$49*(1-$C83)*(1+(Inputs!$B$39*(Scenarios!$C$6+((1+$B83)/(1-Inputs!$C$55)-1))+(1-Inputs!$B$39)*Inputs!$B$41)))-Inputs!$C$51*(1+Inputs!$B$42))+Inputs!$C$52*(1+Inputs!$B$43))*(1-Inputs!$B$8)/$D83 -> 0.29923922 | G83: =((Inputs!$D$47*(1+(Inputs!$B$39*(Scenarios!$C$6+((1+$B83)/(1-Inputs!$D$55)-1))+(1-Inputs!$B$39)*Inputs!$B$41))*(1+Scenarios!$C$8)+(Inputs!$D$48-Inputs!$D$50)*(1+Inputs!$B$42)-(Inputs!$D$49*$C83*(1+Scenarios!$C$9)+Inputs!$D$49*(1-$C83)*(1+(Inputs!$B$39*(Scenarios!$C$6+((1+$B83)/(1-Inputs!$D$55)-1))+(1-Inputs!$B$39)*Inputs!$B$41)))-Inputs!$D$51*(1+Inputs!$B$42))+Inputs!$D$52*(1+Inputs!$B$43))*(1-Inputs!$B$8)/$D83 -> 0.3632942 | H83: =((Inputs!$E$47*(1+(Inputs!$B$39*(Scenarios!$C$6+((1+$B83)/(1-Inputs!$E$55)-1))+(1-Inputs!$B$39)*Inputs!$B$41))*(1+Scenarios!$C$8)+(Inputs!$E$48-Inputs!$E$50)*(1+Inputs!$B$42)-(Inputs!$E$49*$C83*(1+Scenarios!$C$9)+Inputs!$E$49*(1-$C83)*(1+(Inputs!$B$39*(Scenarios!$C$6+((1+$B83)/(1-Inputs!$E$55)-1))+(1-Inputs!$B$39)*Inputs!$B$41)))-Inputs!$E$51*(1+Inputs!$B$42))+Inputs!$E$52*(1+Inputs!$B$43))*(1-Inputs!$B$8)/$D83 -> 0.32369793 | I83: =E83+(Inputs!$B$12+(-(Inputs!$B$7-$D83)*Inputs!$B$6*(Inputs!$B$12*4/(Inputs!$B$9*1000))/4))*(1-Inputs!$B$8)/$D83 -> 0.36739041 | J83: =SUM(E83:H83)+4*(Inputs!$B$12+(-(Inputs!$B$7-$D83)*Inputs!$B$6*(Inputs!$B$12*4/(Inputs!$B$9*1000))/4))*(1-Inputs!$B$8)/$D83 -> 1.4520874 | K83: =G83+H83+2*(Scenarios!$C$11-Scenarios!$C$10)*(1-Inputs!$B$8)/$D83+(E83*(1+Scenarios!$C$15)+((Scenarios!$C$13+(Inputs!$B$12-Scenarios!$C$12)*4*(1-Inputs!$B$8)/$D83)/4))+(F83*(1+Scenarios!$C$15)+((Scenarios!$C$13+(Inputs!$B$12-Scenarios!$C$12)*4*(1-Inputs!$B$8)/$D83)/4)) -> 1.396492 | L83: =(G83+H83)*(1+Scenarios!$C$15)+2*((Scenarios!$C$13+(Inputs!$B$12-Scenarios!$C$12)*4*(1-Inputs!$B$8)/$D83)/4)+((E83*(1+Scenarios!$C$15)+((Scenarios!$C$13+(Inputs!$B$12-Scenarios!$C$12)*4*(1-Inputs!$B$8)/$D83)/4))+(F83*(1+Scenarios!$C$15)+((Scenarios!$C$13+(Inputs!$B$12-Scenarios!$C$12)*4*(1-Inputs!$B$8)/$D83)/4)))*(1+Scenarios!$C$16) -> 1.5887493 | M83: =(1-(L83/K83-1)/Valuation!$C$32)*K83/(1+Valuation!$C$33)+(1-Valuation!$C$31/Valuation!$C$32)*(L83/(1+Valuation!$C$33)^2+L83*(1+Valuation!$C$31)/(1+Valuation!$C$33)^3+L83*(1+Valuation!$C$31)^2/(1+Valuation!$C$33)^4+L83*(1+Valuation!$C$31)^3/(1+Valuation!$C$33)^5)+L83*(1+Valuation!$C$31)^4*(1-Valuation!$C$34/Valuation!$C$32)/(Valuation!$C$33-Valuation!$C$34)/(1+Valuation!$C$33)^5+(Inputs!$B$10-(Inputs!$B$7-$D83)*Inputs!$B$6/1000)*1000/$D83 -> 23.103869
A84: Shares 930m | B84: -0.13 | C84: 0.55 | D84: 930 | E84: =((Inputs!$B$47*(1+(Inputs!$B$39*(Scenarios!$C$6+((1+$B84)/(1-Inputs!$B$55)-1))+(1-Inputs!$B$39)*Inputs!$B$41))*(1+Scenarios!$C$8)+(Inputs!$B$48-Inputs!$B$50)*(1+Inputs!$B$42)-(Inputs!$B$49*$C84*(1+Scenarios!$C$9)+Inputs!$B$49*(1-$C84)*(1+(Inputs!$B$39*(Scenarios!$C$6+((1+$B84)/(1-Inputs!$B$55)-1))+(1-Inputs!$B$39)*Inputs!$B$41)))-Inputs!$B$51*(1+Inputs!$B$42))+Inputs!$B$52*(1+Inputs!$B$43))*(1-Inputs!$B$8)/$D84 -> 0.33528802 | F84: =((Inputs!$C$47*(1+(Inputs!$B$39*(Scenarios!$C$6+((1+$B84)/(1-Inputs!$C$55)-1))+(1-Inputs!$B$39)*Inputs!$B$41))*(1+Scenarios!$C$8)+(Inputs!$C$48-Inputs!$C$50)*(1+Inputs!$B$42)-(Inputs!$C$49*$C84*(1+Scenarios!$C$9)+Inputs!$C$49*(1-$C84)*(1+(Inputs!$B$39*(Scenarios!$C$6+((1+$B84)/(1-Inputs!$C$55)-1))+(1-Inputs!$B$39)*Inputs!$B$41)))-Inputs!$C$51*(1+Inputs!$B$42))+Inputs!$C$52*(1+Inputs!$B$43))*(1-Inputs!$B$8)/$D84 -> 0.29988275 | G84: =((Inputs!$D$47*(1+(Inputs!$B$39*(Scenarios!$C$6+((1+$B84)/(1-Inputs!$D$55)-1))+(1-Inputs!$B$39)*Inputs!$B$41))*(1+Scenarios!$C$8)+(Inputs!$D$48-Inputs!$D$50)*(1+Inputs!$B$42)-(Inputs!$D$49*$C84*(1+Scenarios!$C$9)+Inputs!$D$49*(1-$C84)*(1+(Inputs!$B$39*(Scenarios!$C$6+((1+$B84)/(1-Inputs!$D$55)-1))+(1-Inputs!$B$39)*Inputs!$B$41)))-Inputs!$D$51*(1+Inputs!$B$42))+Inputs!$D$52*(1+Inputs!$B$43))*(1-Inputs!$B$8)/$D84 -> 0.36407548 | H84: =((Inputs!$E$47*(1+(Inputs!$B$39*(Scenarios!$C$6+((1+$B84)/(1-Inputs!$E$55)-1))+(1-Inputs!$B$39)*Inputs!$B$41))*(1+Scenarios!$C$8)+(Inputs!$E$48-Inputs!$E$50)*(1+Inputs!$B$42)-(Inputs!$E$49*$C84*(1+Scenarios!$C$9)+Inputs!$E$49*(1-$C84)*(1+(Inputs!$B$39*(Scenarios!$C$6+((1+$B84)/(1-Inputs!$E$55)-1))+(1-Inputs!$B$39)*Inputs!$B$41)))-Inputs!$E$51*(1+Inputs!$B$42))+Inputs!$E$52*(1+Inputs!$B$43))*(1-Inputs!$B$8)/$D84 -> 0.32439405 | I84: =E84+(Inputs!$B$12+(-(Inputs!$B$7-$D84)*Inputs!$B$6*(Inputs!$B$12*4/(Inputs!$B$9*1000))/4))*(1-Inputs!$B$8)/$D84 -> 0.36778066 | J84: =SUM(E84:H84)+4*(Inputs!$B$12+(-(Inputs!$B$7-$D84)*Inputs!$B$6*(Inputs!$B$12*4/(Inputs!$B$9*1000))/4))*(1-Inputs!$B$8)/$D84 -> 1.4536108 | K84: =G84+H84+2*(Scenarios!$C$11-Scenarios!$C$10)*(1-Inputs!$B$8)/$D84+(E84*(1+Scenarios!$C$15)+((Scenarios!$C$13+(Inputs!$B$12-Scenarios!$C$12)*4*(1-Inputs!$B$8)/$D84)/4))+(F84*(1+Scenarios!$C$15)+((Scenarios!$C$13+(Inputs!$B$12-Scenarios!$C$12)*4*(1-Inputs!$B$8)/$D84)/4)) -> 1.3994737 | L84: =(G84+H84)*(1+Scenarios!$C$15)+2*((Scenarios!$C$13+(Inputs!$B$12-Scenarios!$C$12)*4*(1-Inputs!$B$8)/$D84)/4)+((E84*(1+Scenarios!$C$15)+((Scenarios!$C$13+(Inputs!$B$12-Scenarios!$C$12)*4*(1-Inputs!$B$8)/$D84)/4))+(F84*(1+Scenarios!$C$15)+((Scenarios!$C$13+(Inputs!$B$12-Scenarios!$C$12)*4*(1-Inputs!$B$8)/$D84)/4)))*(1+Scenarios!$C$16) -> 1.5921217 | M84: =(1-(L84/K84-1)/Valuation!$C$32)*K84/(1+Valuation!$C$33)+(1-Valuation!$C$31/Valuation!$C$32)*(L84/(1+Valuation!$C$33)^2+L84*(1+Valuation!$C$31)/(1+Valuation!$C$33)^3+L84*(1+Valuation!$C$31)^2/(1+Valuation!$C$33)^4+L84*(1+Valuation!$C$31)^3/(1+Valuation!$C$33)^5)+L84*(1+Valuation!$C$31)^4*(1-Valuation!$C$34/Valuation!$C$32)/(Valuation!$C$33-Valuation!$C$34)/(1+Valuation!$C$33)^5+(Inputs!$B$10-(Inputs!$B$7-$D84)*Inputs!$B$6/1000)*1000/$D84 -> 23.09441
A85: Shares 920m | B85: -0.13 | C85: 0.55 | D85: 920 | E85: =((Inputs!$B$47*(1+(Inputs!$B$39*(Scenarios!$C$6+((1+$B85)/(1-Inputs!$B$55)-1))+(1-Inputs!$B$39)*Inputs!$B$41))*(1+Scenarios!$C$8)+(Inputs!$B$48-Inputs!$B$50)*(1+Inputs!$B$42)-(Inputs!$B$49*$C85*(1+Scenarios!$C$9)+Inputs!$B$49*(1-$C85)*(1+(Inputs!$B$39*(Scenarios!$C$6+((1+$B85)/(1-Inputs!$B$55)-1))+(1-Inputs!$B$39)*Inputs!$B$41)))-Inputs!$B$51*(1+Inputs!$B$42))+Inputs!$B$52*(1+Inputs!$B$43))*(1-Inputs!$B$8)/$D85 -> 0.33893246 | F85: =((Inputs!$C$47*(1+(Inputs!$B$39*(Scenarios!$C$6+((1+$B85)/(1-Inputs!$C$55)-1))+(1-Inputs!$B$39)*Inputs!$B$41))*(1+Scenarios!$C$8)+(Inputs!$C$48-Inputs!$C$50)*(1+Inputs!$B$42)-(Inputs!$C$49*$C85*(1+Scenarios!$C$9)+Inputs!$C$49*(1-$C85)*(1+(Inputs!$B$39*(Scenarios!$C$6+((1+$B85)/(1-Inputs!$C$55)-1))+(1-Inputs!$B$39)*Inputs!$B$41)))-Inputs!$C$51*(1+Inputs!$B$42))+Inputs!$C$52*(1+Inputs!$B$43))*(1-Inputs!$B$8)/$D85 -> 0.30314234 | G85: =((Inputs!$D$47*(1+(Inputs!$B$39*(Scenarios!$C$6+((1+$B85)/(1-Inputs!$D$55)-1))+(1-Inputs!$B$39)*Inputs!$B$41))*(1+Scenarios!$C$8)+(Inputs!$D$48-Inputs!$D$50)*(1+Inputs!$B$42)-(Inputs!$D$49*$C85*(1+Scenarios!$C$9)+Inputs!$D$49*(1-$C85)*(1+(Inputs!$B$39*(Scenarios!$C$6+((1+$B85)/(1-Inputs!$D$55)-1))+(1-Inputs!$B$39)*Inputs!$B$41)))-Inputs!$D$51*(1+Inputs!$B$42))+Inputs!$D$52*(1+Inputs!$B$43))*(1-Inputs!$B$8)/$D85 -> 0.36803282 | H85: =((Inputs!$E$47*(1+(Inputs!$B$39*(Scenarios!$C$6+((1+$B85)/(1-Inputs!$E$55)-1))+(1-Inputs!$B$39)*Inputs!$B$41))*(1+Scenarios!$C$8)+(Inputs!$E$48-Inputs!$E$50)*(1+Inputs!$B$42)-(Inputs!$E$49*$C85*(1+Scenarios!$C$9)+Inputs!$E$49*(1-$C85)*(1+(Inputs!$B$39*(Scenarios!$C$6+((1+$B85)/(1-Inputs!$E$55)-1))+(1-Inputs!$B$39)*Inputs!$B$41)))-Inputs!$E$51*(1+Inputs!$B$42))+Inputs!$E$52*(1+Inputs!$B$43))*(1-Inputs!$B$8)/$D85 -> 0.32792007 | I85: =E85+(Inputs!$B$12+(-(Inputs!$B$7-$D85)*Inputs!$B$6*(Inputs!$B$12*4/(Inputs!$B$9*1000))/4))*(1-Inputs!$B$8)/$D85 -> 0.36975736 | J85: =SUM(E85:H85)+4*(Inputs!$B$12+(-(Inputs!$B$7-$D85)*Inputs!$B$6*(Inputs!$B$12*4/(Inputs!$B$9*1000))/4))*(1-Inputs!$B$8)/$D85 -> 1.4613273 | K85: =G85+H85+2*(Scenarios!$C$11-Scenarios!$C$10)*(1-Inputs!$B$8)/$D85+(E85*(1+Scenarios!$C$15)+((Scenarios!$C$13+(Inputs!$B$12-Scenarios!$C$12)*4*(1-Inputs!$B$8)/$D85)/4))+(F85*(1+Scenarios!$C$15)+((Scenarios!$C$13+(Inputs!$B$12-Scenarios!$C$12)*4*(1-Inputs!$B$8)/$D85)/4)) -> 1.4145767 | L85: =(G85+H85)*(1+Scenarios!$C$15)+2*((Scenarios!$C$13+(Inputs!$B$12-Scenarios!$C$12)*4*(1-Inputs!$B$8)/$D85)/4)+((E85*(1+Scenarios!$C$15)+((Scenarios!$C$13+(Inputs!$B$12-Scenarios!$C$12)*4*(1-Inputs!$B$8)/$D85)/4))+(F85*(1+Scenarios!$C$15)+((Scenarios!$C$13+(Inputs!$B$12-Scenarios!$C$12)*4*(1-Inputs!$B$8)/$D85)/4)))*(1+Scenarios!$C$16) -> 1.6092034 | M85: =(1-(L85/K85-1)/Valuation!$C$32)*K85/(1+Valuation!$C$33)+(1-Valuation!$C$31/Valuation!$C$32)*(L85/(1+Valuation!$C$33)^2+L85*(1+Valuation!$C$31)/(1+Valuation!$C$33)^3+L85*(1+Valuation!$C$31)^2/(1+Valuation!$C$33)^4+L85*(1+Valuation!$C$31)^3/(1+Valuation!$C$33)^5)+L85*(1+Valuation!$C$31)^4*(1-Valuation!$C$34/Valuation!$C$32)/(Valuation!$C$33-Valuation!$C$34)/(1+Valuation!$C$33)^5+(Inputs!$B$10-(Inputs!$B$7-$D85)*Inputs!$B$6/1000)*1000/$D85 -> 23.046497

Sheet Consensus
A1: Consensus (secondary sources) and our estimates
A3: Published consensus — kept separate by provider (re-verified 10/2/26)
A4: Provider / period | B4: As of | C4: EPS ($/sh) | D4: n | E4: Low | F4: High | G4: Basis / note
A5: Zacks: Q1 FY27 (Oct-26) | B5: 10/1/26 | C5: 0.41 | D5: 4 | E5: 0.38 | F5: 0.43 | G5: Via Nasdaq. Zacks estimates as of 10/1/26; re-verified 10/2/26.
A6: Zacks: Q2 FY27 (Jan-27) | B6: 10/1/26 | C6: 0.37 | D6: 4 | E6: 0.36 | F6: 0.39
A7: Zacks: Q3 FY27 (Apr-27) | B7: 10/1/26 | C7: 0.45 | D7: 4 | E7: 0.43 | F7: 0.47
A8: Zacks: Q4 FY27 (Jul-27) | B8: 10/1/26 | C8: 0.41 | D8: 4 | E8: 0.38 | F8: 0.44
A9: S&P Global MI via StockAnalysis: published FY27 EPS consensus (Jul-27) | B9: updated 9/25/26 | C9: 1.62 | D9: 9 | E9: 1.56 | F9: 1.67 | G9: Published FY27 EPS consensus. Public aggregate does not disclose exact ACV accounting treatment; we compare our ex-ACV estimate to isolate the core operating thesis.
A10: Zacks: FY27 (Jul-27) | B10: 10/1/26 | C10: 1.65 | D10: 5 | E10: 1.57 | F10: 1.7 | G10: Published FY27 EPS consensus; ACV treatment not disclosed
A11: Zacks: FY28 (Jul-28) | B11: 10/1/26 | C11: 1.81 | D11: 5 | E11: 1.72 | F11: 1.88
A12: Yahoo Finance: FY27 (staleness cross-check only; not used) | B12: 10/1/26 | C12: 1.75 | D12: 8 | E12: 1.62 | F12: 1.83 | G12: Not used to govern the pitch: includes pre-print estimates (30 days earlier $1.85); its quarterly row was a stale Q4-FY26 estimate.
A14: Our estimates vs consensus (base world W2)
A15: Comparison | B15: Ours ($/sh) | C15: Consensus | D15: Gap | G15: Note
A16: Q1 FY27 EPS vs Zacks | B16: =EPS_Build!B46 -> 0.36739041 | C16: =C5 -> 0.41 | D16: =B16/C16-1 -> -0.10392583 | G16: Q1 (Aug-Oct) precedes any ACV consolidation
A17: Q2 FY27 EPS ex-ACV vs Zacks | B17: =EPS_Build!C46 -> 0.33206111 | C17: =C6 -> 0.37 | D17: =B17/C17-1 -> -0.10253754
A18: FY27 EPS ex-ACV vs published FY27 consensus (S&P Global) | B18: =EPS_Build!$F$46 -> 1.4520874 | C18: =C9 -> 1.62 | D18: =B18/C18-1 -> -0.10364974 | G18: Core operating thesis comparison
A19: FY27 EPS ex-ACV vs Zacks FY27 | B19: =EPS_Build!$F$46 -> 1.4520874 | C19: =C10 -> 1.65 | D19: =B19/C19-1 -> -0.11994702
A20: FY27 GAAP EPS incl. modeled ACV vs S&P Global | B20: =EPS_Build!$F$49 -> 1.3829887 | C20: =C9 -> 1.62 | D20: =B20/C20-1 -> -0.14630326 | G20: Team ACV estimate (amortization, forgone interest, close mid-Q2); company guides EPS-neutral in the first full year
A21: FY28 EPS incl. ACV vs Zacks FY28 | B21: =Valuation!C14 -> 1.6305834 | C21: =C11 -> 1.81 | D21: =B21/C21-1 -> -0.099125188 | G21: FY28 = standalone + explicit ACV contribution

Sheet Catalysts
A1: Catalyst path and falsification
A3: Catalysts (3-12 month horizon; planned exit and valuation date mid-Feb 2027, after Q2 FY27)
A4: Date | B4: Event | C4: What investors learn | D4: Supports | E4: Source
A5: Oct 7, 2026 | B5: ACV tender offer expiry (extended) | C5: Whether a majority tenders (47.8% at 9/30). A tender result is not the close; company guides close by CY-end 2026. | D5: Neutral / secondary | E5: Schedule TO-T/A filed 10/1/26 (SEC)
A6: Oct 13, 2026 | B6: HSR waiting period expiry (refiled 9/28) | C6: Whether antitrust review extends (Second Request). Not a close date. | D6: Neutral / secondary | E6: Schedule TO-T/A filed 9/29/26 (SEC)
A7: Early Nov 2026 (estimated) | B7: RB Global Q3-26 | C7: First full-quarter read-through on IAA automotive units after its partner expansion | D7: Short if IAA units strong | E7: RB Global Q2-26 call (secondary transcript)
A8: Mid-Nov 2026 (estimated) | B8: CPRT Q1 FY27 results | C8: First full quarter of the lost-customer volume at its full run-rate; key read-throughs are U.S. insurance units, OpEx/car and U.S. operating margin. | D8: Primary discovery event | E8: Team estimate of timing
A9: Mid-Feb 2027 (estimated) | B9: CPRT Q2 FY27 results | C9: Second full quarter of lost volume plus the first ACV GAAP contribution (model assumes closing during Q2 FY27; company guidance is close by calendar year-end 2026). Planned exit and valuation date. | D9: Short; planned exit | E9: Team estimate of timing
A11: Falsification thresholds (Q1 FY27) - exit and reassess if any is met
A12: KPI | B12: Threshold | C12: Our base (W2, Q1) | E12: Basis
A13: U.S. insurance units y/y | B13: -0.06 | C13: =EPS_Build!B32 -> -0.12 | E13: Better than −6% means the lost volume is being offset
A14: Consolidated operating margin, ex-ACV | B14: 0.36 | C14: =EPS_Build!B43 -> 0.34108031 | E14: ≥36% means cost absorption is not happening (yr-ago Q1 37%)
A15: OpEx per car growth y/y | B15: 0.03 | E15: ≤ +3% means fast cost cuts (Q4-FY26 +12.7%, CEO; U.S. facility cost per unit +14.2%, CFO; Q4 call)

Sheet Sources
A1: Sources: Audit Ledger
A2: Source types: Primary | Secondary consensus | Secondary transcript | Secondary market data | Derived | Team estimate. SEC links: https://www.sec.gov/Archives/edgar/data/<CIK>/<accession without dashes>/ (CPRT CIK 900075; ACV CIK 1637873).
A4: No. | B4: Datapoint | C4: Value | D4: Source | E4: Source type | F4: Date | G4: Link / SEC accession | H4: Notes
A5: 1 | B5: FY26 revenue, segment P&L, Q4 derivation | C5: Revenue $4.67bn; U.S. service $3,388m | D5: Copart FY26 Form 10-K, segment note | E5: Primary | F5: 9/29/26 | G5: 10-K, accession 0001193125-26-405731: https://www.sec.gov/Archives/edgar/data/900075/000119312526405731/cprt-20260731.htm | H5: Q4 = FY less Q1-Q3 10-Qs
A6: 2 | B6: FY26 quarterly segment data (Q1-Q3) | C6: See Inputs | D6: Copart Form 10-Q filings, Q1-Q3 FY26 | E6: Primary | F6: 11/24/25; 3/3/26; 5/29/26 | G6: 10-Q accessions 0001193125-25-291660; 0001193125-26-088593; 0001193125-26-245578
A7: 3 | B7: Diluted weighted-average shares | C7: 932.1m (Q4 FY26); 956.9m (FY26); Q1-Q3 977.1m / 975.1m / 942.8m | D7: Copart Q4 FY26 earnings release (8-K Ex. 99.1); 10-Q XBRL | E7: Primary | F7: 9/10/26 | G7: 8-K, accession 0001193125-26-387902: https://www.sec.gov/Archives/edgar/data/900075/000119312526387902/cprt-ex99_1.htm | H7: Model uses 932m (v1 used 940m)
A8: 4 | B8: Shares outstanding; FY26 buybacks | C8: 926.3m (9/25/26); 43.4m shares / $1.63bn repurchased in FY26; 282m authorized remaining | D8: Copart FY26 Form 10-K (cover; Item 5; MD&A) | E8: Primary | F8: 9/29/26 | G8: 10-K, accession 0001193125-26-405731 | H8: Buyback risk in Sensitivity
A9: 5 | B9: Effective tax rate | C9: 19.3% | D9: Copart FY26 Form 10-K | E9: Primary | F9: 9/29/26 | G9: 10-K, accession 0001193125-26-405731 | H9: Model uses 19.5%
A10: 6 | B10: Cash, equivalents, restricted cash + HTM securities | C10: $1,907.9m + $2,581.9m = $4.49bn | D10: Copart FY26 Form 10-K, balance sheet | E10: Primary | F10: 9/29/26 | G10: 10-K, accession 0001193125-26-405731
A11: 7 | B11: Operating cash flow; capex | C11: $1,604.5m; $337.4m | D11: Copart FY26 Form 10-K, cash flow statement | E11: Primary | F11: 9/29/26 | G11: 10-K, accession 0001193125-26-405731 | H11: FY26 FCF $1.27bn
A12: 8 | B12: Interest income FY26 | C12: $181.9m | D12: Copart FY26 Form 10-K, segment note | E12: Primary | F12: 9/29/26 | G12: 10-K, accession 0001193125-26-405731
A13: 9 | B13: Q4 FY26 revenue / diluted EPS; equity | C13: $1.152bn / $0.35; equity $9,097m | D13: Copart Form 8-K Ex. 99.1 (earnings release) | E13: Primary | F13: 9/10/26 | G13: 8-K, accession 0001193125-26-387902
A14: 10 | B14: Q4 domestic insurance assignments; ex-one-customer | C14: −7.5%; +2.3% | D14: Copart Q4 FY26 earnings-call transcript (Schedule TO-C, Ex. 99.2) | E14: Primary — SEC-filed earnings-call transcript, Ex. 99.2 | F14: 9/10/26 call; filed 9/11/26 | G14: SC TO-C, accession 0001193125-26-388383: https://www.sec.gov/Archives/edgar/data/900075/000119312526388383/d138398dex992.htm | H14: Basis of the 9.8-pt drag (Inputs)
A15: 11 | B15: OpEx per car; U.S. facility costs; total-loss frequency | C15: +12.7% (CEO); +7.7% (+14.2% per unit, CFO); 23.3%, highest second quarter on record (CY Q2-26) | D15: Copart Q4 FY26 earnings-call transcript (Schedule TO-C, Ex. 99.2) | E15: Primary — SEC-filed earnings-call transcript, Ex. 99.2 | F15: 9/10/26 call; filed 9/11/26 | G15: SC TO-C, accession 0001193125-26-388383
A16: 12 | B16: ACV close timing and EPS effect (management) | C16: Close by end of calendar year 2026; breakeven in the first year, accretive FY28 | D16: Copart FY26 Form 10-K (Note 19; MD&A); Q4 FY26 call transcript | E16: Primary | F16: 9/29/26; 9/10/26 | G16: 10-K, accession 0001193125-26-405731; SC TO-C accession 0001193125-26-388383 (Ex. 99.2) | H16: Close date is a team assumption (mid-Q2)
A17: 13 | B17: RB Global partner expansion | C17: Incremental volume from its largest automotive-insurance partner had been transitioning over roughly the prior 90 days as of Aug. 4, following expansion to all 50 states | D17: RB Global Q2-26 earnings call (transcript) | E17: Secondary transcript | F17: 8/4/26 | G17: The Motley Fool transcript; RB Global IR: investor.rbglobal.com | H17: Carrier identity not disclosed; not used in formulas
A18: 14 | B18: ACV transaction | C18: $10.50/sh cash; ~$1.9bn equity value | D18: Copart Form 8-K (deal announcement, Ex. 99.1); Schedule TO-T | E18: Primary | F18: 9/10/26; 9/17/26 | G18: 8-K accession 0001193125-26-388064; SC TO-T accession 0001193125-26-393827
A19: 15 | B19: ACV EPS guidance (company; inconsistent across materials) | C19: Formal transaction announcement: neutral to EPS in the first full year of ownership and accretive in FY2028 and beyond. Subsequent Q4 earnings-call language indicated first-full-year accretion. Model conservatively governs off the formal transaction announcement. | D19: Copart 8-K Ex. 99.1 / 99.2 (deal announcement); Q4 FY26 call transcript (SC TO-C Ex. 99.2) | E19: Primary | F19: 9/10/26; 9/11/26 | G19: 8-K accession 0001193125-26-388064; SC TO-C accession 0001193125-26-388383 | H19: Modeled FY27 ACV impact and FY28 contribution are team estimates
A20: 16 | B20: ACV acquired net cash | C20: $242.3m cash − $205.0m line of credit = +$37.3m (6/30/26) | D20: ACV Auctions Form 10-Q (Q2-26), XBRL | E20: Primary | F20: 8/10/26 | G20: ACV 10-Q accession 0001637873-26-000034 | H20: ACV acquired net cash is not explicitly modeled in horizon cash; June-30 ACV net cash was approximately +$37m before subsequent changes, an impact of < $0.05/share.
A21: 17 | B21: ACV tender status | C21: 47.78% tendered; expiry extended to 10/7/26 | D21: Schedule TO-T/A | E21: Primary | F21: 10/1/26 | G21: SC TO-T/A, accession 0001193125-26-409871
A22: 18 | B22: HSR status | C22: Refiled 9/28; waiting period expected to expire 10/13/26 | D22: Schedule TO-T/A | E22: Primary | F22: 9/29/26 | G22: SC TO-T/A, accession 0001193125-26-406039
A23: 19 | B23: ACV TTM financials | C23: Revenue $801m; operating loss −$57m (TTM to Q2-26) | D23: ACV Auctions Form 10-K (FY25) and Form 10-Q (Q2-26), XBRL | E23: Primary | F23: 2/23/26; 8/10/26 | G23: ACV 10-K accession 0001637873-26-000011; 10-Q accession 0001637873-26-000034
A24: 20 | B24: 10-year Treasury yield | C24: 5.24% | D24: U.S. Treasury Daily Par Yield Curve Rates | E24: Primary | F24: 10/1/26 | G24: home.treasury.gov/resource-center/data-chart-center/interest-rates (Daily Treasury Par Yield Curve Rates, 2026)
A25: 21 | B25: Manheim Used Vehicle Value Index | C25: −0.4% y/y, mid-September | D25: Cox Automotive, Manheim mid-month release | E25: Secondary market data | F25: Sep 2026 | G25: coxautoinc.com/market-insights (Manheim Used Vehicle Value Index) | H25: Qualitative support only; not in formulas
A26: 22 | B26: Consensus EPS (quarterly, FY27, FY28) | C26: See Consensus sheet | D26: Zacks via Nasdaq | E26: Secondary consensus | F26: 10/1/26; re-verified 10/2/26 | G26: nasdaq.com/market-activity/stocks/cprt/earnings (data: api.nasdaq.com/api/analyst/CPRT/earnings-forecast) | H26: Zacks estimates as of 10/1/26; re-verified 10/2/26.
A27: 23 | B27: Share price | C27: $27.29 | D27: Yahoo Finance daily close | E27: Secondary market data | F27: 10/1/26 | G27: finance.yahoo.com/quote/CPRT/history
A28: 24 | B28: Published FY27 EPS consensus | C28: $1.62 (n=9; range $1.56-$1.67) | D28: S&P Global Market Intelligence via StockAnalysis | E28: Secondary consensus | F28: updated 9/25/26 | G28: stockanalysis.com/stocks/cprt/forecast/ (verified 10/2/26) | H28: Exact ACV treatment not disclosed
A29: 25 | B29: Consensus EPS FY27 (cross-check) | C29: $1.75 (n=8) | D29: Yahoo Finance | E29: Secondary consensus | F29: 10/1/26 | G29: finance.yahoo.com/quote/CPRT/analysis | H29: Staleness cross-check only; not used
A30: 26 | B30: Sell-side commentary | C30: Loss 'temporary'; further near-term declines | D30: HSBC note as reported by Investing.com | E30: Secondary consensus | F30: 9/17/26 | G30: Investing.com news summary of the HSBC note (named secondary source) | H30: Context only; not in formulas
A31: 27 | B31: Core ROIC; net-income CAGR | C31: ~29% (FY26), ~31% (FY25); FY21-FY26 CAGR ~9.7% | D31: Team calculation from 10-K / 8-K data and SEC XBRL | E31: Derived | F31: 10/2/26 | G31: data.sec.gov/api/xbrl/companyfacts/CIK0000900075.json | H31: ROIC = operating income × (1 − tax) / (equity − cash − HTM)
A32: 28 | B32: Scenario drivers, probabilities, ROIC, growth, FY28 ACV | C32: See Scenarios | D32: Team model | E32: Team estimate | F32: 10/2/26 | G32: This workbook (Scenarios) | H32: Rationale rows on Scenarios
A33: 29 | B33: Operating structure; horizon cash | C33: See Inputs | D33: Team model (basis on Inputs) | E33: Team estimate | F33: 10/2/26 | G33: This workbook (Inputs)
A34: 30 | B34: Beta 0.90; ERP 5%; terminal growth 3% | C34: See Inputs | D34: Team model (basis on Inputs) | E34: Team estimate | F34: 10/2/26 | G34: This workbook (Inputs)
A35: 31 | B35: DOJ AML investigation | C35: Ongoing investigation; potential outcome/loss not estimable | D35: Copart FY26 Form 10-K (Note 15 Commitments and Contingencies; Item 1A) | E35: Primary | F35: 9/29/26 | G35: 10-K, accession 0001193125-26-405731 | H35: Known legal/regulatory overhang; not modeled in thesis or valuation.
A36: 32 | B36: Company scale | C36: 286 operating facilities; ~1 million members in 185+ countries; 4 million+ vehicles sold a year | D36: Copart FY26 Form 10-K (Item 2 Properties); 8-K Ex. 99.1 (About Copart); Q4 FY26 call transcript (SC TO-C Ex. 99.2) | E36: Primary | F36: 9/29/26; 9/10/26 | G36: 10-K accession 0001193125-26-405731; 8-K accession 0001193125-26-387902; SC TO-C accession 0001193125-26-388383 | H36: Memo cites 286 facilities (10-K)
A37: 33 | B37: Trailing P/E and price de-rating | C37: ~18x trailing P/E vs ~35x 2021-26 median; price −40% from 52-week high ($45.76, 10/21/25) | D37: Team calculation from Yahoo Finance prices and SEC XBRL EPS | E37: Derived | F37: 10/1/26 | G37: data.sec.gov companyfacts; finance.yahoo.com/quote/CPRT/history | H37: Supports 'the stock has already de-rated materially'
A38: 34 | B38: Post-earnings-reaction study | C38: Full sample (governing): 3M mean excess +4.5% / +5.6% / +6.3% (n = 22 / 13 / 9) | D38: Team backtest (point-in-time) | E38: Team estimate | F38: 10/2/26 | G38: This workbook (Checks: study design and results) | H38: Basis for the planned exit after Q2

Sheet Checks
A1: Model Checks
A3: Calibration: zero-growth replay of FY26 vs reported diluted EPS (FY26 quarterly diluted shares)
A4: Quarter | B4: Q1 | C4: Q2 | D4: Q3 | E4: Q4 | F4: FY26
A5: Model replay ($/sh) | B5: =((Inputs!B$47+Inputs!B$48-Inputs!B$50-Inputs!B$49-Inputs!B$51)+Inputs!B$52+Inputs!B$54)*(1-Inputs!$B$8)/Inputs!B$57 -> 0.39883379 | C5: =((Inputs!C$47+Inputs!C$48-Inputs!C$50-Inputs!C$49-Inputs!C$51)+Inputs!C$52+Inputs!C$54)*(1-Inputs!$B$8)/Inputs!C$57 -> 0.36217157 | D5: =((Inputs!D$47+Inputs!D$48-Inputs!D$50-Inputs!D$49-Inputs!D$51)+Inputs!D$52+Inputs!D$54)*(1-Inputs!$B$8)/Inputs!D$57 -> 0.42956672 | E5: =((Inputs!E$47+Inputs!E$48-Inputs!E$50-Inputs!E$49-Inputs!E$51)+Inputs!E$52+Inputs!E$54)*(1-Inputs!$B$8)/Inputs!E$57 -> 0.35279745 | F5: =SUM(B5:E5) -> 1.5433695
A6: Reported ($/sh) | B6: =Inputs!B$56 -> 0.41 | C6: =Inputs!C$56 -> 0.36 | D6: =Inputs!D$56 -> 0.43 | E6: =Inputs!E$56 -> 0.35 | F6: =SUM(B6:E6) -> 1.55
A7: Difference ($/sh) | B7: =B5-B6 -> -0.011166206 | C7: =C5-C6 -> 0.0021715721 | D7: =D5-D6 -> -0.00043328384 | E7: =E5-E6 -> 0.0027974466 | F7: =SUM(B7:E7) -> -0.0066304712
A8: Model excludes certain other income / FX / NCI items; FY26 replay differs from reported EPS by approximately $0.01/share (~0.4%; F7).
A10: Integrity
A11: Scenario probabilities sum to 100% | B11: =IF(ABS(Scenarios!B18-1)<0.0001,"OK","CHECK") -> OK
A12: Cost of equity exceeds terminal growth, base and stress | B12: =IF(AND(Inputs!$B$34>Inputs!$B$32,Inputs!$B$35>Inputs!$B$32),"OK","CHECK") -> OK
A13: Sensitivity engine base case = Valuation W2 value | B13: =IF(ABS(Sensitivity!$M$77-Valuation!C42)<0.000001,"OK","CHECK") -> OK
A14: Sensitivity engine base FY27 EPS = EPS_Build W2 | B14: =IF(ABS(Sensitivity!$J$77-EPS_Build!$F$46)<0.000001,"OK","CHECK") -> OK
A15: EPS bridge ends at EPS_Build W2 FY27 EPS ex-ACV | B15: =IF(ABS(EPS_Build!$J$113-EPS_Build!$F$46)<0.000001,"OK","CHECK") -> OK
A16: Displayed bridge (memo, $0.01) sums exactly | B16: =IF(ABS(ROUND(EPS_Build!$B$117,2)+ROUND(EPS_Build!$B$118,2)+ROUND(EPS_Build!$B$119,2)+ROUND(EPS_Build!$B$120,2)+ROUND(EPS_Build!$B$121,2)+ROUND(EPS_Build!$B$122,2)-ROUND(EPS_Build!$B$123,2))<0.0001,"OK","CHECK") -> OK
A17: FY27 GAAP EPS = ex-ACV EPS + ACV impact (all worlds) | B17: =IF(ABS(Valuation!B11-Valuation!B9-Valuation!B10)+ABS(Valuation!C11-Valuation!C9-Valuation!C10)+ABS(Valuation!D11-Valuation!D9-Valuation!D10)+ABS(Valuation!E11-Valuation!E9-Valuation!E10)<0.000001,"OK","CHECK") -> OK
A18: Lost-customer reconciliation: W2 share in Q4 FY26 base between 0% and 100% | B18: =IF(AND(Inputs!$B$24>0,Inputs!$B$24<=1),"OK","CHECK") -> OK
A19: ACV consolidated share of Q2 between 0% and 100% | B19: =IF(AND(Inputs!$B$16>=0,Inputs!$B$16<=1),"OK","CHECK") -> OK
A20: Payout ratios valid: year-1 and normalized payouts between 0% and 100%, all worlds | B20: =IF(AND(MIN(Valuation!B35:E35,Valuation!B36:E36)>0,MAX(Valuation!B35:E35,Valuation!B36:E36)<=1),"OK","CHECK") -> OK
A21: Growth below incremental ROIC (year-1 g1 and normalized g), all worlds | B21: =IF(AND(MAX(Valuation!B26-Valuation!B32,Valuation!C26-Valuation!C32,Valuation!D26-Valuation!D32,Valuation!E26-Valuation!E32)<0,MAX(Valuation!B31-Valuation!B32,Valuation!C31-Valuation!C32,Valuation!D31-Valuation!D32,Valuation!E31-Valuation!E32)<0),"OK","WARNING") -> OK
A22: Waterfall ties: FY26 EPS + bridge = FY27 ex-ACV; + ACV impact = FY27 GAAP (W2) | B22: =IF(AND(ABS(EPS_Build!$C$122-EPS_Build!$F$46)<0.000001,ABS(EPS_Build!$C$124-EPS_Build!$F$49)<0.000001),"OK","CHECK") -> OK
A24: Post-earnings-reaction study (holding-period discipline)
A25: Sample period | B25: Governing: all CPRT earnings releases Sep 2004 - Sep 2026 (89 releases), COVID period included. Robustness: excludes Feb 2020 - Jun 2023. The 9/10/26 release has no forward window yet.
A26: Event definition | B26: 2-day excess reaction vs SPY, close(t+1) / close(t−1), around the earnings-release 8-K date; a price reaction, not an EPS miss vs consensus
A27: Thresholds tested | B27: Excess reaction ≤ −3%, ≤ −5%, ≤ −7%
A28: Benchmark / forward window | B28: SPY; excess return from the close of day t+1 over 21 / 63 / 126 trading days (1M / 3M / 6M); 3M governs
A29: Source | B29: Team backtest (scripts/backtest.py); prices: Yahoo Finance; dates: SEC 8-K filing dates
A31: Governing: full sample (incl. COVID)
A32: Threshold (2-day excess) | B32: Events | C32: n (with 3M) | D32: 1M mean | E32: 3M mean | F32: 3M median | G32: 3M hit rate
A33: ≤ −3% | B33: 23 | C33: 22 | D33: -0.0062 | E33: 0.0448 | F33: 0.0318 | G33: 0.7273
A34: ≤ −5% | B34: 14 | C34: 13 | D34: -0.0134 | E34: 0.0564 | F34: 0.0628 | G34: 0.7692
A35: ≤ −7% | B35: 9 | C35: 9 | D35: -0.0225 | E35: 0.0629 | F35: 0.0308 | G35: 0.7778
A37: Robustness only: ex-COVID (Feb 2020 - Jun 2023 excluded)
A38: Threshold (2-day excess) | B38: Events | C38: n (with 3M) | D38: 1M mean | E38: 3M mean | F38: 3M median | G38: 3M hit rate
A39: ≤ −3% | B39: 22 | C39: 21 | D39: -0.0038 | E39: 0.0461 | F39: 0.0328 | G39: 0.7143
A40: ≤ −5% | B40: 13 | C40: 12 | D40: -0.0099 | E40: 0.0596 | F40: 0.0667 | G40: 0.75
A41: ≤ −7% | B41: 8 | C41: 8 | D41: -0.0183 | E41: 0.0685 | F41: 0.0525 | G41: 0.75
A42: Full-sample 6M mean excess: +3.6% / +4.3% / +4.1%. Positive 3M drift after large negative reactions in both samples argues against holding the short past Q2.
